Workbook

Sheet About
A1: BObIC BAU Output by ISIC Code
A3: Source: | B3: Most Industries
B4: OECD
B5: 2018
B6: Input-Output Tables 2018 Edition (ISIC Rev. 4)
B7: https://stats.oecd.org/Index.aspx?DataSetCode=IOTSI4_2018
B8: Variable: TTL
B10: ISIC Code Splits and IO-matrix
B11: National Account System (SCN) version 2010
B12: Current Employment Statistics - 2015
B13: https://ftp.ibge.gov.br/Contas_Nacionais/Matriz_de_Insumo_Produto/2015/Matriz_de_Insumo_Produto_2015_Nivel_67.xls
B14: Gross Output by Industry
B15: Underlying Detail: Gross Output by Industry
B16: Components of Value Added
A18: Notes
A19: The output of each domestic industry can be found in the columns (where the ISIC codes
A20: are prefixed with "D" for domestic). This output is in the total row and is equal to the
A21: inputs the industry buys plus the value added and taxes (less subsidies) paid.
A23: We divide up various ISIC codes that need to be disaggregated in the EPS using data
A24: from BLS and BEA publications for the U.S. Data for various other countries that can
A25: help with some of these splits, such as chemicals (ISIC 20) and pharmaceuticals (ISIC 21),
A26: can be found in the OECD's "STAN Database for Structural Analysis," variable EMPN, at:
A27: https://stats.oecd.org/Index.aspx?DataSetCode=STANI4_2020
A29: We convert 2015 USD to 2012 USD with the following conversion factor:
A30: 0.96868157 | B30: 2012 USD per 2015 USD

Sheet OECD TTL
A1: =DotStatQuery(B1) -> #NAME? | B1: Sorry, the query is too large to fit into the Excel cell. You will not be able to update your table with the .Stat Populator.
A2: Dataset: Input-Output Tables 2018 edition
A3: Variable | C3: TTL: Total
A4: Country | C4: USA: United States
A5: Time | C5: 2015
A6: Unit | C6: US Dollar, Millions
A7: To: (sector in column) | C7: D01T03: Agriculture, forestry and fishing | D7: D05T06: Mining and extraction of energy producing products | E7: D07T08: Mining and quarrying of non-energy producing products | F7: D09: Mining support service activities | G7: D10T12: Food products, beverages and tobacco | H7: D13T15: Textiles, wearing apparel, leather and related products | I7: D16: Wood and products of wood and cork | J7: D17T18: Paper products and printing | K7: D19: Coke and refined petroleum products | L7: D20T21: Chemicals and pharmaceutical products | M7: D22: Rubber and plastic products | N7: D23: Other non-metallic mineral products | O7: D24: Basic metals | P7: D25: Fabricated metal products | Q7: D26: Computer, electronic and optical products | R7: D27: Electrical equipment | S7: D28: Machinery and equipment, nec | T7: D29: Motor vehicles, trailers and semi-trailers | U7: D30: Other transport equipment | V7: D31T33: Other manufacturing; repair and installation of machinery and equipment | W7: D35T39: Electricity, gas, water supply, sewerage, waste and remediation services | X7: D41T43: Construction | Y7: D45T47: Wholesale and retail trade; repair of motor vehicles | Z7: D49T53: Transportation and storage | AA7: D55T56: Accomodation and food services | AB7: D58T60: Publishing, audiovisual and broadcasting activities | AC7: D61: Telecommunications | AD7: D62T63: IT and other information services | AE7: D64T66: Financial and insurance activities | AF7: D68: Real estate activities | AG7: D69T82: Other business sector services | AH7: D84: Public admin. and defence; compulsory social security | AI7: D85: Education | AJ7: D86T88: Human health and social work | AK7: D90T96: Arts, entertainment, recreation and other service activities | AL7: D97T98: Private households with employed persons | AM7: HFCE: Final consumption expenditure of households | AN7: NPISH: Final consumption expenditure of non-profit institutions serving households | AO7: GGFC: Final consumption expenditure of general government | AP7: GFCF: Gross Fixed Capital Formation | AQ7: INVNT: Changes in inventories | AR7: CONS_ABR: Direct purchases abroad by residents (imports) | AS7: CONS_NONRES: Direct purchases by non-residents (exports) | AT7: EXPO: Exports (cross border) | AU7: IMPO: Imports (cross border)
A8: From: (sector in row)
A9: TTL_01T03: Agriculture, forestry and fishing | C9: 67012.6 | D9: 103.4 | E9: 27.2 | F9: 10.2 | G9: 221344.9 | H9: 2197.8 | I9: 8765.8 | J9: 3937.3 | K9: 15.7 | L9: 5128.2 | M9: 227.7 | N9: 21.9 | O9: 138.5 | P9: 41.4 | Q9: 3.5 | R9: 4.4 | S9: 25.6 | T9: 32.2 | U9: 18.3 | V9: 940 | W9: 113.8 | X9: 1771.8 | Y9: 3999.1 | Z9: 79.6 | AA9: 2242.4 | AB9: 23.8 | AC9: 14.9 | AD9: 63.3 | AE9: 55.4 | AF9: 314.2 | AG9: 3992.7 | AH9: 2090.4 | AI9: 693.9 | AJ9: 1735.3 | AK9: 1363.9 | AL9: 0 | AM9: 109689.9 | AN9: 2166.8 | AO9: 71 | AP9: 633.4 | AQ9: -143.5 | AR9: 1165.6 | AS9: 1920.1 | AT9: 49518.6 | AU9: -37816
A10: TTL_05T06: Mining and extraction of energy producing products | C10: 2211.3 | D10: 20554 | E10: 4843.5 | F10: 7971.8 | G10: 8068.1 | H10: 74.5 | I10: 73.8 | J10: 463.7 | K10: 251591.7 | L10: 27125 | M10: 151.2 | N10: 779.4 | O10: 9613.2 | P10: 104.6 | Q10: 16.4 | R10: 30.7 | S10: 237.6 | T10: 121.8 | U10: 418.4 | V10: 308.3 | W10: 41877.5 | X10: 944.4 | Y10: 670.7 | Z10: 7094.5 | AA10: 277.5 | AB10: 90.5 | AC10: 416.6 | AD10: 110.3 | AE10: 361.3 | AF10: 229.7 | AG10: 5912 | AH10: 20054.8 | AI10: 382.4 | AJ10: 2687.8 | AK10: 3577 | AL10: 0 | AM10: 9940.1 | AN10: 120 | AO10: 10.4 | AP10: 5733.6 | AQ10: 371 | AR10: 63.2 | AS10: 69.8 | AT10: 18940.2 | AU10: -161022.9
A11: TTL_07T08: Mining and quarrying of non-energy producing products | C11: 551.1 | D11: 1199.9 | E11: 836.4 | F11: 726.5 | G11: 671.5 | H11: 34.2 | I11: 37.4 | J11: 500.6 | K11: 1531.1 | L11: 7190.3 | M11: 151.3 | N11: 6349.6 | O11: 17808.5 | P11: 1513 | Q11: 122.1 | R11: 301.6 | S11: 475.3 | T11: 353.5 | U11: 157.9 | V11: 804.3 | W11: 491.7 | X11: 10451.8 | Y11: 666.5 | Z11: 353.8 | AA11: 65.5 | AB11: 6.9 | AC11: 16.9 | AD11: 9.8 | AE11: 23.1 | AF11: 1466.3 | AG11: 605.2 | AH11: 1388.6 | AI11: 37.7 | AJ11: 163.5 | AK11: 195.5 | AL11: 0 | AM11: 1205.7 | AN11: 1.5 | AO11: 6.5 | AP11: 7905.1 | AQ11: 56.9 | AR11: 16.5 | AS11: 3.8 | AT11: 6342.5 | AU11: -7908.2
A12: TTL_09: Mining support service activities | C12: 3070.6 | D12: 27907.3 | E12: 9294 | F12: 15182.3 | G12: 10156.8 | H12: 2.9 | I12: 5.4 | J12: 11.9 | K12: 436.8 | L12: 4431.8 | M12: 13.2 | N12: 7.3 | O12: 1083.5 | P12: 48.5 | Q12: 7.4 | R12: 9 | S12: 34 | T12: 60.3 | U12: 106.5 | V12: 11.9 | W12: 537.9 | X12: 95.1 | Y12: 28.5 | Z12: 27.5 | AA12: 16.2 | AB12: 3.7 | AC12: 8.6 | AD12: 7.3 | AE12: 7.3 | AF12: 65.2 | AG12: 5618.6 | AH12: 87.5 | AI12: 4.4 | AJ12: 17.5 | AK12: 148.3 | AL12: 0 | AM12: 180.1 | AN12: 0.6 | AO12: 0.3 | AP12: 7591.1 | AQ12: 24.9 | AR12: 4.6 | AS12: 0.9 | AT12: 2983.2 | AU12: -1554.4
A13: TTL_10T12: Food products, beverages and tobacco | C13: 32898.8 | D13: 40.2 | E13: 20 | F13: 21.7 | G13: 109205.7 | H13: 627 | I13: 263.5 | J13: 1915.2 | K13: 514.4 | L13: 9607.9 | M13: 1679.5 | N13: 244.7 | O13: 271 | P13: 390.2 | Q13: 180.3 | R13: 151 | S13: 398.5 | T13: 888.1 | U13: 394.5 | V13: 537.1 | W13: 494.6 | X13: 1400.9 | Y13: 14772.9 | Z13: 935.8 | AA13: 103985.8 | AB13: 328.8 | AC13: 172.6 | AD13: 201.8 | AE13: 545.3 | AF13: 1336.6 | AG13: 4232 | AH13: 16752.1 | AI13: 2774.9 | AJ13: 20849.1 | AK13: 6603.2 | AL13: 0 | AM13: 601442.9 | AN13: 9711.3 | AO13: 367.5 | AP13: 983.8 | AQ13: 227.1 | AR13: 4374.2 | AS13: 7370.3 | AT13: 60181.5 | AU13: -84486.2
A14: TTL_13T15: Textiles, wearing apparel, leather and related products | C14: 356 | D14: 59.9 | E14: 28.6 | F14: 27 | G14: 587.9 | H14: 11850.3 | I14: 629.6 | J14: 2131.7 | K14: 65.5 | L14: 2129.7 | M14: 2063.9 | N14: 270.7 | O14: 93 | P14: 188.1 | Q14: 149.5 | R14: 70.8 | S14: 647 | T14: 4312.8 | U14: 948.4 | V14: 5590.7 | W14: 268.6 | X14: 1482.6 | Y14: 7163.8 | Z14: 925.7 | AA14: 989.3 | AB14: 187.2 | AC14: 93.8 | AD14: 165.7 | AE14: 348.9 | AF14: 237.2 | AG14: 2377.2 | AH14: 5265.9 | AI14: 419 | AJ14: 5415.3 | AK14: 2442 | AL14: 0 | AM14: 158748.2 | AN14: 685.7 | AO14: 39.3 | AP14: 582.3 | AQ14: 111.9 | AR14: 2363.9 | AS14: 1232.9 | AT14: 8336.8 | AU14: -145065.5
A15: TTL_16: Wood and of products of wood and cork (except furniture) | C15: 745.1 | D15: 160.4 | E15: 72.2 | F15: 20.6 | G15: 800.4 | H15: 119.2 | I15: 19684.7 | J15: 4820.8 | K15: 8.5 | L15: 1218.7 | M15: 1232 | N15: 304.4 | O15: 144.4 | P15: 485.4 | Q15: 128.7 | R15: 248.2 | S15: 666.3 | T15: 2950 | U15: 730.9 | V15: 16448.9 | W15: 596 | X15: 25108.9 | Y15: 3051.1 | Z15: 683.7 | AA15: 3177.4 | AB15: 237.3 | AC15: 126.3 | AD15: 182.2 | AE15: 130.7 | AF15: 4479 | AG15: 3878.4 | AH15: 3127.4 | AI15: 259.4 | AJ15: 934.3 | AK15: 1878.6 | AL15: 0 | AM15: 7780.5 | AN15: 1.7 | AO15: 1.2 | AP15: 2066 | AQ15: 262.9 | AR15: 163.2 | AS15: 205 | AT15: 6289.2 | AU15: -16997.3
A16: TTL_17T18: Paper products and printing | C16: 864.6 | D16: 66.5 | E16: 71 | F16: 27.3 | G16: 12726.7 | H16: 1812.7 | I16: 823.2 | J16: 44981.7 | K16: 99 | L16: 6696.4 | M16: 5593.8 | N16: 1260.7 | O16: 835.3 | P16: 2908.9 | Q16: 576.1 | R16: 849.7 | S16: 1956.1 | T16: 4846 | U16: 1323.8 | V16: 3070.3 | W16: 1840.6 | X16: 4572.1 | Y16: 13367.7 | Z16: 3235.1 | AA16: 7034.1 | AB16: 8316.5 | AC16: 2382 | AD16: 3109.5 | AE16: 5304.1 | AF16: 833.1 | AG16: 18660.2 | AH16: 15413.6 | AI16: 2882.5 | AJ16: 10312.3 | AK16: 6483.5 | AL16: 0 | AM16: 64058.7 | AN16: 49.6 | AO16: 17 | AP16: 1888.5 | AQ16: 229.8 | AR16: 471.1 | AS16: 1161.8 | AT16: 30004.1 | AU16: -23813.7
A17: TTL_19: Coke and refined petroleum products | C17: 10126.4 | D17: 507.6 | E17: 704 | F17: 382.5 | G17: 4523.9 | H17: 312 | I17: 593.6 | J17: 3180.1 | K17: 4852.4 | L17: 25880 | M17: 1423.5 | N17: 735.6 | O17: 5591.2 | P17: 1167.1 | Q17: 155.1 | R17: 760.2 | S17: 1189.4 | T17: 859.8 | U17: 2349.5 | V17: 1421.2 | W17: 8364.7 | X17: 26306 | Y17: 3998.7 | Z17: 88382.6 | AA17: 2094.4 | AB17: 461.8 | AC17: 1605.7 | AD17: 1421.2 | AE17: 2337.4 | AF17: 3197.1 | AG17: 12335.1 | AH17: 56326.6 | AI17: 1594.6 | AJ17: 6481.2 | AK17: 5032.3 | AL17: 0 | AM17: 170851.7 | AN17: 4.1 | AO17: 43.8 | AP17: 590.7 | AQ17: 549.1 | AR17: 1039 | AS17: 2736.2 | AT17: 83383.3 | AU17: -55734.3
A18: TTL_20T21: Chemicals and pharmaceutical products | C18: 16289.2 | D18: 701.3 | E18: 348.3 | F18: 283 | G18: 7120.1 | H18: 5688.3 | I18: 2626.9 | J18: 10052.1 | K18: 7325.3 | L18: 106423 | M18: 36591.4 | N18: 3196.8 | O18: 5974.9 | P18: 6845.1 | Q18: 3214.2 | R18: 2538.4 | S18: 4774.9 | T18: 10886.4 | U18: 4495.4 | V18: 5131.6 | W18: 2171.9 | X18: 11890.3 | Y18: 10437.7 | Z18: 4685.4 | AA18: 2841.8 | AB18: 1813 | AC18: 1184.3 | AD18: 707.2 | AE18: 935.4 | AF18: 6011.6 | AG18: 13098.4 | AH18: 13024.2 | AI18: 2668.6 | AJ18: 82628.8 | AK18: 7452.8 | AL18: 0 | AM18: 395215.5 | AN18: 137.5 | AO18: 4681.7 | AP18: 7342.1 | AQ18: 1419.3 | AR18: 982.4 | AS18: 1918.4 | AT18: 136712.4 | AU18: -165140.7
A19: TTL_22: Rubber and plastics products | C19: 2124.5 | D19: 308.9 | E19: 210.7 | F19: 126.6 | G19: 12477.3 | H19: 1009.1 | I19: 812 | J19: 3584.7 | K19: 92.4 | L19: 8378.4 | M19: 16729.5 | N19: 1023.5 | O19: 1957.2 | P19: 3435.4 | Q19: 990.8 | R19: 1324.5 | S19: 7177.3 | T19: 27216.3 | U19: 7150.6 | V19: 5863.8 | W19: 1302.2 | X19: 21824.9 | Y19: 13765.2 | Z19: 7570.7 | AA19: 7206.4 | AB19: 496.8 | AC19: 1670.9 | AD19: 679.8 | AE19: 931.2 | AF19: 2515 | AG19: 7967.4 | AH19: 9488.3 | AI19: 2634.5 | AJ19: 11039.6 | AK19: 2576.5 | AL19: 0 | AM19: 52725.3 | AN19: 9.5 | AO19: 9.2 | AP19: 5435.4 | AQ19: 1005.3 | AR19: 55.5 | AS19: 61.4 | AT19: 27545.8 | AU19: -49527.3
A20: TTL_23: Other non-metallic mineral products | C20: 151.6 | D20: 102.1 | E20: 226.9 | F20: 142.9 | G20: 4353.9 | H20: 344 | I20: 1307.5 | J20: 651.9 | K20: 266.6 | L20: 3320 | M20: 2199.8 | N20: 14361.8 | O20: 1659.8 | P20: 1655.7 | Q20: 236.1 | R20: 1057.5 | S20: 1852.3 | T20: 7860.5 | U20: 1468.6 | V20: 1487.8 | W20: 745.7 | X20: 48327.7 | Y20: 1509 | Z20: 1133 | AA20: 4766.8 | AB20: 77.2 | AC20: 341.1 | AD20: 175.6 | AE20: 237.7 | AF20: 1423.6 | AG20: 3339.8 | AH20: 3768.1 | AI20: 658.6 | AJ20: 4558.4 | AK20: 1376.4 | AL20: 0 | AM20: 15837.2 | AN20: 5.4 | AO20: 10.6 | AP20: 1968.1 | AQ20: 136.4 | AR20: 28.4 | AS20: 17.7 | AT20: 10452.3 | AU20: -26110.4
... A49: OUTPUT: Output at basic prices | C49: 455757.4 | D49: 293671.1 | E49: 64889.3 | F49: 87786.1 | G49: 935808.4 | H49: 87018.8 | I49: 98613 | J49: 269203.3 | K49: 490118.1 | L49: 785327 | M49: 230983 | N49: 119491.4 | O49: 225243.7 | P49: 367581.1 | Q49: 380874.8 | R49: 125254.1 | S49: 380878.6 | T49: 666400 | U49: 334983 | V49: 246719.5 | W49: 475620.1 | X49: 1351706.6 | Y49: 2970593.4 | Z49: 1121923.2 | AA49: 917753.9 | AB49: 657592 | AC49: 635977.4 | AD49: 578097.8 | AE49: 2294683.9 | AF49: 3002385.4 | AG49: 3345452.3 | AH49: 2508797.3 | AI49: 1304057.4 | AJ49: 2187438.6 | AK49: 800816.1 | AL49: 21351.7 | AM49: 0 | AN49: 0 | AO49: 0 | AP49: 0 | AQ49: 0 | AR49: 0 | AS49: 0 | AT49: 0 | AU49: 0
A50: Data extracted on 03 Jun 2020 20:33 UTC (GMT) from OECD.Stat
A54: ISIC 41T43 | C54: Calibrated
A55: https://www.businesswire.com/news/home/20250428619006/en/Brazil-Construction-Industry-Databook-2025-Robust-Growth-in-Brazils-Construction-Sector-Forecasted-to-Expand-4.3-Annually-to-2029---ResearchAndMarkets.com

Sheet BR Data for ISIC Splits
A1: Data for Year 2015
A2: Calculated values are italicized. Non-italicized values come directly from source documents.
A3: Metric | B3: Source URL | C3: Source table | D3: Coal Mining | E3: Oil and gas extraction | F3: All Mining other than Oil and Gas (inc. Coal) | G3: Chemicals | H3: Pharmaceuticals | I3: Chemicals and Pharmaceuticals | J3: Glass | K3: Cement and Other Nometallic Minerals | L3: All Nonmetallic Minerals | M3: Iron and steel | N3: Other metals | O3: All primary metals | P3: Electricity generation and distribution | Q3: Energy pipelines and gas processing | R3: Water and waste | S3: All Utilities
A4: NAICS Code | D4: 580 | E4: 680 | F4: 00580 + 0791 + 0792 | G4: 2091 to 2093 | H4: 2094 | I4: 2091 to 2094 | J4: 23003 | K4: 23001+23002 | L4: 23001 + 23002 + 23003 | M4: 24911 + 24912 | N4: 24921 + 24922 | P4: 35001 | Q4: =P4 -> 35001 | R4: 36801
A5: ISIC Code | D5: 05 | E5: 06 | F5: 05 + 07T08 | G5: 20 | H5: 21 | I5: 20T21 | J5: 231 | K5: 239 | L5: 23 | M5: 241 | N5: 242 | O5: 24 | P5: 351 | Q5: 352T353 | R5: 36T39 | S5: 35T39
A6: Gross Output (detail level) | B6: https://ftp.ibge.gov.br/Contas_Nacionais/Matriz_de_Insumo_Produto/2015/Matriz_de_Insumo_Produto_2015_Nivel_67.xls | C6: U.Gross Output by Industry - Detail Level | D6: =D9 -> 10877 | E6: =D10 -> 98426 | F6: =SUM(D9,D11:D12) -> 51374 | G6: =SUM(D13:D15) -> 211561 | H6: =D16 -> 34825 | J6: =D19 -> 33040.529 | K6: =SUM(D17:D18) -> 90597.471 | M6: =D20 -> 79845 | N6: =D21 -> 44607 | P6: =G22*D22 -> 131466 | Q6: =G23*D22 -> 43822 | R6: =D23 -> 25127
B8: Brazil Gross Output for sectors | D8: MR$
B9: 580 | C9: Extração de carvão mineral e de minerais não-metálicos | D9: 10877
B10: 680 | C10: Extração de petróleo e gás, inclusive as atividades de apoio | D10: 98426
B11: 791 | C11: Extração de minério de ferro, inclusive beneficiamentos e a aglomeração | D11: 28837
B12: 792 | C12: Extração de minerais metálicos não-ferrosos, inclusive beneficiamentos | D12: 11660
B13: 2091 | C13: Fabricação de químicos orgânicos e inorgânicos, resinas e elastômeros | D13: 120094
B14: 2092 | C14: Fabricação de defensivos, desinfestantes, tintas e químicos diversos | D14: 59389
B15: 2093 | C15: Fabricação de produtos de limpeza, cosméticos/perfumaria e higiene pessoal | D15: 32078
B16: 2100 | C16: Fabricação de produtos farmoquímicos e farmacêuticos | D16: 34825
B17: 2300 | C17: Fabricação de produtos de minerais não-metálicos | D17: 61819 | E17: 2300 | F17: Fabricação de produtos de minerais não-metálicos | G17: =SUM(G18:G20) -> 87114
B18: 23001 + 23002 | C18: Cimento + Artefatos de cimento, gesso e semelhantes | D18: =D17*(G18+G19)/G17 -> 28778.471 | E18: 23001 | F18: Cimento | G18: 16383
B19: 23003 | C19: Vidros, cerâmicos e outros prod. de minerais não-metálicos | D19: =D17*G20/G17 -> 33040.529 | E19: 23002 | F19: Artefatos de cimento, gesso e semelhantes | G19: 24171
B20: 2491 | C20: Produção de ferro-gusa/ferroligas, siderurgia e tubos de aço sem costura | D20: 79845 | E20: 23003 | F20: Vidros, cerâmicos e outros prod. de minerais não-metálicos | G20: 46560
B21: 2492 | C21: Metalurgia de metais não-ferosos e a fundição de metais | D21: 44607
B22: 3500 | C22: Energia elétrica, gás natural e outras utilidades | D22: 175288 | E22: weight by average revenue between 2013-2022 | F22: Electricity generation and distribution | G22: 0.75
B23: 3680 | C23: Água, esgoto e gestão de resíduos | D23: 25127 | F23: Energy pipelines and gas processing | G23: 0.25

Sheet BObIC
A1: Unit: USD | B1: ISIC 01T03 | C1: ISIC 05 | D1: ISIC 06 | E1: ISIC 07T08 | F1: ISIC 09 | G1: ISIC 10T12 | H1: ISIC 13T15 | I1: ISIC 16 | J1: ISIC 17T18 | K1: ISIC 19 | L1: ISIC 20 | M1: ISIC 21 | N1: ISIC 22 | O1: ISIC 231 | P1: ISIC 239 | Q1: ISIC 241 | R1: ISIC 242 | S1: ISIC 25 | T1: ISIC 26 | U1: ISIC 27 | V1: ISIC 28 | W1: ISIC 29 | X1: ISIC 30 | Y1: ISIC 31T33 | Z1: ISIC 351 | AA1: ISIC 352T353 | AB1: ISIC 36T39 | AC1: ISIC 41T43 | AD1: ISIC 45T47 | AE1: ISIC 49T53 | AF1: ISIC 55T56 | AG1: ISIC 58T60 | AH1: ISIC 61 | AI1: ISIC 62T63 | AJ1: ISIC 64T66 | AK1: ISIC 68 | AL1: ISIC 69T82 | AM1: ISIC 84 | AN1: ISIC 85 | AO1: ISIC 86T88 | AP1: ISIC 90T96 | AQ1: ISIC 97T98
A2: Output | B2: ='OECD TTL'!C49*10^6*About!$A$30 -> 4.4148379e+11 | C2: ='OECD TTL'!D49*10^6*About!$A$30*('BR Data for ISIC Splits'!D6/SUM('BR Data for ISIC Splits'!D6:E6)) -> 2.8308659e+10 | D2: ='OECD TTL'!D49*10^6*About!$A$30*('BR Data for ISIC Splits'!E6/SUM('BR Data for ISIC Splits'!D6:E6)) -> 2.5616512e+11 | E2: ='OECD TTL'!E49*10^6*About!$A$30 -> 6.2857069e+10 | F2: ='OECD TTL'!F49*10^6*About!$A$30 -> 8.5036777e+10 | G2: ='OECD TTL'!G49*10^6*About!$A$30 -> 9.0650035e+11 | H2: ='OECD TTL'!H49*10^6*About!$A$30 -> 8.4293508e+10 | I2: ='OECD TTL'!I49*10^6*About!$A$30 -> 9.5524596e+10 | J2: ='OECD TTL'!J49*10^6*About!$A$30 -> 2.6077228e+11 | K2: ='OECD TTL'!K49*10^6*About!$A$30 -> 4.7476837e+11 | L2: ='OECD TTL'!L49*10^6*About!$A$30*('BR Data for ISIC Splits'!G6/SUM('BR Data for ISIC Splits'!G6:H6)) -> 6.5320748e+11 | M2: ='OECD TTL'!L49*10^6*About!$A$30*('BR Data for ISIC Splits'!H6/SUM('BR Data for ISIC Splits'!G6:H6)) -> 1.0752431e+11 | N2: ='OECD TTL'!M49*10^6*About!$A$30 -> 2.2374898e+11 | O2: ='OECD TTL'!N49*10^6*About!$A$30*('BR Data for ISIC Splits'!J6/SUM('BR Data for ISIC Splits'!J6:K6)) -> 3.0932335e+10 | P2: ='OECD TTL'!N49*10^6*About!$A$30*('BR Data for ISIC Splits'!K6/SUM('BR Data for ISIC Splits'!J6:K6)) -> 8.4816782e+10 | Q2: ='OECD TTL'!O49*10^6*About!$A$30*('BR Data for ISIC Splits'!M6/SUM('BR Data for ISIC Splits'!M6:N6)) -> 1.3998437e+11 | R2: ='OECD TTL'!O49*10^6*About!$A$30*('BR Data for ISIC Splits'!N6/SUM('BR Data for ISIC Splits'!M6:N6)) -> 7.8205055e+10 | S2: ='OECD TTL'!P49*10^6*About!$A$30 -> 3.5606904e+11 | T2: ='OECD TTL'!Q49*10^6*About!$A$30 -> 3.689464e+11 | U2: ='OECD TTL'!R49*10^6*About!$A$30 -> 1.2133134e+11 | V2: ='OECD TTL'!S49*10^6*About!$A$30 -> 3.6895008e+11 | W2: ='OECD TTL'!T49*10^6*About!$A$30 -> 6.455294e+11 | X2: ='OECD TTL'!U49*10^6*About!$A$30 -> 3.2449186e+11 | Y2: ='OECD TTL'!V49*10^6*About!$A$30 -> 2.3899263e+11 | Z2: ='OECD TTL'!W49*10^6*About!$A$30*('BR Data for ISIC Splits'!P6/SUM('BR Data for ISIC Splits'!P6:R6)) -> 3.0222088e+11 | AA2: ='OECD TTL'!W49*10^6*About!$A$30*('BR Data for ISIC Splits'!Q6/SUM('BR Data for ISIC Splits'!P6:R6)) -> 1.0074029e+11 | AB2: ='OECD TTL'!W49*10^6*About!$A$30*('BR Data for ISIC Splits'!R6/SUM('BR Data for ISIC Splits'!P6:R6)) -> 5.7763254e+10 | AC2: ='OECD TTL'!X49*10^6*About!$A$30 -> 1.3093733e+12 | AD2: ='OECD TTL'!Y49*10^6*About!$A$30 -> 2.8775591e+12 | AE2: ='OECD TTL'!Z49*10^6*About!$A$30 -> 1.0867863e+12 | AF2: ='OECD TTL'!AA49*10^6*About!$A$30 -> 8.8901129e+11 | AG2: ='OECD TTL'!AB49*10^6*About!$A$30 -> 6.3699725e+11 | AH2: ='OECD TTL'!AC49*10^6*About!$A$30 -> 6.1605959e+11 | AI2: ='OECD TTL'!AD49*10^6*About!$A$30 -> 5.5999269e+11 | AJ2: ='OECD TTL'!AE49*10^6*About!$A$30 -> 2.222818e+12 | ... AQ2: ='OECD TTL'!AL49*10^6*About!$A$30 -> 2.0682998e+10
