Workbook

Sheet Summary
A1: Brazil: average new-vehicle price by vehicle type and forecast to 2050
A2: All values are live formulas. Change the scenario and statistic on the Assumptions sheet. Base year 2022; prices per vehicle.
A3: Scenario: | B3: =Assumptions!B7 -> Base | C3: =Assumptions!B10&" used for road base prices; real R$ = constant 2022 prices" -> Mean used for road base prices; real R$ = constant 2022 prices
G4: Real R$ per vehicle (constant 2022 prices)
A5: Mode | B5: Vehicle type | C5: What the price represents | D5: Observations / benchmarks (n) | E5: 2022 base, R$ (constant) | F5: 2022 base, US$ (constant) | G5: 2030 | H5: 2035 | I5: 2040 | J5: 2045 | K5: 2050 | L5: 2050 nominal, R$ | M5: Real CAGR 2022-2050 | N5: Confidence | O5: Main sources
A6: Road | B6: Road - Passenger LDV | C6: Cars, SUVs, sports cars, luxury (FIPE 0-km listings, 2022) | D6: ='Road Avg'!$B$6 -> 8968 | E6: =Forecast!$E$10 -> 427911.79 | F6: =Forecast!$E$38 -> 82852.105 | G6: {=INDEX(Forecast!$E$10:$AG$10,MATCH(G$5,Forecast!$E$5:$AG$5,0))} -> 427911.79 | H6: {=INDEX(Forecast!$E$10:$AG$10,MATCH(H$5,Forecast!$E$5:$AG$5,0))} -> 427911.79 | I6: {=INDEX(Forecast!$E$10:$AG$10,MATCH(I$5,Forecast!$E$5:$AG$5,0))} -> 427911.79 | J6: {=INDEX(Forecast!$E$10:$AG$10,MATCH(J$5,Forecast!$E$5:$AG$5,0))} -> 427911.79 | K6: {=INDEX(Forecast!$E$10:$AG$10,MATCH(K$5,Forecast!$E$5:$AG$5,0))} -> 427911.79 | L6: {=INDEX(Forecast!$E$24:$AG$24,MATCH(Assumptions!$B$5,Forecast!$E$5:$AG$5,0))} -> 1036613.2 | M6: =(K6/E6)^(1/(Assumptions!$B$5-Assumptions!$B$4))-1 -> 0 | N6: High | O6: FIPE (your file)
A7: Road | B7: Road - Passenger HDV | C7: Minibuses / passenger vans > 3,856 kg GVW (Sprinter 416/516 VAN, Ducato Multi, Transit Minibus). No full-size buses in dataset | D7: ='Road Avg'!$B$7 -> 281 | E7: =Forecast!$E$11 -> 298836.74 | F7: =Forecast!$E$39 -> 57860.648 | G7: {=INDEX(Forecast!$E$11:$AG$11,MATCH(G$5,Forecast!$E$5:$AG$5,0))} -> 298836.74 | H7: {=INDEX(Forecast!$E$11:$AG$11,MATCH(H$5,Forecast!$E$5:$AG$5,0))} -> 298836.74 | I7: {=INDEX(Forecast!$E$11:$AG$11,MATCH(I$5,Forecast!$E$5:$AG$5,0))} -> 298836.74 | J7: {=INDEX(Forecast!$E$11:$AG$11,MATCH(J$5,Forecast!$E$5:$AG$5,0))} -> 298836.74 | K7: {=INDEX(Forecast!$E$11:$AG$11,MATCH(K$5,Forecast!$E$5:$AG$5,0))} -> 298836.74 | L7: {=INDEX(Forecast!$E$25:$AG$25,MATCH(Assumptions!$B$5,Forecast!$E$5:$AG$5,0))} -> 723929.84 | M7: =(K7/E7)^(1/(Assumptions!$B$5-Assumptions!$B$4))-1 -> 0 | N7: Medium | O7: FIPE (your file)
A8: Road | B8: Road - Freight LDV | C8: Pickups, cargo vans, light trucks <= 3,856 kg GVW | D8: ='Road Avg'!$B$8 -> 2030 | E8: =Forecast!$E$12 -> 212826.35 | F8: =Forecast!$E$40 -> 41207.35 | G8: {=INDEX(Forecast!$E$12:$AG$12,MATCH(G$5,Forecast!$E$5:$AG$5,0))} -> 212826.35 | H8: {=INDEX(Forecast!$E$12:$AG$12,MATCH(H$5,Forecast!$E$5:$AG$5,0))} -> 212826.35 | I8: {=INDEX(Forecast!$E$12:$AG$12,MATCH(I$5,Forecast!$E$5:$AG$5,0))} -> 212826.35 | J8: {=INDEX(Forecast!$E$12:$AG$12,MATCH(J$5,Forecast!$E$5:$AG$5,0))} -> 212826.35 | K8: {=INDEX(Forecast!$E$12:$AG$12,MATCH(K$5,Forecast!$E$5:$AG$5,0))} -> 212826.35 | L8: {=INDEX(Forecast!$E$26:$AG$26,MATCH(Assumptions!$B$5,Forecast!$E$5:$AG$5,0))} -> 515570.28 | M8: =(K8/E8)^(1/(Assumptions!$B$5-Assumptions!$B$4))-1 -> 0 | N8: High | O8: FIPE (your file)
A9: Road | B9: Road - Freight HDV | C9: Iveco Daily 45-70, Sprinter 416/516 chassis & vans, Ram 2500/3500 (> 3,856 kg GVW). No heavy trucks in dataset | D9: ='Road Avg'!$B$9 -> 353 | E9: =Forecast!$E$13 -> 295851.61 | F9: =Forecast!$E$41 -> 57282.668 | G9: {=INDEX(Forecast!$E$13:$AG$13,MATCH(G$5,Forecast!$E$5:$AG$5,0))} -> 295851.61 | H9: {=INDEX(Forecast!$E$13:$AG$13,MATCH(H$5,Forecast!$E$5:$AG$5,0))} -> 295851.61 | I9: {=INDEX(Forecast!$E$13:$AG$13,MATCH(I$5,Forecast!$E$5:$AG$5,0))} -> 295851.61 | J9: {=INDEX(Forecast!$E$13:$AG$13,MATCH(J$5,Forecast!$E$5:$AG$5,0))} -> 295851.61 | K9: {=INDEX(Forecast!$E$13:$AG$13,MATCH(K$5,Forecast!$E$5:$AG$5,0))} -> 295851.61 | L9: {=INDEX(Forecast!$E$27:$AG$27,MATCH(Assumptions!$B$5,Forecast!$E$5:$AG$5,0))} -> 716698.38 | M9: =(K9/E9)^(1/(Assumptions!$B$5-Assumptions!$B$4))-1 -> 0 | N9: Medium | O9: FIPE (your file)
A10: Motorbike | B10: Motorbike - Passenger | C10: Honda CG 160, Biz, Pop 110i weighted by 2022 registrations | D10: ='NonRoad Avg'!$C$6 -> 6 | E10: =Forecast!$E$14 -> 11475.445 | F10: =Forecast!$E$42 -> 2221.8709 | G10: {=INDEX(Forecast!$E$14:$AG$14,MATCH(G$5,Forecast!$E$5:$AG$5,0))} -> 11475.445 | H10: {=INDEX(Forecast!$E$14:$AG$14,MATCH(H$5,Forecast!$E$5:$AG$5,0))} -> 11475.445 | I10: {=INDEX(Forecast!$E$14:$AG$14,MATCH(I$5,Forecast!$E$5:$AG$5,0))} -> 11475.445 | J10: {=INDEX(Forecast!$E$14:$AG$14,MATCH(J$5,Forecast!$E$5:$AG$5,0))} -> 11475.445 | K10: {=INDEX(Forecast!$E$14:$AG$14,MATCH(K$5,Forecast!$E$5:$AG$5,0))} -> 11475.445 | L10: {=INDEX(Forecast!$E$28:$AG$28,MATCH(Assumptions!$B$5,Forecast!$E$5:$AG$5,0))} -> 27799.182 | M10: =(K10/E10)^(1/(Assumptions!$B$5-Assumptions!$B$4))-1 -> 0 | N10: Medium | O10: Bem Parana; Motonline; Tabela FIPE Brasil (Fenabrave)
A11: Motorbike | B11: Motorbike - Freight | C11: Honda CG 160 Cargo | D11: ='NonRoad Avg'!$C$7 -> 1 | E11: =Forecast!$E$15 -> 12587.82 | F11: =Forecast!$E$43 -> 2437.2485 | G11: {=INDEX(Forecast!$E$15:$AG$15,MATCH(G$5,Forecast!$E$5:$AG$5,0))} -> 12587.82 | H11: {=INDEX(Forecast!$E$15:$AG$15,MATCH(H$5,Forecast!$E$5:$AG$5,0))} -> 12587.82 | I11: {=INDEX(Forecast!$E$15:$AG$15,MATCH(I$5,Forecast!$E$5:$AG$5,0))} -> 12587.82 | J11: {=INDEX(Forecast!$E$15:$AG$15,MATCH(J$5,Forecast!$E$5:$AG$5,0))} -> 12587.82 | K11: {=INDEX(Forecast!$E$15:$AG$15,MATCH(K$5,Forecast!$E$5:$AG$5,0))} -> 12587.82 | L11: {=INDEX(Forecast!$E$29:$AG$29,MATCH(Assumptions!$B$5,Forecast!$E$5:$AG$5,0))} -> 30493.903 | M11: =(K11/E11)^(1/(Assumptions!$B$5-Assumptions!$B$4))-1 -> 0 | N11: Low | O11: Bem Parana
A12: Aircraft | B12: Aircraft - Passenger | C12: A320neo, 737 MAX 8, E195-E2 | D12: ='NonRoad Avg'!$C$8 -> 3 | E12: =Forecast!$E$16 -> 2.2354408e+08 | F12: =Forecast!$E$44 -> 43282513 | G12: {=INDEX(Forecast!$E$16:$AG$16,MATCH(G$5,Forecast!$E$5:$AG$5,0))} -> 2.2354408e+08 | H12: {=INDEX(Forecast!$E$16:$AG$16,MATCH(H$5,Forecast!$E$5:$AG$5,0))} -> 2.2354408e+08 | I12: {=INDEX(Forecast!$E$16:$AG$16,MATCH(I$5,Forecast!$E$5:$AG$5,0))} -> 2.2354408e+08 | J12: {=INDEX(Forecast!$E$16:$AG$16,MATCH(J$5,Forecast!$E$5:$AG$5,0))} -> 2.2354408e+08 | K12: {=INDEX(Forecast!$E$16:$AG$16,MATCH(K$5,Forecast!$E$5:$AG$5,0))} -> 2.2354408e+08 | L12: {=INDEX(Forecast!$E$30:$AG$30,MATCH(Assumptions!$B$5,Forecast!$E$5:$AG$5,0))} -> 5.4153391e+08 | M12: =(K12/E12)^(1/(Assumptions!$B$5-Assumptions!$B$4))-1 -> 0 | N12: Medium | O12: InsideFlyer; AirDataNews
A13: Aircraft | B13: Aircraft - Freight | C13: Converted 737-800BCF and A321P2F freighters | D13: ='NonRoad Avg'!$C$9 -> 2 | E13: =Forecast!$E$17 -> 1.1367651e+08 | F13: =Forecast!$E$45 -> 22010000 | G13: {=INDEX(Forecast!$E$17:$AG$17,MATCH(G$5,Forecast!$E$5:$AG$5,0))} -> 1.1367651e+08 | H13: {=INDEX(Forecast!$E$17:$AG$17,MATCH(H$5,Forecast!$E$5:$AG$5,0))} -> 1.1367651e+08 | I13: {=INDEX(Forecast!$E$17:$AG$17,MATCH(I$5,Forecast!$E$5:$AG$5,0))} -> 1.1367651e+08 | J13: {=INDEX(Forecast!$E$17:$AG$17,MATCH(J$5,Forecast!$E$5:$AG$5,0))} -> 1.1367651e+08 | K13: {=INDEX(Forecast!$E$17:$AG$17,MATCH(K$5,Forecast!$E$5:$AG$5,0))} -> 1.1367651e+08 | L13: {=INDEX(Forecast!$E$31:$AG$31,MATCH(Assumptions!$B$5,Forecast!$E$5:$AG$5,0))} -> 2.7538053e+08 | M13: =(K13/E13)^(1/(Assumptions!$B$5-Assumptions!$B$4))-1 -> 0 | N13: Medium | O13: IBA; STAT Times
A14: Ship | B14: Ship - Passenger | C14: Bahia ferry-boat (1,254 pax + 168 vehicles), used | D14: ='NonRoad Avg'!$C$10 -> 1 | E14: =Forecast!$E$18 -> 75018509 | F14: =Forecast!$E$46 -> 14525053 | G14: {=INDEX(Forecast!$E$18:$AG$18,MATCH(G$5,Forecast!$E$5:$AG$5,0))} -> 75018509 | H14: {=INDEX(Forecast!$E$18:$AG$18,MATCH(H$5,Forecast!$E$5:$AG$5,0))} -> 75018509 | I14: {=INDEX(Forecast!$E$18:$AG$18,MATCH(I$5,Forecast!$E$5:$AG$5,0))} -> 75018509 | J14: {=INDEX(Forecast!$E$18:$AG$18,MATCH(J$5,Forecast!$E$5:$AG$5,0))} -> 75018509 | K14: {=INDEX(Forecast!$E$18:$AG$18,MATCH(K$5,Forecast!$E$5:$AG$5,0))} -> 75018509 | L14: {=INDEX(Forecast!$E$32:$AG$32,MATCH(Assumptions!$B$5,Forecast!$E$5:$AG$5,0))} -> 1.8173179e+08 | M14: =(K14/E14)^(1/(Assumptions!$B$5-Assumptions!$B$4))-1 -> 0 | N14: Low | O14: Bahia Noticias
A15: Ship | B15: Ship - Freight | C15: Transpetro Handy and MR1 tankers (Brazilian yards) | D15: ='NonRoad Avg'!$C$11 -> 2 | E15: =Forecast!$E$19 -> 4.0037794e+08 | F15: =Forecast!$E$47 -> 77521012 | G15: {=INDEX(Forecast!$E$19:$AG$19,MATCH(G$5,Forecast!$E$5:$AG$5,0))} -> 4.0037794e+08 | H15: {=INDEX(Forecast!$E$19:$AG$19,MATCH(H$5,Forecast!$E$5:$AG$5,0))} -> 4.0037794e+08 | I15: {=INDEX(Forecast!$E$19:$AG$19,MATCH(I$5,Forecast!$E$5:$AG$5,0))} -> 4.0037794e+08 | J15: {=INDEX(Forecast!$E$19:$AG$19,MATCH(J$5,Forecast!$E$5:$AG$5,0))} -> 4.0037794e+08 | K15: {=INDEX(Forecast!$E$19:$AG$19,MATCH(K$5,Forecast!$E$5:$AG$5,0))} -> 4.0037794e+08 | L15: {=INDEX(Forecast!$E$33:$AG$33,MATCH(Assumptions!$B$5,Forecast!$E$5:$AG$5,0))} -> 9.6991265e+08 | M15: =(K15/E15)^(1/(Assumptions!$B$5-Assumptions!$B$4))-1 -> 0 | N15: Medium | O15: Eixos; Times Brasil
A16: Rail | B16: Rail - Passenger | C16: Metro SP six-car trainset | D16: ='NonRoad Avg'!$C$12 -> 1 | E16: =Forecast!$E$20 -> 64329558 | F16: =Forecast!$E$48 -> 12455463 | G16: {=INDEX(Forecast!$E$20:$AG$20,MATCH(G$5,Forecast!$E$5:$AG$5,0))} -> 64329558 | H16: {=INDEX(Forecast!$E$20:$AG$20,MATCH(H$5,Forecast!$E$5:$AG$5,0))} -> 64329558 | I16: {=INDEX(Forecast!$E$20:$AG$20,MATCH(I$5,Forecast!$E$5:$AG$5,0))} -> 64329558 | J16: {=INDEX(Forecast!$E$20:$AG$20,MATCH(J$5,Forecast!$E$5:$AG$5,0))} -> 64329558 | K16: {=INDEX(Forecast!$E$20:$AG$20,MATCH(K$5,Forecast!$E$5:$AG$5,0))} -> 64329558 | L16: {=INDEX(Forecast!$E$34:$AG$34,MATCH(Assumptions!$B$5,Forecast!$E$5:$AG$5,0))} -> 1.5583789e+08 | M16: =(K16/E16)^(1/(Assumptions!$B$5-Assumptions!$B$4))-1 -> 0 | N16: Low | O16: Diario do Transporte
A17: Rail | B17: Rail - Freight | C17: Locomotives (MRS, VLI purchases) | D17: ='NonRoad Avg'!$C$13 -> 4 | E17: =Forecast!$E$21 -> 19501752 | F17: =Forecast!$E$49 -> 3775921.1 | G17: {=INDEX(Forecast!$E$21:$AG$21,MATCH(G$5,Forecast!$E$5:$AG$5,0))} -> 19501752 | H17: {=INDEX(Forecast!$E$21:$AG$21,MATCH(H$5,Forecast!$E$5:$AG$5,0))} -> 19501752 | I17: {=INDEX(Forecast!$E$21:$AG$21,MATCH(I$5,Forecast!$E$5:$AG$5,0))} -> 19501752 | J17: {=INDEX(Forecast!$E$21:$AG$21,MATCH(J$5,Forecast!$E$5:$AG$5,0))} -> 19501752 | K17: {=INDEX(Forecast!$E$21:$AG$21,MATCH(K$5,Forecast!$E$5:$AG$5,0))} -> 19501752 | L17: {=INDEX(Forecast!$E$35:$AG$35,MATCH(Assumptions!$B$5,Forecast!$E$5:$AG$5,0))} -> 47242852 | M17: =(K17/E17)^(1/(Assumptions!$B$5-Assumptions!$B$4))-1 -> 0 | N17: Medium | O17: Mundo Logistica; Diario do Comercio
A19: Read before using the numbers
A20: 1. The FIPE file is 0-km cars and light commercial vehicles (model-year 2023, Jan-Dec 2022). It has no full-size buses or heavy trucks, so 'HDV' here means FIPE-listed vehicles above 3,856 kg GVW (large vans, Iveco Daily 45-70, Sprinter 416/516, Ram 2500/3500).
A21: 2. The Passenger LDV mean is pulled up by supercars and ultra-luxury cars (Rolls-Royce, Ferrari, McLaren). The median (Road_Avg column E) is much lower; switch with Assumptions!B9.
A22: 3. Aircraft, ship and rail prices come from a small number of public contracts and valuations (one row per source in Bench_NonRoad). Single-benchmark categories are marked Low confidence. Change Include (1/0) or add rows there and everything updates.
A23: 4. Motorbike prices are manufacturer-suggested prices (DF base), which sit below FIPE market prices. Passenger motorbike covers 52% of 2022 registrations (Honda CG 160, Biz, Pop).
A24: 5. Real growth rates are analyst assumptions (Base = flat real price; Low/High = -1/+1 pp). No sourced long-run price trend exists in the data. Nominal series add IPCA (actual to 2026, then the 3% target).
A25: 6. Freight rail = locomotive price (no wagons). Passenger rail = one six-car trainset. Ships and aircraft are per vessel / per aircraft.
A26: 7. Prices by fuel (BEV, NGV, gasoline, diesel, PHEV, LPG, hydrogen) are on Fuel_Price and Fuel_Forecast. Only road gasoline/diesel/PHEV come from your FIPE file; BEV, NGV and hydrogen rest on the few Brazilian sources on Fuel_Evidence; cells marked 'Analyst' are indicative placeholders.

Sheet Assumptions
A1: Assumptions and scenario controls
A2: Blue = input. Yellow fill = cells you are meant to change. Black = formula. Green = link to another sheet.
A3: General | B3: Value | F3: Note / source
A4: Base year (FIPE data year; do not change) | B4: 2022 | F4: The FIPE workbook covers Jan-Dec 2022. Base prices are nominal 2022 R$ = constant 2022 R$.
A5: Final forecast year | B5: =Forecast!AG5 -> 2050 | F5: Horizon is fixed at 29 columns (2022-2050) on the Forecast sheet.
A6: Scenario for real price growth (1 = Low, 2 = Base, 3 = High) | B6: 2 | F6: Drop-down. Picks the Low / Base / High column of the growth table below.
A7: Scenario name | B7: =CHOOSE(B6,"Low","Base","High") -> Base
A8: Long-run inflation after the last actual IPCA year (%/yr) | B8: 0.03 | F8: Brazil's continuous inflation target of 3.0% (CMN, from 2025). Actual IPCA is used up to the last year in Macro.
A9: Statistic for road base prices (1 = Mean, 2 = Median) | B9: 1 | F9: Mean = "average price". The median is far lower for Passenger LDV because supercars (up to R$ 8.6 m) skew the mean.
A10: Statistic name | B10: =CHOOSE(B9,"Mean","Median") -> Mean
A11: PROCONVE light / heavy threshold (kg GVW) | B11: 3856 | F11: Informational: defines LDV (<= 3,856 kg) vs HDV in Class_Rules.
A12: Average PTAX in base year (R$ per US$) | B12: {=INDEX(Macro!$L$6:$L$17,MATCH(B4,Macro!$K$6:$K$17,0))} -> 5.1647667 | F12: Used for the constant-price US$ view. No future FX forecast is made.
A13: Last year with actual IPCA in Macro | B13: =Macro!K17 -> 2026 | F13: 2026 is partial (12-month rate to Aug-2026).
F14: Source for the 3% target: CNN Brasil, continuous inflation target from 2025
A16: Real price growth by vehicle type (% per year, constant 2022 R$, applied 2023-2050)
A17: Vehicle type | B17: Low | C17: Base | D17: High | E17: Selected | F17: Rationale
A18: Road - Passenger LDV | B18: -0.01 | C18: 0 | D18: 0.01 | E18: =INDEX(B18:D18,1,$B$6) -> 0 | F18: Analyst assumption. The dataset covers one year (2022), so it cannot support a sourced long-run trend. Base = constant real price; +/-1 pp brackets emissions/safety content (PROCONVE L8/P8) against scale and local-content cost-downs.
A19: Road - Passenger HDV | B19: -0.01 | C19: 0 | D19: 0.01 | E19: =INDEX(B19:D19,1,$B$6) -> 0 | F19: Analyst assumption. The dataset covers one year (2022), so it cannot support a sourced long-run trend. Base = constant real price; +/-1 pp brackets emissions/safety content (PROCONVE L8/P8) against scale and local-content cost-downs.
A20: Road - Freight LDV | B20: -0.01 | C20: 0 | D20: 0.01 | E20: =INDEX(B20:D20,1,$B$6) -> 0 | F20: Analyst assumption. The dataset covers one year (2022), so it cannot support a sourced long-run trend. Base = constant real price; +/-1 pp brackets emissions/safety content (PROCONVE L8/P8) against scale and local-content cost-downs.
A21: Road - Freight HDV | B21: -0.01 | C21: 0 | D21: 0.01 | E21: =INDEX(B21:D21,1,$B$6) -> 0 | F21: Analyst assumption. The dataset covers one year (2022), so it cannot support a sourced long-run trend. Base = constant real price; +/-1 pp brackets emissions/safety content (PROCONVE L8/P8) against scale and local-content cost-downs.
A22: Motorbike - Passenger | B22: -0.015 | C22: 0 | D22: 0.01 | E22: =INDEX(B22:D22,1,$B$6) -> 0 | F22: Analyst assumption anchored on the FIPE-vs-IPCA cross-check in Macro!K25:Q28: real change of about -1.6%/yr (CG 160 Start, 2021-26) and +0.3%/yr (Pop 110i, 2022-26). Base 0%.
A23: Motorbike - Freight | B23: -0.015 | C23: 0 | D23: 0.01 | E23: =INDEX(B23:D23,1,$B$6) -> 0 | F23: Analyst assumption anchored on the FIPE-vs-IPCA cross-check in Macro!K25:Q28: real change of about -1.6%/yr (CG 160 Start, 2021-26) and +0.3%/yr (Pop 110i, 2022-26). Base 0%.
A24: Aircraft - Passenger | B24: -0.01 | C24: 0 | D24: 0.01 | E24: =INDEX(B24:D24,1,$B$6) -> 0 | F24: Analyst assumption (no sourced long-run trend). Prices are market values / negotiated prices, not list prices.
A25: Aircraft - Freight | B25: -0.01 | C25: 0 | D25: 0.01 | E25: =INDEX(B25:D25,1,$B$6) -> 0 | F25: Analyst assumption (no sourced long-run trend). Prices are market values / negotiated prices, not list prices.
A26: Ship - Passenger | B26: -0.01 | C26: 0 | D26: 0.01 | E26: =INDEX(B26:D26,1,$B$6) -> 0 | F26: Analyst assumption (no sourced long-run trend). Newbuild prices depend on yard, local-content rules and ship type.
A27: Ship - Freight | B27: -0.01 | C27: 0 | D27: 0.01 | E27: =INDEX(B27:D27,1,$B$6) -> 0 | F27: Analyst assumption (no sourced long-run trend). Newbuild prices depend on yard, local-content rules and ship type.
A28: Rail - Passenger | B28: -0.01 | C28: 0 | D28: 0.01 | E28: =INDEX(B28:D28,1,$B$6) -> 0 | F28: Analyst assumption (no sourced long-run trend). Rolling-stock contract prices include systems and services.
A29: Rail - Freight | B29: -0.01 | C29: 0 | D29: 0.01 | E29: =INDEX(B29:D29,1,$B$6) -> 0 | F29: Analyst assumption (no sourced long-run trend). Rolling-stock contract prices include systems and services.
A32: Premium convergence by fuel (annual %, applied to the price premium over the reference vehicle)
A33: Fuel | B33: Convergence (%/yr) | F33: Rationale
A34: BEV | B34: 0.03 | F34: Analyst assumption: battery-cost decline and scale close part of the premium. 3%/yr halves a premium by about 2040.
A35: NGV | B35: 0.01 | F35: Analyst assumption: mature conversion kits; little cost decline.
A36: Gasoline | B36: 0 | F36: Reference technology: no premium.
A37: Diesel | B37: 0 | F37: Reference technology: no premium.
A38: PHEV | B38: 0.02 | F38: Analyst assumption.
A39: LPG | B39: 0.01 | F39: Analyst assumption.
A40: Hydrogen | B40: 0.03 | F40: Analyst assumption: fuel-cell and tank cost decline with scale; starts from a large premium.
A42: Premium(t) = 1 + (Premium(2022) - 1) x (1 - convergence)^(t - 2022) when the 2022 price is above the reference vehicle; otherwise the 2022 ratio is held constant.

Sheet Fuel Price
A1: Average new-vehicle price by fuel / powertrain, 2022 (constant 2022 R$)
A2: Rows = the 12 vehicle types. Columns = BEV, NGV, gasoline, diesel, PHEV, LPG, hydrogen. Method codes: D = FIPE data, B = baseline (Summary base price), S = sourced absolute price, X = multiplier x reference price, P = reference price + additive cost, N = not available.
A3: Method code, evidence class and inputs are editable (yellow / blue). Changing a code or input updates the price, ratio and forecast automatically.
A6: 1. Method code per cell (editable)
A7: ID | B7: Vehicle type | C7: Battery electric vehicle (BEV) | D7: Natural gas vehicle (NGV) | E7: Gasoline vehicle | F7: Diesel vehicle | G7: Plug-in hybrid vehicle (PHEV) | H7: LPG vehicle | I7: Hydrogen (fuel-cell) vehicle
A8: 1 | B8: Road - Passenger LDV | C8: S | D8: P | E8: D | F8: D | G8: D | H8: N | I8: X
A9: 2 | B9: Road - Passenger HDV | C9: X | D9: X | E9: D | F9: D | G9: D | H9: N | I9: X
A10: 3 | B10: Road - Freight LDV | C10: X | D10: P | E10: D | F10: D | G10: D | H10: N | I10: X
A11: 4 | B11: Road - Freight HDV | C11: X | D11: X | E11: D | F11: D | G11: D | H11: N | I11: X
A12: 5 | B12: Motorbike - Passenger | C12: S | D12: N | E12: B | F12: N | G12: N | H12: N | I12: N
A13: 6 | B13: Motorbike - Freight | C13: X | D13: N | E13: B | F13: N | G13: N | H13: N | I13: N
A14: 7 | B14: Aircraft - Passenger | C14: N | D14: N | E14: B | F14: N | G14: N | H14: N | I14: N
A15: 8 | B15: Aircraft - Freight | C15: N | D15: N | E15: B | F15: N | G15: N | H15: N | I15: N
A16: 9 | B16: Ship - Passenger | C16: X | D16: X | E16: N | F16: B | G16: X | H16: X | I16: X
A17: 10 | B17: Ship - Freight | C17: N | D17: X | E17: N | F17: B | G17: X | H17: X | I17: N
A18: 11 | B18: Rail - Passenger | C18: B | D18: N | E18: N | F18: X | G18: N | H18: N | I18: X
A19: 12 | B19: Rail - Freight | C19: X | D19: X | E19: N | F19: B | G19: X | H19: N | I19: X
A21: 2. Evidence class per cell (Data / Baseline / Sourced / Proxy / Analyst / n/a)
A22: ID | B22: Vehicle type | C22: Battery electric vehicle (BEV) | D22: Natural gas vehicle (NGV) | E22: Gasoline vehicle | F22: Diesel vehicle | G22: Plug-in hybrid vehicle (PHEV) | H22: LPG vehicle | I22: Hydrogen (fuel-cell) vehicle
A23: 1 | B23: Road - Passenger LDV | C23: Sourced | D23: Sourced | E23: Data | F23: Data | G23: Data | H23: n/a | I23: Sourced
A24: 2 | B24: Road - Passenger HDV | C24: Sourced | D24: Analyst | E24: Data | F24: Data | G24: Data | H24: n/a | I24: Analyst
A25: 3 | B25: Road - Freight LDV | C25: Proxy | D25: Sourced | E25: Data | F25: Data | G25: Data | H25: n/a | I25: Proxy
A26: 4 | B26: Road - Freight HDV | C26: Proxy | D26: Analyst | E26: Data | F26: Data | G26: Data | H26: n/a | I26: Analyst
A27: 5 | B27: Motorbike - Passenger | C27: Sourced | D27: n/a | E27: Baseline | F27: n/a | G27: n/a | H27: n/a | I27: n/a
A28: 6 | B28: Motorbike - Freight | C28: Proxy | D28: n/a | E28: Baseline | F28: n/a | G28: n/a | H28: n/a | I28: n/a
A29: 7 | B29: Aircraft - Passenger | C29: n/a | D29: n/a | E29: Baseline | F29: n/a | G29: n/a | H29: n/a | I29: n/a
A30: 8 | B30: Aircraft - Freight | C30: n/a | D30: n/a | E30: Baseline | F30: n/a | G30: n/a | H30: n/a | I30: n/a
A31: 9 | B31: Ship - Passenger | C31: Analyst | D31: Analyst | E31: n/a | F31: Baseline | G31: Analyst | H31: Analyst | I31: Analyst
A32: 10 | B32: Ship - Freight | C32: n/a | D32: Analyst | E32: n/a | F32: Baseline | G32: Analyst | H32: Analyst | I32: n/a
A33: 11 | B33: Rail - Passenger | C33: Baseline | D33: n/a | E33: n/a | F33: Analyst | G33: n/a | H33: n/a | I33: Analyst
A34: 12 | B34: Rail - Freight | C34: Analyst | D34: Analyst | E34: n/a | F34: Baseline | G34: Analyst | H34: n/a | I34: Analyst
A36: 3. Inputs used by codes S, X, P: absolute price (R$), multiplier, or additive cost (R$)
A37: ID | B37: Vehicle type | C37: Battery electric vehicle (BEV) | D37: Natural gas vehicle (NGV) | E37: Gasoline vehicle | F37: Diesel vehicle | G37: Plug-in hybrid vehicle (PHEV) | H37: LPG vehicle | I37: Hydrogen (fuel-cell) vehicle
A38: 1 | B38: Road - Passenger LDV | C38: ='Fuel Evidence'!$J$16 -> 147487.33 | D38: ='Fuel Evidence'!$J$17 -> 5000 | I38: ='Fuel Evidence'!$J$23 -> 2.0582121
A39: 2 | B39: Road - Passenger HDV | C39: ='Fuel Evidence'!$J$18 -> 3 | D39: 1.2 | I39: 4.5
A40: 3 | B40: Road - Freight LDV | C40: ='Fuel Evidence'!$J$30 -> 1.4113703 | D40: ='Fuel Evidence'!$J$17 -> 5000 | I40: ='Fuel Evidence'!$J$23 -> 2.0582121
A41: 4 | B41: Road - Freight HDV | C41: ='Fuel Evidence'!$J$18 -> 3 | D41: 1.2 | I41: 4.5
A42: 5 | B42: Motorbike - Passenger | C42: ='Fuel Evidence'!$J$20 -> 16014
A43: 6 | B43: Motorbike - Freight | C43: =C87/E87 -> 1.3955015
A44: 7 | B44: Aircraft - Passenger
A45: 8 | B45: Aircraft - Freight
A46: 9 | B46: Ship - Passenger | C46: 1.6 | D46: 1.15 | G46: 1.25 | H46: 1.1 | I46: 2.5
A47: 10 | B47: Ship - Freight | D47: 1.15 | G47: 1.15 | H47: 1.1
A48: 11 | B48: Rail - Passenger | F48: 0.8 | I48: 1.5
A49: 12 | B49: Rail - Freight | C49: 1.5 | D49: 1.2 | G49: 1.2 | I49: 2
A51: 4. FIPE data: mean price by fuel class (road types only)
A52: ID | B52: Vehicle type | C52: Battery electric vehicle (BEV) | D52: Natural gas vehicle (NGV) | E52: Gasoline vehicle | F52: Diesel vehicle | G52: Plug-in hybrid vehicle (PHEV) | H52: LPG vehicle | I52: Hydrogen (fuel-cell) vehicle
A53: 1 | B53: Road - Passenger LDV | C53: n/a | D53: n/a | E53: =IF(E68>0,AVERAGEIFS('Vehicle Price'!$K$2:$K$11633,'Vehicle Price'!$N$2:$N$11633,'Road Avg'!$A$6,'Vehicle Price'!$O$2:$O$11633,"Gasoline"),"n/a") -> 422580.76 | F53: =IF(F68>0,AVERAGEIFS('Vehicle Price'!$K$2:$K$11633,'Vehicle Price'!$N$2:$N$11633,'Road Avg'!$A$6,'Vehicle Price'!$O$2:$O$11633,"Diesel"),"n/a") -> 384177.66 | G53: =IF(G68>0,AVERAGEIFS('Vehicle Price'!$K$2:$K$11633,'Vehicle Price'!$N$2:$N$11633,'Road Avg'!$A$6,'Vehicle Price'!$O$2:$O$11633,"Plug-in hybrid"),"n/a") -> 602925.26 | H53: n/a | I53: n/a
A54: 2 | B54: Road - Passenger HDV | C54: n/a | D54: n/a | E54: =IF(E69>0,AVERAGEIFS('Vehicle Price'!$K$2:$K$11633,'Vehicle Price'!$N$2:$N$11633,'Road Avg'!$A$7,'Vehicle Price'!$O$2:$O$11633,"Gasoline"),"n/a") -> n/a | F54: =IF(F69>0,AVERAGEIFS('Vehicle Price'!$K$2:$K$11633,'Vehicle Price'!$N$2:$N$11633,'Road Avg'!$A$7,'Vehicle Price'!$O$2:$O$11633,"Diesel"),"n/a") -> 298836.74 | G54: =IF(G69>0,AVERAGEIFS('Vehicle Price'!$K$2:$K$11633,'Vehicle Price'!$N$2:$N$11633,'Road Avg'!$A$7,'Vehicle Price'!$O$2:$O$11633,"Plug-in hybrid"),"n/a") -> n/a | H54: n/a | I54: n/a
A55: 3 | B55: Road - Freight LDV | C55: n/a | D55: n/a | E55: =IF(E70>0,AVERAGEIFS('Vehicle Price'!$K$2:$K$11633,'Vehicle Price'!$N$2:$N$11633,'Road Avg'!$A$8,'Vehicle Price'!$O$2:$O$11633,"Gasoline"),"n/a") -> 136355.91 | F55: =IF(F70>0,AVERAGEIFS('Vehicle Price'!$K$2:$K$11633,'Vehicle Price'!$N$2:$N$11633,'Road Avg'!$A$8,'Vehicle Price'!$O$2:$O$11633,"Diesel"),"n/a") -> 239296.88 | G55: =IF(G70>0,AVERAGEIFS('Vehicle Price'!$K$2:$K$11633,'Vehicle Price'!$N$2:$N$11633,'Road Avg'!$A$8,'Vehicle Price'!$O$2:$O$11633,"Plug-in hybrid"),"n/a") -> n/a | H55: n/a | I55: n/a
A56: 4 | B56: Road - Freight HDV | C56: n/a | D56: n/a | E56: =IF(E71>0,AVERAGEIFS('Vehicle Price'!$K$2:$K$11633,'Vehicle Price'!$N$2:$N$11633,'Road Avg'!$A$9,'Vehicle Price'!$O$2:$O$11633,"Gasoline"),"n/a") -> n/a | F56: =IF(F71>0,AVERAGEIFS('Vehicle Price'!$K$2:$K$11633,'Vehicle Price'!$N$2:$N$11633,'Road Avg'!$A$9,'Vehicle Price'!$O$2:$O$11633,"Diesel"),"n/a") -> 295851.61 | G56: =IF(G71>0,AVERAGEIFS('Vehicle Price'!$K$2:$K$11633,'Vehicle Price'!$N$2:$N$11633,'Road Avg'!$A$9,'Vehicle Price'!$O$2:$O$11633,"Plug-in hybrid"),"n/a") -> n/a | H56: n/a | I56: n/a
A57: 5 | B57: Motorbike - Passenger | C57: n/a | D57: n/a | E57: n/a | F57: n/a | G57: n/a | H57: n/a | I57: n/a
A58: 6 | B58: Motorbike - Freight | C58: n/a | D58: n/a | E58: n/a | F58: n/a | G58: n/a | H58: n/a | I58: n/a
A59: 7 | B59: Aircraft - Passenger | C59: n/a | D59: n/a | E59: n/a | F59: n/a | G59: n/a | H59: n/a | I59: n/a
A60: 8 | B60: Aircraft - Freight | C60: n/a | D60: n/a | E60: n/a | F60: n/a | G60: n/a | H60: n/a | I60: n/a
A61: 9 | B61: Ship - Passenger | C61: n/a | D61: n/a | E61: n/a | F61: n/a | G61: n/a | H61: n/a | I61: n/a
A62: 10 | B62: Ship - Freight | C62: n/a | D62: n/a | E62: n/a | F62: n/a | G62: n/a | H62: n/a | I62: n/a
A63: 11 | B63: Rail - Passenger | C63: n/a | D63: n/a | E63: n/a | F63: n/a | G63: n/a | H63: n/a | I63: n/a
A64: 12 | B64: Rail - Freight | C64: n/a | D64: n/a | E64: n/a | F64: n/a | G64: n/a | H64: n/a | I64: n/a
A66: 5. FIPE data: number of observations by fuel class
A67: ID | B67: Vehicle type | C67: Battery electric vehicle (BEV) | D67: Natural gas vehicle (NGV) | E67: Gasoline vehicle | F67: Diesel vehicle | G67: Plug-in hybrid vehicle (PHEV) | H67: LPG vehicle | I67: Hydrogen (fuel-cell) vehicle
A68: 1 | B68: Road - Passenger LDV | C68: n/a | D68: n/a | E68: =COUNTIFS('Vehicle Price'!$N$2:$N$11633,'Road Avg'!$A$6,'Vehicle Price'!$O$2:$O$11633,"Gasoline") -> 7906 | F68: =COUNTIFS('Vehicle Price'!$N$2:$N$11633,'Road Avg'!$A$6,'Vehicle Price'!$O$2:$O$11633,"Diesel") -> 657 | G68: =COUNTIFS('Vehicle Price'!$N$2:$N$11633,'Road Avg'!$A$6,'Vehicle Price'!$O$2:$O$11633,"Plug-in hybrid") -> 405 | H68: n/a | I68: n/a
A69: 2 | B69: Road - Passenger HDV | C69: n/a | D69: n/a | E69: =COUNTIFS('Vehicle Price'!$N$2:$N$11633,'Road Avg'!$A$7,'Vehicle Price'!$O$2:$O$11633,"Gasoline") -> 0 | F69: =COUNTIFS('Vehicle Price'!$N$2:$N$11633,'Road Avg'!$A$7,'Vehicle Price'!$O$2:$O$11633,"Diesel") -> 281 | G69: =COUNTIFS('Vehicle Price'!$N$2:$N$11633,'Road Avg'!$A$7,'Vehicle Price'!$O$2:$O$11633,"Plug-in hybrid") -> 0 | H69: n/a | I69: n/a
A70: 3 | B70: Road - Freight LDV | C70: n/a | D70: n/a | E70: =COUNTIFS('Vehicle Price'!$N$2:$N$11633,'Road Avg'!$A$8,'Vehicle Price'!$O$2:$O$11633,"Gasoline") -> 522 | F70: =COUNTIFS('Vehicle Price'!$N$2:$N$11633,'Road Avg'!$A$8,'Vehicle Price'!$O$2:$O$11633,"Diesel") -> 1508 | G70: =COUNTIFS('Vehicle Price'!$N$2:$N$11633,'Road Avg'!$A$8,'Vehicle Price'!$O$2:$O$11633,"Plug-in hybrid") -> 0 | H70: n/a | I70: n/a
A71: 4 | B71: Road - Freight HDV | C71: n/a | D71: n/a | E71: =COUNTIFS('Vehicle Price'!$N$2:$N$11633,'Road Avg'!$A$9,'Vehicle Price'!$O$2:$O$11633,"Gasoline") -> 0 | F71: =COUNTIFS('Vehicle Price'!$N$2:$N$11633,'Road Avg'!$A$9,'Vehicle Price'!$O$2:$O$11633,"Diesel") -> 353 | G71: =COUNTIFS('Vehicle Price'!$N$2:$N$11633,'Road Avg'!$A$9,'Vehicle Price'!$O$2:$O$11633,"Plug-in hybrid") -> 0 | H71: n/a | I71: n/a
A72: 5 | B72: Motorbike - Passenger | C72: n/a | D72: n/a | E72: n/a | F72: n/a | G72: n/a | H72: n/a | I72: n/a
A73: 6 | B73: Motorbike - Freight | C73: n/a | D73: n/a | E73: n/a | F73: n/a | G73: n/a | H73: n/a | I73: n/a
A74: 7 | B74: Aircraft - Passenger | C74: n/a | D74: n/a | E74: n/a | F74: n/a | G74: n/a | H74: n/a | I74: n/a
A75: 8 | B75: Aircraft - Freight | C75: n/a | D75: n/a | E75: n/a | F75: n/a | G75: n/a | H75: n/a | I75: n/a
A76: 9 | B76: Ship - Passenger | C76: n/a | D76: n/a | E76: n/a | F76: n/a | G76: n/a | H76: n/a | I76: n/a
A77: 10 | B77: Ship - Freight | C77: n/a | D77: n/a | E77: n/a | F77: n/a | G77: n/a | H77: n/a | I77: n/a
A78: 11 | B78: Rail - Passenger | C78: n/a | D78: n/a | E78: n/a | F78: n/a | G78: n/a | H78: n/a | I78: n/a
A79: 12 | B79: Rail - Freight | C79: n/a | D79: n/a | E79: n/a | F79: n/a | G79: n/a | H79: n/a | I79: n/a
A81: 6. RESULT - average price by fuel, 2022 (constant 2022 R$)
A82: ID | B82: Vehicle type | C82: Battery electric vehicle (BEV) | D82: Natural gas vehicle (NGV) | E82: Gasoline vehicle | F82: Diesel vehicle | G82: Plug-in hybrid vehicle (PHEV) | H82: LPG vehicle | I82: Hydrogen (fuel-cell) vehicle | J82: Reference price (R$) | K82: Reference basis
A83: 1 | B83: Road - Passenger LDV | C83: =IFERROR(IF(C8="N","n/a",IF(C8="D",C53,IF(C8="B",$J83,IF(C8="S",C38,IF(C8="P",$J83+C38,IF(C8="X",$J83*C38,"n/a")))))),"n/a") -> 147487.33 | D83: =IFERROR(IF(D8="N","n/a",IF(D8="D",D53,IF(D8="B",$J83,IF(D8="S",D38,IF(D8="P",$J83+D38,IF(D8="X",$J83*D38,"n/a")))))),"n/a") -> 427580.76 | E83: =IFERROR(IF(E8="N","n/a",IF(E8="D",E53,IF(E8="B",$J83,IF(E8="S",E38,IF(E8="P",$J83+E38,IF(E8="X",$J83*E38,"n/a")))))),"n/a") -> 422580.76 | F83: =IFERROR(IF(F8="N","n/a",IF(F8="D",F53,IF(F8="B",$J83,IF(F8="S",F38,IF(F8="P",$J83+F38,IF(F8="X",$J83*F38,"n/a")))))),"n/a") -> 384177.66 | G83: =IFERROR(IF(G8="N","n/a",IF(G8="D",G53,IF(G8="B",$J83,IF(G8="S",G38,IF(G8="P",$J83+G38,IF(G8="X",$J83*G38,"n/a")))))),"n/a") -> 602925.26 | H83: =IFERROR(IF(H8="N","n/a",IF(H8="D",H53,IF(H8="B",$J83,IF(H8="S",H38,IF(H8="P",$J83+H38,IF(H8="X",$J83*H38,"n/a")))))),"n/a") -> n/a | I83: =IFERROR(IF(I8="N","n/a",IF(I8="D",I53,IF(I8="B",$J83,IF(I8="S",I38,IF(I8="P",$J83+I38,IF(I8="X",$J83*I38,"n/a")))))),"n/a") -> 869760.81 | J83: =IF(ISNUMBER(E53),E53,F53) -> 422580.76 | K83: ICE mean from FIPE (gasoline; diesel if none)
A84: 2 | B84: Road - Passenger HDV | C84: =IFERROR(IF(C9="N","n/a",IF(C9="D",C54,IF(C9="B",$J84,IF(C9="S",C39,IF(C9="P",$J84+C39,IF(C9="X",$J84*C39,"n/a")))))),"n/a") -> 896510.23 | D84: =IFERROR(IF(D9="N","n/a",IF(D9="D",D54,IF(D9="B",$J84,IF(D9="S",D39,IF(D9="P",$J84+D39,IF(D9="X",$J84*D39,"n/a")))))),"n/a") -> 358604.09 | E84: =IFERROR(IF(E9="N","n/a",IF(E9="D",E54,IF(E9="B",$J84,IF(E9="S",E39,IF(E9="P",$J84+E39,IF(E9="X",$J84*E39,"n/a")))))),"n/a") -> n/a | F84: =IFERROR(IF(F9="N","n/a",IF(F9="D",F54,IF(F9="B",$J84,IF(F9="S",F39,IF(F9="P",$J84+F39,IF(F9="X",$J84*F39,"n/a")))))),"n/a") -> 298836.74 | G84: =IFERROR(IF(G9="N","n/a",IF(G9="D",G54,IF(G9="B",$J84,IF(G9="S",G39,IF(G9="P",$J84+G39,IF(G9="X",$J84*G39,"n/a")))))),"n/a") -> n/a | H84: =IFERROR(IF(H9="N","n/a",IF(H9="D",H54,IF(H9="B",$J84,IF(H9="S",H39,IF(H9="P",$J84+H39,IF(H9="X",$J84*H39,"n/a")))))),"n/a") -> n/a | I84: =IFERROR(IF(I9="N","n/a",IF(I9="D",I54,IF(I9="B",$J84,IF(I9="S",I39,IF(I9="P",$J84+I39,IF(I9="X",$J84*I39,"n/a")))))),"n/a") -> 1344765.3 | J84: =IF(ISNUMBER(E54),E54,F54) -> 298836.74 | K84: ICE mean from FIPE (gasoline; diesel if none)
A85: 3 | B85: Road - Freight LDV | C85: =IFERROR(IF(C10="N","n/a",IF(C10="D",C55,IF(C10="B",$J85,IF(C10="S",C40,IF(C10="P",$J85+C40,IF(C10="X",$J85*C40,"n/a")))))),"n/a") -> 192448.68 | D85: =IFERROR(IF(D10="N","n/a",IF(D10="D",D55,IF(D10="B",$J85,IF(D10="S",D40,IF(D10="P",$J85+D40,IF(D10="X",$J85*D40,"n/a")))))),"n/a") -> 141355.91 | E85: =IFERROR(IF(E10="N","n/a",IF(E10="D",E55,IF(E10="B",$J85,IF(E10="S",E40,IF(E10="P",$J85+E40,IF(E10="X",$J85*E40,"n/a")))))),"n/a") -> 136355.91 | F85: =IFERROR(IF(F10="N","n/a",IF(F10="D",F55,IF(F10="B",$J85,IF(F10="S",F40,IF(F10="P",$J85+F40,IF(F10="X",$J85*F40,"n/a")))))),"n/a") -> 239296.88 | G85: =IFERROR(IF(G10="N","n/a",IF(G10="D",G55,IF(G10="B",$J85,IF(G10="S",G40,IF(G10="P",$J85+G40,IF(G10="X",$J85*G40,"n/a")))))),"n/a") -> n/a | H85: =IFERROR(IF(H10="N","n/a",IF(H10="D",H55,IF(H10="B",$J85,IF(H10="S",H40,IF(H10="P",$J85+H40,IF(H10="X",$J85*H40,"n/a")))))),"n/a") -> n/a | I85: =IFERROR(IF(I10="N","n/a",IF(I10="D",I55,IF(I10="B",$J85,IF(I10="S",I40,IF(I10="P",$J85+I40,IF(I10="X",$J85*I40,"n/a")))))),"n/a") -> 280649.38 | J85: =IF(ISNUMBER(E55),E55,F55) -> 136355.91 | K85: ICE mean from FIPE (gasoline; diesel if none)
A86: 4 | B86: Road - Freight HDV | C86: =IFERROR(IF(C11="N","n/a",IF(C11="D",C56,IF(C11="B",$J86,IF(C11="S",C41,IF(C11="P",$J86+C41,IF(C11="X",$J86*C41,"n/a")))))),"n/a") -> 887554.84 | D86: =IFERROR(IF(D11="N","n/a",IF(D11="D",D56,IF(D11="B",$J86,IF(D11="S",D41,IF(D11="P",$J86+D41,IF(D11="X",$J86*D41,"n/a")))))),"n/a") -> 355021.93 | E86: =IFERROR(IF(E11="N","n/a",IF(E11="D",E56,IF(E11="B",$J86,IF(E11="S",E41,IF(E11="P",$J86+E41,IF(E11="X",$J86*E41,"n/a")))))),"n/a") -> n/a | F86: =IFERROR(IF(F11="N","n/a",IF(F11="D",F56,IF(F11="B",$J86,IF(F11="S",F41,IF(F11="P",$J86+F41,IF(F11="X",$J86*F41,"n/a")))))),"n/a") -> 295851.61 | G86: =IFERROR(IF(G11="N","n/a",IF(G11="D",G56,IF(G11="B",$J86,IF(G11="S",G41,IF(G11="P",$J86+G41,IF(G11="X",$J86*G41,"n/a")))))),"n/a") -> n/a | H86: =IFERROR(IF(H11="N","n/a",IF(H11="D",H56,IF(H11="B",$J86,IF(H11="S",H41,IF(H11="P",$J86+H41,IF(H11="X",$J86*H41,"n/a")))))),"n/a") -> n/a | I86: =IFERROR(IF(I11="N","n/a",IF(I11="D",I56,IF(I11="B",$J86,IF(I11="S",I41,IF(I11="P",$J86+I41,IF(I11="X",$J86*I41,"n/a")))))),"n/a") -> 1331332.3 | J86: =IF(ISNUMBER(E56),E56,F56) -> 295851.61 | K86: ICE mean from FIPE (gasoline; diesel if none)
A87: 5 | B87: Motorbike - Passenger | C87: =IFERROR(IF(C12="N","n/a",IF(C12="D",C57,IF(C12="B",$J87,IF(C12="S",C42,IF(C12="P",$J87+C42,IF(C12="X",$J87*C42,"n/a")))))),"n/a") -> 16014 | D87: =IFERROR(IF(D12="N","n/a",IF(D12="D",D57,IF(D12="B",$J87,IF(D12="S",D42,IF(D12="P",$J87+D42,IF(D12="X",$J87*D42,"n/a")))))),"n/a") -> n/a | E87: =IFERROR(IF(E12="N","n/a",IF(E12="D",E57,IF(E12="B",$J87,IF(E12="S",E42,IF(E12="P",$J87+E42,IF(E12="X",$J87*E42,"n/a")))))),"n/a") -> 11475.445 | F87: =IFERROR(IF(F12="N","n/a",IF(F12="D",F57,IF(F12="B",$J87,IF(F12="S",F42,IF(F12="P",$J87+F42,IF(F12="X",$J87*F42,"n/a")))))),"n/a") -> n/a | G87: =IFERROR(IF(G12="N","n/a",IF(G12="D",G57,IF(G12="B",$J87,IF(G12="S",G42,IF(G12="P",$J87+G42,IF(G12="X",$J87*G42,"n/a")))))),"n/a") -> n/a | H87: =IFERROR(IF(H12="N","n/a",IF(H12="D",H57,IF(H12="B",$J87,IF(H12="S",H42,IF(H12="P",$J87+H42,IF(H12="X",$J87*H42,"n/a")))))),"n/a") -> n/a | I87: =IFERROR(IF(I12="N","n/a",IF(I12="D",I57,IF(I12="B",$J87,IF(I12="S",I42,IF(I12="P",$J87+I42,IF(I12="X",$J87*I42,"n/a")))))),"n/a") -> n/a | J87: ='NonRoad Avg'!$D$6 -> 11475.445 | K87: Base price on NonRoad_Avg
A88: 6 | B88: Motorbike - Freight | C88: =IFERROR(IF(C13="N","n/a",IF(C13="D",C58,IF(C13="B",$J88,IF(C13="S",C43,IF(C13="P",$J88+C43,IF(C13="X",$J88*C43,"n/a")))))),"n/a") -> 17566.321 | D88: =IFERROR(IF(D13="N","n/a",IF(D13="D",D58,IF(D13="B",$J88,IF(D13="S",D43,IF(D13="P",$J88+D43,IF(D13="X",$J88*D43,"n/a")))))),"n/a") -> n/a | E88: =IFERROR(IF(E13="N","n/a",IF(E13="D",E58,IF(E13="B",$J88,IF(E13="S",E43,IF(E13="P",$J88+E43,IF(E13="X",$J88*E43,"n/a")))))),"n/a") -> 12587.82 | F88: =IFERROR(IF(F13="N","n/a",IF(F13="D",F58,IF(F13="B",$J88,IF(F13="S",F43,IF(F13="P",$J88+F43,IF(F13="X",$J88*F43,"n/a")))))),"n/a") -> n/a | G88: =IFERROR(IF(G13="N","n/a",IF(G13="D",G58,IF(G13="B",$J88,IF(G13="S",G43,IF(G13="P",$J88+G43,IF(G13="X",$J88*G43,"n/a")))))),"n/a") -> n/a | H88: =IFERROR(IF(H13="N","n/a",IF(H13="D",H58,IF(H13="B",$J88,IF(H13="S",H43,IF(H13="P",$J88+H43,IF(H13="X",$J88*H43,"n/a")))))),"n/a") -> n/a | I88: =IFERROR(IF(I13="N","n/a",IF(I13="D",I58,IF(I13="B",$J88,IF(I13="S",I43,IF(I13="P",$J88+I43,IF(I13="X",$J88*I43,"n/a")))))),"n/a") -> n/a | J88: ='NonRoad Avg'!$D$7 -> 12587.82 | K88: Base price on NonRoad_Avg
A89: 7 | B89: Aircraft - Passenger | C89: =IFERROR(IF(C14="N","n/a",IF(C14="D",C59,IF(C14="B",$J89,IF(C14="S",C44,IF(C14="P",$J89+C44,IF(C14="X",$J89*C44,"n/a")))))),"n/a") -> n/a | D89: =IFERROR(IF(D14="N","n/a",IF(D14="D",D59,IF(D14="B",$J89,IF(D14="S",D44,IF(D14="P",$J89+D44,IF(D14="X",$J89*D44,"n/a")))))),"n/a") -> n/a | E89: =IFERROR(IF(E14="N","n/a",IF(E14="D",E59,IF(E14="B",$J89,IF(E14="S",E44,IF(E14="P",$J89+E44,IF(E14="X",$J89*E44,"n/a")))))),"n/a") -> 2.2354408e+08 | F89: =IFERROR(IF(F14="N","n/a",IF(F14="D",F59,IF(F14="B",$J89,IF(F14="S",F44,IF(F14="P",$J89+F44,IF(F14="X",$J89*F44,"n/a")))))),"n/a") -> n/a | G89: =IFERROR(IF(G14="N","n/a",IF(G14="D",G59,IF(G14="B",$J89,IF(G14="S",G44,IF(G14="P",$J89+G44,IF(G14="X",$J89*G44,"n/a")))))),"n/a") -> n/a | H89: =IFERROR(IF(H14="N","n/a",IF(H14="D",H59,IF(H14="B",$J89,IF(H14="S",H44,IF(H14="P",$J89+H44,IF(H14="X",$J89*H44,"n/a")))))),"n/a") -> n/a | I89: =IFERROR(IF(I14="N","n/a",IF(I14="D",I59,IF(I14="B",$J89,IF(I14="S",I44,IF(I14="P",$J89+I44,IF(I14="X",$J89*I44,"n/a")))))),"n/a") -> n/a | J89: ='NonRoad Avg'!$D$8 -> 2.2354408e+08 | K89: Base price on NonRoad_Avg (jet-fuel aircraft shown in the Gasoline column)
A90: 8 | B90: Aircraft - Freight | C90: =IFERROR(IF(C15="N","n/a",IF(C15="D",C60,IF(C15="B",$J90,IF(C15="S",C45,IF(C15="P",$J90+C45,IF(C15="X",$J90*C45,"n/a")))))),"n/a") -> n/a | D90: =IFERROR(IF(D15="N","n/a",IF(D15="D",D60,IF(D15="B",$J90,IF(D15="S",D45,IF(D15="P",$J90+D45,IF(D15="X",$J90*D45,"n/a")))))),"n/a") -> n/a | E90: =IFERROR(IF(E15="N","n/a",IF(E15="D",E60,IF(E15="B",$J90,IF(E15="S",E45,IF(E15="P",$J90+E45,IF(E15="X",$J90*E45,"n/a")))))),"n/a") -> 1.1367651e+08 | F90: =IFERROR(IF(F15="N","n/a",IF(F15="D",F60,IF(F15="B",$J90,IF(F15="S",F45,IF(F15="P",$J90+F45,IF(F15="X",$J90*F45,"n/a")))))),"n/a") -> n/a | G90: =IFERROR(IF(G15="N","n/a",IF(G15="D",G60,IF(G15="B",$J90,IF(G15="S",G45,IF(G15="P",$J90+G45,IF(G15="X",$J90*G45,"n/a")))))),"n/a") -> n/a | H90: =IFERROR(IF(H15="N","n/a",IF(H15="D",H60,IF(H15="B",$J90,IF(H15="S",H45,IF(H15="P",$J90+H45,IF(H15="X",$J90*H45,"n/a")))))),"n/a") -> n/a | I90: =IFERROR(IF(I15="N","n/a",IF(I15="D",I60,IF(I15="B",$J90,IF(I15="S",I45,IF(I15="P",$J90+I45,IF(I15="X",$J90*I45,"n/a")))))),"n/a") -> n/a | J90: ='NonRoad Avg'!$D$9 -> 1.1367651e+08 | K90: Base price on NonRoad_Avg (jet-fuel aircraft shown in the Gasoline column)
A91: 9 | B91: Ship - Passenger | C91: =IFERROR(IF(C16="N","n/a",IF(C16="D",C61,IF(C16="B",$J91,IF(C16="S",C46,IF(C16="P",$J91+C46,IF(C16="X",$J91*C46,"n/a")))))),"n/a") -> 1.2002961e+08 | D91: =IFERROR(IF(D16="N","n/a",IF(D16="D",D61,IF(D16="B",$J91,IF(D16="S",D46,IF(D16="P",$J91+D46,IF(D16="X",$J91*D46,"n/a")))))),"n/a") -> 86271285 | E91: =IFERROR(IF(E16="N","n/a",IF(E16="D",E61,IF(E16="B",$J91,IF(E16="S",E46,IF(E16="P",$J91+E46,IF(E16="X",$J91*E46,"n/a")))))),"n/a") -> n/a | F91: =IFERROR(IF(F16="N","n/a",IF(F16="D",F61,IF(F16="B",$J91,IF(F16="S",F46,IF(F16="P",$J91+F46,IF(F16="X",$J91*F46,"n/a")))))),"n/a") -> 75018509 | G91: =IFERROR(IF(G16="N","n/a",IF(G16="D",G61,IF(G16="B",$J91,IF(G16="S",G46,IF(G16="P",$J91+G46,IF(G16="X",$J91*G46,"n/a")))))),"n/a") -> 93773136 | H91: =IFERROR(IF(H16="N","n/a",IF(H16="D",H61,IF(H16="B",$J91,IF(H16="S",H46,IF(H16="P",$J91+H46,IF(H16="X",$J91*H46,"n/a")))))),"n/a") -> 82520360 | I91: =IFERROR(IF(I16="N","n/a",IF(I16="D",I61,IF(I16="B",$J91,IF(I16="S",I46,IF(I16="P",$J91+I46,IF(I16="X",$J91*I46,"n/a")))))),"n/a") -> 1.8754627e+08 | J91: ='NonRoad Avg'!$D$10 -> 75018509 | K91: Base price on NonRoad_Avg
A92: 10 | B92: Ship - Freight | C92: =IFERROR(IF(C17="N","n/a",IF(C17="D",C62,IF(C17="B",$J92,IF(C17="S",C47,IF(C17="P",$J92+C47,IF(C17="X",$J92*C47,"n/a")))))),"n/a") -> n/a | D92: =IFERROR(IF(D17="N","n/a",IF(D17="D",D62,IF(D17="B",$J92,IF(D17="S",D47,IF(D17="P",$J92+D47,IF(D17="X",$J92*D47,"n/a")))))),"n/a") -> 4.6043463e+08 | E92: =IFERROR(IF(E17="N","n/a",IF(E17="D",E62,IF(E17="B",$J92,IF(E17="S",E47,IF(E17="P",$J92+E47,IF(E17="X",$J92*E47,"n/a")))))),"n/a") -> n/a | F92: =IFERROR(IF(F17="N","n/a",IF(F17="D",F62,IF(F17="B",$J92,IF(F17="S",F47,IF(F17="P",$J92+F47,IF(F17="X",$J92*F47,"n/a")))))),"n/a") -> 4.0037794e+08 | G92: =IFERROR(IF(G17="N","n/a",IF(G17="D",G62,IF(G17="B",$J92,IF(G17="S",G47,IF(G17="P",$J92+G47,IF(G17="X",$J92*G47,"n/a")))))),"n/a") -> 4.6043463e+08 | H92: =IFERROR(IF(H17="N","n/a",IF(H17="D",H62,IF(H17="B",$J92,IF(H17="S",H47,IF(H17="P",$J92+H47,IF(H17="X",$J92*H47,"n/a")))))),"n/a") -> 4.4041573e+08 | I92: =IFERROR(IF(I17="N","n/a",IF(I17="D",I62,IF(I17="B",$J92,IF(I17="S",I47,IF(I17="P",$J92+I47,IF(I17="X",$J92*I47,"n/a")))))),"n/a") -> n/a | J92: ='NonRoad Avg'!$D$11 -> 4.0037794e+08 | K92: Base price on NonRoad_Avg
A93: 11 | B93: Rail - Passenger | C93: =IFERROR(IF(C18="N","n/a",IF(C18="D",C63,IF(C18="B",$J93,IF(C18="S",C48,IF(C18="P",$J93+C48,IF(C18="X",$J93*C48,"n/a")))))),"n/a") -> 64329558 | D93: =IFERROR(IF(D18="N","n/a",IF(D18="D",D63,IF(D18="B",$J93,IF(D18="S",D48,IF(D18="P",$J93+D48,IF(D18="X",$J93*D48,"n/a")))))),"n/a") -> n/a | E93: =IFERROR(IF(E18="N","n/a",IF(E18="D",E63,IF(E18="B",$J93,IF(E18="S",E48,IF(E18="P",$J93+E48,IF(E18="X",$J93*E48,"n/a")))))),"n/a") -> n/a | F93: =IFERROR(IF(F18="N","n/a",IF(F18="D",F63,IF(F18="B",$J93,IF(F18="S",F48,IF(F18="P",$J93+F48,IF(F18="X",$J93*F48,"n/a")))))),"n/a") -> 51463646 | G93: =IFERROR(IF(G18="N","n/a",IF(G18="D",G63,IF(G18="B",$J93,IF(G18="S",G48,IF(G18="P",$J93+G48,IF(G18="X",$J93*G48,"n/a")))))),"n/a") -> n/a | H93: =IFERROR(IF(H18="N","n/a",IF(H18="D",H63,IF(H18="B",$J93,IF(H18="S",H48,IF(H18="P",$J93+H48,IF(H18="X",$J93*H48,"n/a")))))),"n/a") -> n/a | I93: =IFERROR(IF(I18="N","n/a",IF(I18="D",I63,IF(I18="B",$J93,IF(I18="S",I48,IF(I18="P",$J93+I48,IF(I18="X",$J93*I48,"n/a")))))),"n/a") -> 96494337 | J93: ='NonRoad Avg'!$D$12 -> 64329558 | K93: Base price on NonRoad_Avg (electric trainset, so the BEV column is the baseline)
A94: 12 | B94: Rail - Freight | C94: =IFERROR(IF(C19="N","n/a",IF(C19="D",C64,IF(C19="B",$J94,IF(C19="S",C49,IF(C19="P",$J94+C49,IF(C19="X",$J94*C49,"n/a")))))),"n/a") -> 29252627 | D94: =IFERROR(IF(D19="N","n/a",IF(D19="D",D64,IF(D19="B",$J94,IF(D19="S",D49,IF(D19="P",$J94+D49,IF(D19="X",$J94*D49,"n/a")))))),"n/a") -> 23402102 | E94: =IFERROR(IF(E19="N","n/a",IF(E19="D",E64,IF(E19="B",$J94,IF(E19="S",E49,IF(E19="P",$J94+E49,IF(E19="X",$J94*E49,"n/a")))))),"n/a") -> n/a | F94: =IFERROR(IF(F19="N","n/a",IF(F19="D",F64,IF(F19="B",$J94,IF(F19="S",F49,IF(F19="P",$J94+F49,IF(F19="X",$J94*F49,"n/a")))))),"n/a") -> 19501752 | G94: =IFERROR(IF(G19="N","n/a",IF(G19="D",G64,IF(G19="B",$J94,IF(G19="S",G49,IF(G19="P",$J94+G49,IF(G19="X",$J94*G49,"n/a")))))),"n/a") -> 23402102 | H94: =IFERROR(IF(H19="N","n/a",IF(H19="D",H64,IF(H19="B",$J94,IF(H19="S",H49,IF(H19="P",$J94+H49,IF(H19="X",$J94*H49,"n/a")))))),"n/a") -> n/a | I94: =IFERROR(IF(I19="N","n/a",IF(I19="D",I64,IF(I19="B",$J94,IF(I19="S",I49,IF(I19="P",$J94+I49,IF(I19="X",$J94*I49,"n/a")))))),"n/a") -> 39003503 | J94: ='NonRoad Avg'!$D$13 -> 19501752 | K94: Base price on NonRoad_Avg
A96: 7. Price relative to the reference price (ratio)
A97: ID | B97: Vehicle type | C97: Battery electric vehicle (BEV) | D97: Natural gas vehicle (NGV) | E97: Gasoline vehicle | F97: Diesel vehicle | G97: Plug-in hybrid vehicle (PHEV) | H97: LPG vehicle | I97: Hydrogen (fuel-cell) vehicle
A98: 1 | B98: Road - Passenger LDV | C98: =IF(ISNUMBER(C83),C83/$J83,"n/a") -> 0.34901574 | D98: =IF(ISNUMBER(D83),D83/$J83,"n/a") -> 1.0118321 | E98: =IF(ISNUMBER(E83),E83/$J83,"n/a") -> 1 | F98: =IF(ISNUMBER(F83),F83/$J83,"n/a") -> 0.90912246 | G98: =IF(ISNUMBER(G83),G83/$J83,"n/a") -> 1.4267693 | H98: =IF(ISNUMBER(H83),H83/$J83,"n/a") -> n/a | I98: =IF(ISNUMBER(I83),I83/$J83,"n/a") -> 2.0582121
A99: 2 | B99: Road - Passenger HDV | C99: =IF(ISNUMBER(C84),C84/$J84,"n/a") -> 3 | D99: =IF(ISNUMBER(D84),D84/$J84,"n/a") -> 1.2 | E99: =IF(ISNUMBER(E84),E84/$J84,"n/a") -> n/a | F99: =IF(ISNUMBER(F84),F84/$J84,"n/a") -> 1 | G99: =IF(ISNUMBER(G84),G84/$J84,"n/a") -> n/a | H99: =IF(ISNUMBER(H84),H84/$J84,"n/a") -> n/a | I99: =IF(ISNUMBER(I84),I84/$J84,"n/a") -> 4.5
A100: 3 | B100: Road - Freight LDV | C100: =IF(ISNUMBER(C85),C85/$J85,"n/a") -> 1.4113703 | D100: =IF(ISNUMBER(D85),D85/$J85,"n/a") -> 1.0366687 | E100: =IF(ISNUMBER(E85),E85/$J85,"n/a") -> 1 | F100: =IF(ISNUMBER(F85),F85/$J85,"n/a") -> 1.7549432 | G100: =IF(ISNUMBER(G85),G85/$J85,"n/a") -> n/a | H100: =IF(ISNUMBER(H85),H85/$J85,"n/a") -> n/a | I100: =IF(ISNUMBER(I85),I85/$J85,"n/a") -> 2.0582121
A101: 4 | B101: Road - Freight HDV | C101: =IF(ISNUMBER(C86),C86/$J86,"n/a") -> 3 | D101: =IF(ISNUMBER(D86),D86/$J86,"n/a") -> 1.2 | E101: =IF(ISNUMBER(E86),E86/$J86,"n/a") -> n/a | F101: =IF(ISNUMBER(F86),F86/$J86,"n/a") -> 1 | G101: =IF(ISNUMBER(G86),G86/$J86,"n/a") -> n/a | H101: =IF(ISNUMBER(H86),H86/$J86,"n/a") -> n/a | I101: =IF(ISNUMBER(I86),I86/$J86,"n/a") -> 4.5
A102: 5 | B102: Motorbike - Passenger | C102: =IF(ISNUMBER(C87),C87/$J87,"n/a") -> 1.3955015 | D102: =IF(ISNUMBER(D87),D87/$J87,"n/a") -> n/a | E102: =IF(ISNUMBER(E87),E87/$J87,"n/a") -> 1 | F102: =IF(ISNUMBER(F87),F87/$J87,"n/a") -> n/a | G102: =IF(ISNUMBER(G87),G87/$J87,"n/a") -> n/a | H102: =IF(ISNUMBER(H87),H87/$J87,"n/a") -> n/a | I102: =IF(ISNUMBER(I87),I87/$J87,"n/a") -> n/a
A103: 6 | B103: Motorbike - Freight | C103: =IF(ISNUMBER(C88),C88/$J88,"n/a") -> 1.3955015 | D103: =IF(ISNUMBER(D88),D88/$J88,"n/a") -> n/a | E103: =IF(ISNUMBER(E88),E88/$J88,"n/a") -> 1 | F103: =IF(ISNUMBER(F88),F88/$J88,"n/a") -> n/a | G103: =IF(ISNUMBER(G88),G88/$J88,"n/a") -> n/a | H103: =IF(ISNUMBER(H88),H88/$J88,"n/a") -> n/a | I103: =IF(ISNUMBER(I88),I88/$J88,"n/a") -> n/a
A104: 7 | B104: Aircraft - Passenger | C104: =IF(ISNUMBER(C89),C89/$J89,"n/a") -> n/a | D104: =IF(ISNUMBER(D89),D89/$J89,"n/a") -> n/a | E104: =IF(ISNUMBER(E89),E89/$J89,"n/a") -> 1 | F104: =IF(ISNUMBER(F89),F89/$J89,"n/a") -> n/a | G104: =IF(ISNUMBER(G89),G89/$J89,"n/a") -> n/a | H104: =IF(ISNUMBER(H89),H89/$J89,"n/a") -> n/a | I104: =IF(ISNUMBER(I89),I89/$J89,"n/a") -> n/a
A105: 8 | B105: Aircraft - Freight | C105: =IF(ISNUMBER(C90),C90/$J90,"n/a") -> n/a | D105: =IF(ISNUMBER(D90),D90/$J90,"n/a") -> n/a | E105: =IF(ISNUMBER(E90),E90/$J90,"n/a") -> 1 | F105: =IF(ISNUMBER(F90),F90/$J90,"n/a") -> n/a | G105: =IF(ISNUMBER(G90),G90/$J90,"n/a") -> n/a | H105: =IF(ISNUMBER(H90),H90/$J90,"n/a") -> n/a | I105: =IF(ISNUMBER(I90),I90/$J90,"n/a") -> n/a
A106: 9 | B106: Ship - Passenger | C106: =IF(ISNUMBER(C91),C91/$J91,"n/a") -> 1.6 | D106: =IF(ISNUMBER(D91),D91/$J91,"n/a") -> 1.15 | E106: =IF(ISNUMBER(E91),E91/$J91,"n/a") -> n/a | F106: =IF(ISNUMBER(F91),F91/$J91,"n/a") -> 1 | G106: =IF(ISNUMBER(G91),G91/$J91,"n/a") -> 1.25 | H106: =IF(ISNUMBER(H91),H91/$J91,"n/a") -> 1.1 | I106: =IF(ISNUMBER(I91),I91/$J91,"n/a") -> 2.5
A107: 10 | B107: Ship - Freight | C107: =IF(ISNUMBER(C92),C92/$J92,"n/a") -> n/a | D107: =IF(ISNUMBER(D92),D92/$J92,"n/a") -> 1.15 | E107: =IF(ISNUMBER(E92),E92/$J92,"n/a") -> n/a | F107: =IF(ISNUMBER(F92),F92/$J92,"n/a") -> 1 | G107: =IF(ISNUMBER(G92),G92/$J92,"n/a") -> 1.15 | H107: =IF(ISNUMBER(H92),H92/$J92,"n/a") -> 1.1 | I107: =IF(ISNUMBER(I92),I92/$J92,"n/a") -> n/a
A108: 11 | B108: Rail - Passenger | C108: =IF(ISNUMBER(C93),C93/$J93,"n/a") -> 1 | D108: =IF(ISNUMBER(D93),D93/$J93,"n/a") -> n/a | E108: =IF(ISNUMBER(E93),E93/$J93,"n/a") -> n/a | F108: =IF(ISNUMBER(F93),F93/$J93,"n/a") -> 0.8 | G108: =IF(ISNUMBER(G93),G93/$J93,"n/a") -> n/a | H108: =IF(ISNUMBER(H93),H93/$J93,"n/a") -> n/a | I108: =IF(ISNUMBER(I93),I93/$J93,"n/a") -> 1.5
...

Sheet Fuel Forecast
A1: Forecast of average price by vehicle type and fuel, 2022-2050
A2: Real price(t) = Price 2022 x (1 + real growth of the type)^(t-2022) x premium factor(t). Premium factor(t) = (1 + (Ratio-1) x (1-convergence)^(t-2022)) / Ratio when Ratio > 1, else 1. Nominal = Real x inflation index (Forecast row 7).
A3: Scenario: | B3: =Assumptions!B7 -> Base
A6: A. Real price by fuel (constant 2022 R$)
A7: ID | B7: Vehicle type | C7: Fuel | D7: Price 2022 (R$) | E7: Reference price (R$) | F7: Ratio to reference | G7: Real growth (%/yr) | H7: Convergence (%/yr) | I7: =Assumptions!$B$4 -> 2022 | J7: =I7+1 -> 2023 | K7: =J7+1 -> 2024 | L7: =K7+1 -> 2025 | M7: =L7+1 -> 2026 | N7: =M7+1 -> 2027 | O7: =N7+1 -> 2028 | P7: =O7+1 -> 2029 | Q7: =P7+1 -> 2030 | ... AK7: =AJ7+1 -> 2050
A8: 1 | B8: Road - Passenger LDV | C8: BEV | D8: ='Fuel Price'!C83 -> 147487.33 | E8: ='Fuel Price'!$J$83 -> 422580.76 | F8: =IF(ISNUMBER(D8),D8/E8,"n/a") -> 0.34901574 | G8: =Assumptions!$E$18 -> 0 | H8: {=INDEX(Assumptions!$B$34:$B$40,MATCH($C8,Assumptions!$A$34:$A$40,0))} -> 0.03 | I8: =IF(ISNUMBER($D8),$D8*(1+$G8)^(I$7-$I$7)*IF($F8>1,(1+($F8-1)*(1-$H8)^(I$7-$I$7))/$F8,1),"n/a") -> 147487.33 | J8: =IF(ISNUMBER($D8),$D8*(1+$G8)^(J$7-$I$7)*IF($F8>1,(1+($F8-1)*(1-$H8)^(J$7-$I$7))/$F8,1),"n/a") -> 147487.33 | K8: =IF(ISNUMBER($D8),$D8*(1+$G8)^(K$7-$I$7)*IF($F8>1,(1+($F8-1)*(1-$H8)^(K$7-$I$7))/$F8,1),"n/a") -> 147487.33 | L8: =IF(ISNUMBER($D8),$D8*(1+$G8)^(L$7-$I$7)*IF($F8>1,(1+($F8-1)*(1-$H8)^(L$7-$I$7))/$F8,1),"n/a") -> 147487.33 | M8: =IF(ISNUMBER($D8),$D8*(1+$G8)^(M$7-$I$7)*IF($F8>1,(1+($F8-1)*(1-$H8)^(M$7-$I$7))/$F8,1),"n/a") -> 147487.33 | N8: =IF(ISNUMBER($D8),$D8*(1+$G8)^(N$7-$I$7)*IF($F8>1,(1+($F8-1)*(1-$H8)^(N$7-$I$7))/$F8,1),"n/a") -> 147487.33 | O8: =IF(ISNUMBER($D8),$D8*(1+$G8)^(O$7-$I$7)*IF($F8>1,(1+($F8-1)*(1-$H8)^(O$7-$I$7))/$F8,1),"n/a") -> 147487.33 | P8: =IF(ISNUMBER($D8),$D8*(1+$G8)^(P$7-$I$7)*IF($F8>1,(1+($F8-1)*(1-$H8)^(P$7-$I$7))/$F8,1),"n/a") -> 147487.33 | ... AK8: =IF(ISNUMBER($D8),$D8*(1+$G8)^(AK$7-$I$7)*IF($F8>1,(1+($F8-1)*(1-$H8)^(AK$7-$I$7))/$F8,1),"n/a") -> 147487.33
A9: 1 | B9: Road - Passenger LDV | C9: NGV | D9: ='Fuel Price'!D83 -> 427580.76 | E9: ='Fuel Price'!$J$83 -> 422580.76 | F9: =IF(ISNUMBER(D9),D9/E9,"n/a") -> 1.0118321 | G9: =Assumptions!$E$18 -> 0 | H9: {=INDEX(Assumptions!$B$34:$B$40,MATCH($C9,Assumptions!$A$34:$A$40,0))} -> 0.01 | I9: =IF(ISNUMBER($D9),$D9*(1+$G9)^(I$7-$I$7)*IF($F9>1,(1+($F9-1)*(1-$H9)^(I$7-$I$7))/$F9,1),"n/a") -> 427580.76 | J9: =IF(ISNUMBER($D9),$D9*(1+$G9)^(J$7-$I$7)*IF($F9>1,(1+($F9-1)*(1-$H9)^(J$7-$I$7))/$F9,1),"n/a") -> 427530.76 | K9: =IF(ISNUMBER($D9),$D9*(1+$G9)^(K$7-$I$7)*IF($F9>1,(1+($F9-1)*(1-$H9)^(K$7-$I$7))/$F9,1),"n/a") -> 427481.26 | L9: =IF(ISNUMBER($D9),$D9*(1+$G9)^(L$7-$I$7)*IF($F9>1,(1+($F9-1)*(1-$H9)^(L$7-$I$7))/$F9,1),"n/a") -> 427432.25 | M9: =IF(ISNUMBER($D9),$D9*(1+$G9)^(M$7-$I$7)*IF($F9>1,(1+($F9-1)*(1-$H9)^(M$7-$I$7))/$F9,1),"n/a") -> 427383.74 | N9: =IF(ISNUMBER($D9),$D9*(1+$G9)^(N$7-$I$7)*IF($F9>1,(1+($F9-1)*(1-$H9)^(N$7-$I$7))/$F9,1),"n/a") -> 427335.71 | O9: =IF(ISNUMBER($D9),$D9*(1+$G9)^(O$7-$I$7)*IF($F9>1,(1+($F9-1)*(1-$H9)^(O$7-$I$7))/$F9,1),"n/a") -> 427288.16 | P9: =IF(ISNUMBER($D9),$D9*(1+$G9)^(P$7-$I$7)*IF($F9>1,(1+($F9-1)*(1-$H9)^(P$7-$I$7))/$F9,1),"n/a") -> 427241.08 | ... AK9: =IF(ISNUMBER($D9),$D9*(1+$G9)^(AK$7-$I$7)*IF($F9>1,(1+($F9-1)*(1-$H9)^(AK$7-$I$7))/$F9,1),"n/a") -> 426354.35
A10: 1 | B10: Road - Passenger LDV | C10: Gasoline | D10: ='Fuel Price'!E83 -> 422580.76 | E10: ='Fuel Price'!$J$83 -> 422580.76 | F10: =IF(ISNUMBER(D10),D10/E10,"n/a") -> 1 | G10: =Assumptions!$E$18 -> 0 | H10: {=INDEX(Assumptions!$B$34:$B$40,MATCH($C10,Assumptions!$A$34:$A$40,0))} -> 0 | I10: =IF(ISNUMBER($D10),$D10*(1+$G10)^(I$7-$I$7)*IF($F10>1,(1+($F10-1)*(1-$H10)^(I$7-$I$7))/$F10,1),"n/a") -> 422580.76 | J10: =IF(ISNUMBER($D10),$D10*(1+$G10)^(J$7-$I$7)*IF($F10>1,(1+($F10-1)*(1-$H10)^(J$7-$I$7))/$F10,1),"n/a") -> 422580.76 | K10: =IF(ISNUMBER($D10),$D10*(1+$G10)^(K$7-$I$7)*IF($F10>1,(1+($F10-1)*(1-$H10)^(K$7-$I$7))/$F10,1),"n/a") -> 422580.76 | L10: =IF(ISNUMBER($D10),$D10*(1+$G10)^(L$7-$I$7)*IF($F10>1,(1+($F10-1)*(1-$H10)^(L$7-$I$7))/$F10,1),"n/a") -> 422580.76 | M10: =IF(ISNUMBER($D10),$D10*(1+$G10)^(M$7-$I$7)*IF($F10>1,(1+($F10-1)*(1-$H10)^(M$7-$I$7))/$F10,1),"n/a") -> 422580.76 | N10: =IF(ISNUMBER($D10),$D10*(1+$G10)^(N$7-$I$7)*IF($F10>1,(1+($F10-1)*(1-$H10)^(N$7-$I$7))/$F10,1),"n/a") -> 422580.76 | O10: =IF(ISNUMBER($D10),$D10*(1+$G10)^(O$7-$I$7)*IF($F10>1,(1+($F10-1)*(1-$H10)^(O$7-$I$7))/$F10,1),"n/a") -> 422580.76 | P10: =IF(ISNUMBER($D10),$D10*(1+$G10)^(P$7-$I$7)*IF($F10>1,(1+($F10-1)*(1-$H10)^(P$7-$I$7))/$F10,1),"n/a") -> 422580.76 | ... AK10: =IF(ISNUMBER($D10),$D10*(1+$G10)^(AK$7-$I$7)*IF($F10>1,(1+($F10-1)*(1-$H10)^(AK$7-$I$7))/$F10,1),"n/a") -> 422580.76
A11: 1 | B11: Road - Passenger LDV | C11: Diesel | D11: ='Fuel Price'!F83 -> 384177.66 | E11: ='Fuel Price'!$J$83 -> 422580.76 | F11: =IF(ISNUMBER(D11),D11/E11,"n/a") -> 0.90912246 | G11: =Assumptions!$E$18 -> 0 | H11: {=INDEX(Assumptions!$B$34:$B$40,MATCH($C11,Assumptions!$A$34:$A$40,0))} -> 0 | I11: =IF(ISNUMBER($D11),$D11*(1+$G11)^(I$7-$I$7)*IF($F11>1,(1+($F11-1)*(1-$H11)^(I$7-$I$7))/$F11,1),"n/a") -> 384177.66 | J11: =IF(ISNUMBER($D11),$D11*(1+$G11)^(J$7-$I$7)*IF($F11>1,(1+($F11-1)*(1-$H11)^(J$7-$I$7))/$F11,1),"n/a") -> 384177.66 | K11: =IF(ISNUMBER($D11),$D11*(1+$G11)^(K$7-$I$7)*IF($F11>1,(1+($F11-1)*(1-$H11)^(K$7-$I$7))/$F11,1),"n/a") -> 384177.66 | L11: =IF(ISNUMBER($D11),$D11*(1+$G11)^(L$7-$I$7)*IF($F11>1,(1+($F11-1)*(1-$H11)^(L$7-$I$7))/$F11,1),"n/a") -> 384177.66 | M11: =IF(ISNUMBER($D11),$D11*(1+$G11)^(M$7-$I$7)*IF($F11>1,(1+($F11-1)*(1-$H11)^(M$7-$I$7))/$F11,1),"n/a") -> 384177.66 | N11: =IF(ISNUMBER($D11),$D11*(1+$G11)^(N$7-$I$7)*IF($F11>1,(1+($F11-1)*(1-$H11)^(N$7-$I$7))/$F11,1),"n/a") -> 384177.66 | O11: =IF(ISNUMBER($D11),$D11*(1+$G11)^(O$7-$I$7)*IF($F11>1,(1+($F11-1)*(1-$H11)^(O$7-$I$7))/$F11,1),"n/a") -> 384177.66 | P11: =IF(ISNUMBER($D11),$D11*(1+$G11)^(P$7-$I$7)*IF($F11>1,(1+($F11-1)*(1-$H11)^(P$7-$I$7))/$F11,1),"n/a") -> 384177.66 | ... AK11: =IF(ISNUMBER($D11),$D11*(1+$G11)^(AK$7-$I$7)*IF($F11>1,(1+($F11-1)*(1-$H11)^(AK$7-$I$7))/$F11,1),"n/a") -> 384177.66
A12: 1 | B12: Road - Passenger LDV | C12: PHEV | D12: ='Fuel Price'!G83 -> 602925.26 | E12: ='Fuel Price'!$J$83 -> 422580.76 | F12: =IF(ISNUMBER(D12),D12/E12,"n/a") -> 1.4267693 | G12: =Assumptions!$E$18 -> 0 | H12: {=INDEX(Assumptions!$B$34:$B$40,MATCH($C12,Assumptions!$A$34:$A$40,0))} -> 0.02 | I12: =IF(ISNUMBER($D12),$D12*(1+$G12)^(I$7-$I$7)*IF($F12>1,(1+($F12-1)*(1-$H12)^(I$7-$I$7))/$F12,1),"n/a") -> 602925.26 | J12: =IF(ISNUMBER($D12),$D12*(1+$G12)^(J$7-$I$7)*IF($F12>1,(1+($F12-1)*(1-$H12)^(J$7-$I$7))/$F12,1),"n/a") -> 599318.37 | K12: =IF(ISNUMBER($D12),$D12*(1+$G12)^(K$7-$I$7)*IF($F12>1,(1+($F12-1)*(1-$H12)^(K$7-$I$7))/$F12,1),"n/a") -> 595783.61 | L12: =IF(ISNUMBER($D12),$D12*(1+$G12)^(L$7-$I$7)*IF($F12>1,(1+($F12-1)*(1-$H12)^(L$7-$I$7))/$F12,1),"n/a") -> 592319.56 | M12: =IF(ISNUMBER($D12),$D12*(1+$G12)^(M$7-$I$7)*IF($F12>1,(1+($F12-1)*(1-$H12)^(M$7-$I$7))/$F12,1),"n/a") -> 588924.78 | N12: =IF(ISNUMBER($D12),$D12*(1+$G12)^(N$7-$I$7)*IF($F12>1,(1+($F12-1)*(1-$H12)^(N$7-$I$7))/$F12,1),"n/a") -> 585597.9 | O12: =IF(ISNUMBER($D12),$D12*(1+$G12)^(O$7-$I$7)*IF($F12>1,(1+($F12-1)*(1-$H12)^(O$7-$I$7))/$F12,1),"n/a") -> 582337.56 | P12: =IF(ISNUMBER($D12),$D12*(1+$G12)^(P$7-$I$7)*IF($F12>1,(1+($F12-1)*(1-$H12)^(P$7-$I$7))/$F12,1),"n/a") -> 579142.42 | ... AK12: =IF(ISNUMBER($D12),$D12*(1+$G12)^(AK$7-$I$7)*IF($F12>1,(1+($F12-1)*(1-$H12)^(AK$7-$I$7))/$F12,1),"n/a") -> 525012.14
A13: 1 | B13: Road - Passenger LDV | C13: LPG | D13: ='Fuel Price'!H83 -> n/a | E13: ='Fuel Price'!$J$83 -> 422580.76 | F13: =IF(ISNUMBER(D13),D13/E13,"n/a") -> n/a | G13: =Assumptions!$E$18 -> 0 | H13: {=INDEX(Assumptions!$B$34:$B$40,MATCH($C13,Assumptions!$A$34:$A$40,0))} -> 0.01 | I13: =IF(ISNUMBER($D13),$D13*(1+$G13)^(I$7-$I$7)*IF($F13>1,(1+($F13-1)*(1-$H13)^(I$7-$I$7))/$F13,1),"n/a") -> n/a | J13: =IF(ISNUMBER($D13),$D13*(1+$G13)^(J$7-$I$7)*IF($F13>1,(1+($F13-1)*(1-$H13)^(J$7-$I$7))/$F13,1),"n/a") -> n/a | K13: =IF(ISNUMBER($D13),$D13*(1+$G13)^(K$7-$I$7)*IF($F13>1,(1+($F13-1)*(1-$H13)^(K$7-$I$7))/$F13,1),"n/a") -> n/a | L13: =IF(ISNUMBER($D13),$D13*(1+$G13)^(L$7-$I$7)*IF($F13>1,(1+($F13-1)*(1-$H13)^(L$7-$I$7))/$F13,1),"n/a") -> n/a | M13: =IF(ISNUMBER($D13),$D13*(1+$G13)^(M$7-$I$7)*IF($F13>1,(1+($F13-1)*(1-$H13)^(M$7-$I$7))/$F13,1),"n/a") -> n/a | N13: =IF(ISNUMBER($D13),$D13*(1+$G13)^(N$7-$I$7)*IF($F13>1,(1+($F13-1)*(1-$H13)^(N$7-$I$7))/$F13,1),"n/a") -> n/a | O13: =IF(ISNUMBER($D13),$D13*(1+$G13)^(O$7-$I$7)*IF($F13>1,(1+($F13-1)*(1-$H13)^(O$7-$I$7))/$F13,1),"n/a") -> n/a | P13: =IF(ISNUMBER($D13),$D13*(1+$G13)^(P$7-$I$7)*IF($F13>1,(1+($F13-1)*(1-$H13)^(P$7-$I$7))/$F13,1),"n/a") -> n/a | ... AK13: =IF(ISNUMBER($D13),$D13*(1+$G13)^(AK$7-$I$7)*IF($F13>1,(1+($F13-1)*(1-$H13)^(AK$7-$I$7))/$F13,1),"n/a") -> n/a
A14: 1 | B14: Road - Passenger LDV | C14: Hydrogen | D14: ='Fuel Price'!I83 -> 869760.81 | E14: ='Fuel Price'!$J$83 -> 422580.76 | F14: =IF(ISNUMBER(D14),D14/E14,"n/a") -> 2.0582121 | G14: =Assumptions!$E$18 -> 0 | H14: {=INDEX(Assumptions!$B$34:$B$40,MATCH($C14,Assumptions!$A$34:$A$40,0))} -> 0.03 | I14: =IF(ISNUMBER($D14),$D14*(1+$G14)^(I$7-$I$7)*IF($F14>1,(1+($F14-1)*(1-$H14)^(I$7-$I$7))/$F14,1),"n/a") -> 869760.81 | J14: =IF(ISNUMBER($D14),$D14*(1+$G14)^(J$7-$I$7)*IF($F14>1,(1+($F14-1)*(1-$H14)^(J$7-$I$7))/$F14,1),"n/a") -> 856345.41 | K14: =IF(ISNUMBER($D14),$D14*(1+$G14)^(K$7-$I$7)*IF($F14>1,(1+($F14-1)*(1-$H14)^(K$7-$I$7))/$F14,1),"n/a") -> 843332.47 | L14: =IF(ISNUMBER($D14),$D14*(1+$G14)^(L$7-$I$7)*IF($F14>1,(1+($F14-1)*(1-$H14)^(L$7-$I$7))/$F14,1),"n/a") -> 830709.92 | M14: =IF(ISNUMBER($D14),$D14*(1+$G14)^(M$7-$I$7)*IF($F14>1,(1+($F14-1)*(1-$H14)^(M$7-$I$7))/$F14,1),"n/a") -> 818466.04 | N14: =IF(ISNUMBER($D14),$D14*(1+$G14)^(N$7-$I$7)*IF($F14>1,(1+($F14-1)*(1-$H14)^(N$7-$I$7))/$F14,1),"n/a") -> 806589.49 | O14: =IF(ISNUMBER($D14),$D14*(1+$G14)^(O$7-$I$7)*IF($F14>1,(1+($F14-1)*(1-$H14)^(O$7-$I$7))/$F14,1),"n/a") -> 795069.22 | P14: =IF(ISNUMBER($D14),$D14*(1+$G14)^(P$7-$I$7)*IF($F14>1,(1+($F14-1)*(1-$H14)^(P$7-$I$7))/$F14,1),"n/a") -> 783894.57 | ... AK14: =IF(ISNUMBER($D14),$D14*(1+$G14)^(AK$7-$I$7)*IF($F14>1,(1+($F14-1)*(1-$H14)^(AK$7-$I$7))/$F14,1),"n/a") -> 613166.75
A15: 2 | B15: Road - Passenger HDV | C15: BEV | D15: ='Fuel Price'!C84 -> 896510.23 | E15: ='Fuel Price'!$J$84 -> 298836.74 | F15: =IF(ISNUMBER(D15),D15/E15,"n/a") -> 3 | G15: =Assumptions!$E$19 -> 0 | H15: {=INDEX(Assumptions!$B$34:$B$40,MATCH($C15,Assumptions!$A$34:$A$40,0))} -> 0.03 | I15: =IF(ISNUMBER($D15),$D15*(1+$G15)^(I$7-$I$7)*IF($F15>1,(1+($F15-1)*(1-$H15)^(I$7-$I$7))/$F15,1),"n/a") -> 896510.23 | J15: =IF(ISNUMBER($D15),$D15*(1+$G15)^(J$7-$I$7)*IF($F15>1,(1+($F15-1)*(1-$H15)^(J$7-$I$7))/$F15,1),"n/a") -> 878580.03 | K15: =IF(ISNUMBER($D15),$D15*(1+$G15)^(K$7-$I$7)*IF($F15>1,(1+($F15-1)*(1-$H15)^(K$7-$I$7))/$F15,1),"n/a") -> 861187.73 | L15: =IF(ISNUMBER($D15),$D15*(1+$G15)^(L$7-$I$7)*IF($F15>1,(1+($F15-1)*(1-$H15)^(L$7-$I$7))/$F15,1),"n/a") -> 844317.2 | M15: =IF(ISNUMBER($D15),$D15*(1+$G15)^(M$7-$I$7)*IF($F15>1,(1+($F15-1)*(1-$H15)^(M$7-$I$7))/$F15,1),"n/a") -> 827952.79 | N15: =IF(ISNUMBER($D15),$D15*(1+$G15)^(N$7-$I$7)*IF($F15>1,(1+($F15-1)*(1-$H15)^(N$7-$I$7))/$F15,1),"n/a") -> 812079.3 | O15: =IF(ISNUMBER($D15),$D15*(1+$G15)^(O$7-$I$7)*IF($F15>1,(1+($F15-1)*(1-$H15)^(O$7-$I$7))/$F15,1),"n/a") -> 796682.03 | P15: =IF(ISNUMBER($D15),$D15*(1+$G15)^(P$7-$I$7)*IF($F15>1,(1+($F15-1)*(1-$H15)^(P$7-$I$7))/$F15,1),"n/a") -> 781746.67 | ... AK15: =IF(ISNUMBER($D15),$D15*(1+$G15)^(AK$7-$I$7)*IF($F15>1,(1+($F15-1)*(1-$H15)^(AK$7-$I$7))/$F15,1),"n/a") -> 553562.32
A16: 2 | B16: Road - Passenger HDV | C16: NGV | D16: ='Fuel Price'!D84 -> 358604.09 | E16: ='Fuel Price'!$J$84 -> 298836.74 | F16: =IF(ISNUMBER(D16),D16/E16,"n/a") -> 1.2 | G16: =Assumptions!$E$19 -> 0 | H16: {=INDEX(Assumptions!$B$34:$B$40,MATCH($C16,Assumptions!$A$34:$A$40,0))} -> 0.01 | I16: =IF(ISNUMBER($D16),$D16*(1+$G16)^(I$7-$I$7)*IF($F16>1,(1+($F16-1)*(1-$H16)^(I$7-$I$7))/$F16,1),"n/a") -> 358604.09 | J16: =IF(ISNUMBER($D16),$D16*(1+$G16)^(J$7-$I$7)*IF($F16>1,(1+($F16-1)*(1-$H16)^(J$7-$I$7))/$F16,1),"n/a") -> 358006.42 | K16: =IF(ISNUMBER($D16),$D16*(1+$G16)^(K$7-$I$7)*IF($F16>1,(1+($F16-1)*(1-$H16)^(K$7-$I$7))/$F16,1),"n/a") -> 357414.72 | L16: =IF(ISNUMBER($D16),$D16*(1+$G16)^(L$7-$I$7)*IF($F16>1,(1+($F16-1)*(1-$H16)^(L$7-$I$7))/$F16,1),"n/a") -> 356828.94 | M16: =IF(ISNUMBER($D16),$D16*(1+$G16)^(M$7-$I$7)*IF($F16>1,(1+($F16-1)*(1-$H16)^(M$7-$I$7))/$F16,1),"n/a") -> 356249.02 | N16: =IF(ISNUMBER($D16),$D16*(1+$G16)^(N$7-$I$7)*IF($F16>1,(1+($F16-1)*(1-$H16)^(N$7-$I$7))/$F16,1),"n/a") -> 355674.9 | O16: =IF(ISNUMBER($D16),$D16*(1+$G16)^(O$7-$I$7)*IF($F16>1,(1+($F16-1)*(1-$H16)^(O$7-$I$7))/$F16,1),"n/a") -> 355106.52 | P16: =IF(ISNUMBER($D16),$D16*(1+$G16)^(P$7-$I$7)*IF($F16>1,(1+($F16-1)*(1-$H16)^(P$7-$I$7))/$F16,1),"n/a") -> 354543.82 | ... AK16: =IF(ISNUMBER($D16),$D16*(1+$G16)^(AK$7-$I$7)*IF($F16>1,(1+($F16-1)*(1-$H16)^(AK$7-$I$7))/$F16,1),"n/a") -> 343944.31
A17: 2 | B17: Road - Passenger HDV | C17: Gasoline | D17: ='Fuel Price'!E84 -> n/a | E17: ='Fuel Price'!$J$84 -> 298836.74 | F17: =IF(ISNUMBER(D17),D17/E17,"n/a") -> n/a | G17: =Assumptions!$E$19 -> 0 | H17: {=INDEX(Assumptions!$B$34:$B$40,MATCH($C17,Assumptions!$A$34:$A$40,0))} -> 0 | I17: =IF(ISNUMBER($D17),$D17*(1+$G17)^(I$7-$I$7)*IF($F17>1,(1+($F17-1)*(1-$H17)^(I$7-$I$7))/$F17,1),"n/a") -> n/a | J17: =IF(ISNUMBER($D17),$D17*(1+$G17)^(J$7-$I$7)*IF($F17>1,(1+($F17-1)*(1-$H17)^(J$7-$I$7))/$F17,1),"n/a") -> n/a | K17: =IF(ISNUMBER($D17),$D17*(1+$G17)^(K$7-$I$7)*IF($F17>1,(1+($F17-1)*(1-$H17)^(K$7-$I$7))/$F17,1),"n/a") -> n/a | L17: =IF(ISNUMBER($D17),$D17*(1+$G17)^(L$7-$I$7)*IF($F17>1,(1+($F17-1)*(1-$H17)^(L$7-$I$7))/$F17,1),"n/a") -> n/a | M17: =IF(ISNUMBER($D17),$D17*(1+$G17)^(M$7-$I$7)*IF($F17>1,(1+($F17-1)*(1-$H17)^(M$7-$I$7))/$F17,1),"n/a") -> n/a | N17: =IF(ISNUMBER($D17),$D17*(1+$G17)^(N$7-$I$7)*IF($F17>1,(1+($F17-1)*(1-$H17)^(N$7-$I$7))/$F17,1),"n/a") -> n/a | O17: =IF(ISNUMBER($D17),$D17*(1+$G17)^(O$7-$I$7)*IF($F17>1,(1+($F17-1)*(1-$H17)^(O$7-$I$7))/$F17,1),"n/a") -> n/a | P17: =IF(ISNUMBER($D17),$D17*(1+$G17)^(P$7-$I$7)*IF($F17>1,(1+($F17-1)*(1-$H17)^(P$7-$I$7))/$F17,1),"n/a") -> n/a | ... AK17: =IF(ISNUMBER($D17),$D17*(1+$G17)^(AK$7-$I$7)*IF($F17>1,(1+($F17-1)*(1-$H17)^(AK$7-$I$7))/$F17,1),"n/a") -> n/a
A18: 2 | B18: Road - Passenger HDV | C18: Diesel | D18: ='Fuel Price'!F84 -> 298836.74 | E18: ='Fuel Price'!$J$84 -> 298836.74 | F18: =IF(ISNUMBER(D18),D18/E18,"n/a") -> 1 | G18: =Assumptions!$E$19 -> 0 | H18: {=INDEX(Assumptions!$B$34:$B$40,MATCH($C18,Assumptions!$A$34:$A$40,0))} -> 0 | I18: =IF(ISNUMBER($D18),$D18*(1+$G18)^(I$7-$I$7)*IF($F18>1,(1+($F18-1)*(1-$H18)^(I$7-$I$7))/$F18,1),"n/a") -> 298836.74 | J18: =IF(ISNUMBER($D18),$D18*(1+$G18)^(J$7-$I$7)*IF($F18>1,(1+($F18-1)*(1-$H18)^(J$7-$I$7))/$F18,1),"n/a") -> 298836.74 | K18: =IF(ISNUMBER($D18),$D18*(1+$G18)^(K$7-$I$7)*IF($F18>1,(1+($F18-1)*(1-$H18)^(K$7-$I$7))/$F18,1),"n/a") -> 298836.74 | L18: =IF(ISNUMBER($D18),$D18*(1+$G18)^(L$7-$I$7)*IF($F18>1,(1+($F18-1)*(1-$H18)^(L$7-$I$7))/$F18,1),"n/a") -> 298836.74 | M18: =IF(ISNUMBER($D18),$D18*(1+$G18)^(M$7-$I$7)*IF($F18>1,(1+($F18-1)*(1-$H18)^(M$7-$I$7))/$F18,1),"n/a") -> 298836.74 | N18: =IF(ISNUMBER($D18),$D18*(1+$G18)^(N$7-$I$7)*IF($F18>1,(1+($F18-1)*(1-$H18)^(N$7-$I$7))/$F18,1),"n/a") -> 298836.74 | O18: =IF(ISNUMBER($D18),$D18*(1+$G18)^(O$7-$I$7)*IF($F18>1,(1+($F18-1)*(1-$H18)^(O$7-$I$7))/$F18,1),"n/a") -> 298836.74 | P18: =IF(ISNUMBER($D18),$D18*(1+$G18)^(P$7-$I$7)*IF($F18>1,(1+($F18-1)*(1-$H18)^(P$7-$I$7))/$F18,1),"n/a") -> 298836.74 | ... AK18: =IF(ISNUMBER($D18),$D18*(1+$G18)^(AK$7-$I$7)*IF($F18>1,(1+($F18-1)*(1-$H18)^(AK$7-$I$7))/$F18,1),"n/a") -> 298836.74
A19: 2 | B19: Road - Passenger HDV | C19: PHEV | D19: ='Fuel Price'!G84 -> n/a | E19: ='Fuel Price'!$J$84 -> 298836.74 | F19: =IF(ISNUMBER(D19),D19/E19,"n/a") -> n/a | G19: =Assumptions!$E$19 -> 0 | H19: {=INDEX(Assumptions!$B$34:$B$40,MATCH($C19,Assumptions!$A$34:$A$40,0))} -> 0.02 | I19: =IF(ISNUMBER($D19),$D19*(1+$G19)^(I$7-$I$7)*IF($F19>1,(1+($F19-1)*(1-$H19)^(I$7-$I$7))/$F19,1),"n/a") -> n/a | J19: =IF(ISNUMBER($D19),$D19*(1+$G19)^(J$7-$I$7)*IF($F19>1,(1+($F19-1)*(1-$H19)^(J$7-$I$7))/$F19,1),"n/a") -> n/a | K19: =IF(ISNUMBER($D19),$D19*(1+$G19)^(K$7-$I$7)*IF($F19>1,(1+($F19-1)*(1-$H19)^(K$7-$I$7))/$F19,1),"n/a") -> n/a | L19: =IF(ISNUMBER($D19),$D19*(1+$G19)^(L$7-$I$7)*IF($F19>1,(1+($F19-1)*(1-$H19)^(L$7-$I$7))/$F19,1),"n/a") -> n/a | M19: =IF(ISNUMBER($D19),$D19*(1+$G19)^(M$7-$I$7)*IF($F19>1,(1+($F19-1)*(1-$H19)^(M$7-$I$7))/$F19,1),"n/a") -> n/a | N19: =IF(ISNUMBER($D19),$D19*(1+$G19)^(N$7-$I$7)*IF($F19>1,(1+($F19-1)*(1-$H19)^(N$7-$I$7))/$F19,1),"n/a") -> n/a | O19: =IF(ISNUMBER($D19),$D19*(1+$G19)^(O$7-$I$7)*IF($F19>1,(1+($F19-1)*(1-$H19)^(O$7-$I$7))/$F19,1),"n/a") -> n/a | P19: =IF(ISNUMBER($D19),$D19*(1+$G19)^(P$7-$I$7)*IF($F19>1,(1+($F19-1)*(1-$H19)^(P$7-$I$7))/$F19,1),"n/a") -> n/a | ... AK19: =IF(ISNUMBER($D19),$D19*(1+$G19)^(AK$7-$I$7)*IF($F19>1,(1+($F19-1)*(1-$H19)^(AK$7-$I$7))/$F19,1),"n/a") -> n/a
A20: 2 | B20: Road - Passenger HDV | C20: LPG | D20: ='Fuel Price'!H84 -> n/a | E20: ='Fuel Price'!$J$84 -> 298836.74 | F20: =IF(ISNUMBER(D20),D20/E20,"n/a") -> n/a | G20: =Assumptions!$E$19 -> 0 | H20: {=INDEX(Assumptions!$B$34:$B$40,MATCH($C20,Assumptions!$A$34:$A$40,0))} -> 0.01 | I20: =IF(ISNUMBER($D20),$D20*(1+$G20)^(I$7-$I$7)*IF($F20>1,(1+($F20-1)*(1-$H20)^(I$7-$I$7))/$F20,1),"n/a") -> n/a | J20: =IF(ISNUMBER($D20),$D20*(1+$G20)^(J$7-$I$7)*IF($F20>1,(1+($F20-1)*(1-$H20)^(J$7-$I$7))/$F20,1),"n/a") -> n/a | K20: =IF(ISNUMBER($D20),$D20*(1+$G20)^(K$7-$I$7)*IF($F20>1,(1+($F20-1)*(1-$H20)^(K$7-$I$7))/$F20,1),"n/a") -> n/a | L20: =IF(ISNUMBER($D20),$D20*(1+$G20)^(L$7-$I$7)*IF($F20>1,(1+($F20-1)*(1-$H20)^(L$7-$I$7))/$F20,1),"n/a") -> n/a | M20: =IF(ISNUMBER($D20),$D20*(1+$G20)^(M$7-$I$7)*IF($F20>1,(1+($F20-1)*(1-$H20)^(M$7-$I$7))/$F20,1),"n/a") -> n/a | N20: =IF(ISNUMBER($D20),$D20*(1+$G20)^(N$7-$I$7)*IF($F20>1,(1+($F20-1)*(1-$H20)^(N$7-$I$7))/$F20,1),"n/a") -> n/a | O20: =IF(ISNUMBER($D20),$D20*(1+$G20)^(O$7-$I$7)*IF($F20>1,(1+($F20-1)*(1-$H20)^(O$7-$I$7))/$F20,1),"n/a") -> n/a | P20: =IF(ISNUMBER($D20),$D20*(1+$G20)^(P$7-$I$7)*IF($F20>1,(1+($F20-1)*(1-$H20)^(P$7-$I$7))/$F20,1),"n/a") -> n/a | ... AK20: =IF(ISNUMBER($D20),$D20*(1+$G20)^(AK$7-$I$7)*IF($F20>1,(1+($F20-1)*(1-$H20)^(AK$7-$I$7))/$F20,1),"n/a") -> n/a
A21: 2 | B21: Road - Passenger HDV | C21: Hydrogen | D21: ='Fuel Price'!I84 -> 1344765.3 | E21: ='Fuel Price'!$J$84 -> 298836.74 | F21: =IF(ISNUMBER(D21),D21/E21,"n/a") -> 4.5 | G21: =Assumptions!$E$19 -> 0 | H21: {=INDEX(Assumptions!$B$34:$B$40,MATCH($C21,Assumptions!$A$34:$A$40,0))} -> 0.03 | I21: =IF(ISNUMBER($D21),$D21*(1+$G21)^(I$7-$I$7)*IF($F21>1,(1+($F21-1)*(1-$H21)^(I$7-$I$7))/$F21,1),"n/a") -> 1344765.3 | J21: =IF(ISNUMBER($D21),$D21*(1+$G21)^(J$7-$I$7)*IF($F21>1,(1+($F21-1)*(1-$H21)^(J$7-$I$7))/$F21,1),"n/a") -> 1313387.5 | K21: =IF(ISNUMBER($D21),$D21*(1+$G21)^(K$7-$I$7)*IF($F21>1,(1+($F21-1)*(1-$H21)^(K$7-$I$7))/$F21,1),"n/a") -> 1282951 | L21: =IF(ISNUMBER($D21),$D21*(1+$G21)^(L$7-$I$7)*IF($F21>1,(1+($F21-1)*(1-$H21)^(L$7-$I$7))/$F21,1),"n/a") -> 1253427.5 | M21: =IF(ISNUMBER($D21),$D21*(1+$G21)^(M$7-$I$7)*IF($F21>1,(1+($F21-1)*(1-$H21)^(M$7-$I$7))/$F21,1),"n/a") -> 1224789.8 | N21: =IF(ISNUMBER($D21),$D21*(1+$G21)^(N$7-$I$7)*IF($F21>1,(1+($F21-1)*(1-$H21)^(N$7-$I$7))/$F21,1),"n/a") -> 1197011.2 | O21: =IF(ISNUMBER($D21),$D21*(1+$G21)^(O$7-$I$7)*IF($F21>1,(1+($F21-1)*(1-$H21)^(O$7-$I$7))/$F21,1),"n/a") -> 1170066 | P21: =IF(ISNUMBER($D21),$D21*(1+$G21)^(P$7-$I$7)*IF($F21>1,(1+($F21-1)*(1-$H21)^(P$7-$I$7))/$F21,1),"n/a") -> 1143929.1 | ... AK21: =IF(ISNUMBER($D21),$D21*(1+$G21)^(AK$7-$I$7)*IF($F21>1,(1+($F21-1)*(1-$H21)^(AK$7-$I$7))/$F21,1),"n/a") -> 744606.5
A22: 3 | B22: Road - Freight LDV | C22: BEV | D22: ='Fuel Price'!C85 -> 192448.68 | E22: ='Fuel Price'!$J$85 -> 136355.91 | F22: =IF(ISNUMBER(D22),D22/E22,"n/a") -> 1.4113703 | G22: =Assumptions!$E$20 -> 0 | H22: {=INDEX(Assumptions!$B$34:$B$40,MATCH($C22,Assumptions!$A$34:$A$40,0))} -> 0.03 | I22: =IF(ISNUMBER($D22),$D22*(1+$G22)^(I$7-$I$7)*IF($F22>1,(1+($F22-1)*(1-$H22)^(I$7-$I$7))/$F22,1),"n/a") -> 192448.68 | J22: =IF(ISNUMBER($D22),$D22*(1+$G22)^(J$7-$I$7)*IF($F22>1,(1+($F22-1)*(1-$H22)^(J$7-$I$7))/$F22,1),"n/a") -> 190765.9 | K22: =IF(ISNUMBER($D22),$D22*(1+$G22)^(K$7-$I$7)*IF($F22>1,(1+($F22-1)*(1-$H22)^(K$7-$I$7))/$F22,1),"n/a") -> 189133.6 | L22: =IF(ISNUMBER($D22),$D22*(1+$G22)^(L$7-$I$7)*IF($F22>1,(1+($F22-1)*(1-$H22)^(L$7-$I$7))/$F22,1),"n/a") -> 187550.27 | M22: =IF(ISNUMBER($D22),$D22*(1+$G22)^(M$7-$I$7)*IF($F22>1,(1+($F22-1)*(1-$H22)^(M$7-$I$7))/$F22,1),"n/a") -> 186014.44 | N22: =IF(ISNUMBER($D22),$D22*(1+$G22)^(N$7-$I$7)*IF($F22>1,(1+($F22-1)*(1-$H22)^(N$7-$I$7))/$F22,1),"n/a") -> 184524.68 | O22: =IF(ISNUMBER($D22),$D22*(1+$G22)^(O$7-$I$7)*IF($F22>1,(1+($F22-1)*(1-$H22)^(O$7-$I$7))/$F22,1),"n/a") -> 183079.62 | P22: =IF(ISNUMBER($D22),$D22*(1+$G22)^(P$7-$I$7)*IF($F22>1,(1+($F22-1)*(1-$H22)^(P$7-$I$7))/$F22,1),"n/a") -> 181677.91 | ... AK22: =IF(ISNUMBER($D22),$D22*(1+$G22)^(AK$7-$I$7)*IF($F22>1,(1+($F22-1)*(1-$H22)^(AK$7-$I$7))/$F22,1),"n/a") -> 160262.38
A23: 3 | B23: Road - Freight LDV | C23: NGV | D23: ='Fuel Price'!D85 -> 141355.91 | E23: ='Fuel Price'!$J$85 -> 136355.91 | F23: =IF(ISNUMBER(D23),D23/E23,"n/a") -> 1.0366687 | G23: =Assumptions!$E$20 -> 0 | H23: {=INDEX(Assumptions!$B$34:$B$40,MATCH($C23,Assumptions!$A$34:$A$40,0))} -> 0.01 | I23: =IF(ISNUMBER($D23),$D23*(1+$G23)^(I$7-$I$7)*IF($F23>1,(1+($F23-1)*(1-$H23)^(I$7-$I$7))/$F23,1),"n/a") -> 141355.91 | J23: =IF(ISNUMBER($D23),$D23*(1+$G23)^(J$7-$I$7)*IF($F23>1,(1+($F23-1)*(1-$H23)^(J$7-$I$7))/$F23,1),"n/a") -> 141305.91 | K23: =IF(ISNUMBER($D23),$D23*(1+$G23)^(K$7-$I$7)*IF($F23>1,(1+($F23-1)*(1-$H23)^(K$7-$I$7))/$F23,1),"n/a") -> 141256.41 | L23: =IF(ISNUMBER($D23),$D23*(1+$G23)^(L$7-$I$7)*IF($F23>1,(1+($F23-1)*(1-$H23)^(L$7-$I$7))/$F23,1),"n/a") -> 141207.41 | M23: =IF(ISNUMBER($D23),$D23*(1+$G23)^(M$7-$I$7)*IF($F23>1,(1+($F23-1)*(1-$H23)^(M$7-$I$7))/$F23,1),"n/a") -> 141158.89 | N23: =IF(ISNUMBER($D23),$D23*(1+$G23)^(N$7-$I$7)*IF($F23>1,(1+($F23-1)*(1-$H23)^(N$7-$I$7))/$F23,1),"n/a") -> 141110.86 | O23: =IF(ISNUMBER($D23),$D23*(1+$G23)^(O$7-$I$7)*IF($F23>1,(1+($F23-1)*(1-$H23)^(O$7-$I$7))/$F23,1),"n/a") -> 141063.31 | P23: =IF(ISNUMBER($D23),$D23*(1+$G23)^(P$7-$I$7)*IF($F23>1,(1+($F23-1)*(1-$H23)^(P$7-$I$7))/$F23,1),"n/a") -> 141016.24 | ... AK23: =IF(ISNUMBER($D23),$D23*(1+$G23)^(AK$7-$I$7)*IF($F23>1,(1+($F23-1)*(1-$H23)^(AK$7-$I$7))/$F23,1),"n/a") -> 140129.51
A24: 3 | B24: Road - Freight LDV | C24: Gasoline | D24: ='Fuel Price'!E85 -> 136355.91 | E24: ='Fuel Price'!$J$85 -> 136355.91 | F24: =IF(ISNUMBER(D24),D24/E24,"n/a") -> 1 | G24: =Assumptions!$E$20 -> 0 | H24: {=INDEX(Assumptions!$B$34:$B$40,MATCH($C24,Assumptions!$A$34:$A$40,0))} -> 0 | I24: =IF(ISNUMBER($D24),$D24*(1+$G24)^(I$7-$I$7)*IF($F24>1,(1+($F24-1)*(1-$H24)^(I$7-$I$7))/$F24,1),"n/a") -> 136355.91 | J24: =IF(ISNUMBER($D24),$D24*(1+$G24)^(J$7-$I$7)*IF($F24>1,(1+($F24-1)*(1-$H24)^(J$7-$I$7))/$F24,1),"n/a") -> 136355.91 | K24: =IF(ISNUMBER($D24),$D24*(1+$G24)^(K$7-$I$7)*IF($F24>1,(1+($F24-1)*(1-$H24)^(K$7-$I$7))/$F24,1),"n/a") -> 136355.91 | L24: =IF(ISNUMBER($D24),$D24*(1+$G24)^(L$7-$I$7)*IF($F24>1,(1+($F24-1)*(1-$H24)^(L$7-$I$7))/$F24,1),"n/a") -> 136355.91 | M24: =IF(ISNUMBER($D24),$D24*(1+$G24)^(M$7-$I$7)*IF($F24>1,(1+($F24-1)*(1-$H24)^(M$7-$I$7))/$F24,1),"n/a") -> 136355.91 | N24: =IF(ISNUMBER($D24),$D24*(1+$G24)^(N$7-$I$7)*IF($F24>1,(1+($F24-1)*(1-$H24)^(N$7-$I$7))/$F24,1),"n/a") -> 136355.91 | O24: =IF(ISNUMBER($D24),$D24*(1+$G24)^(O$7-$I$7)*IF($F24>1,(1+($F24-1)*(1-$H24)^(O$7-$I$7))/$F24,1),"n/a") -> 136355.91 | P24: =IF(ISNUMBER($D24),$D24*(1+$G24)^(P$7-$I$7)*IF($F24>1,(1+($F24-1)*(1-$H24)^(P$7-$I$7))/$F24,1),"n/a") -> 136355.91 | ... AK24: =IF(ISNUMBER($D24),$D24*(1+$G24)^(AK$7-$I$7)*IF($F24>1,(1+($F24-1)*(1-$H24)^(AK$7-$I$7))/$F24,1),"n/a") -> 136355.91
A25: 3 | B25: Road - Freight LDV | C25: Diesel | D25: ='Fuel Price'!F85 -> 239296.88 | E25: ='Fuel Price'!$J$85 -> 136355.91 | F25: =IF(ISNUMBER(D25),D25/E25,"n/a") -> 1.7549432 | G25: =Assumptions!$E$20 -> 0 | H25: {=INDEX(Assumptions!$B$34:$B$40,MATCH($C25,Assumptions!$A$34:$A$40,0))} -> 0 | I25: =IF(ISNUMBER($D25),$D25*(1+$G25)^(I$7-$I$7)*IF($F25>1,(1+($F25-1)*(1-$H25)^(I$7-$I$7))/$F25,1),"n/a") -> 239296.88 | J25: =IF(ISNUMBER($D25),$D25*(1+$G25)^(J$7-$I$7)*IF($F25>1,(1+($F25-1)*(1-$H25)^(J$7-$I$7))/$F25,1),"n/a") -> 239296.88 | K25: =IF(ISNUMBER($D25),$D25*(1+$G25)^(K$7-$I$7)*IF($F25>1,(1+($F25-1)*(1-$H25)^(K$7-$I$7))/$F25,1),"n/a") -> 239296.88 | L25: =IF(ISNUMBER($D25),$D25*(1+$G25)^(L$7-$I$7)*IF($F25>1,(1+($F25-1)*(1-$H25)^(L$7-$I$7))/$F25,1),"n/a") -> 239296.88 | M25: =IF(ISNUMBER($D25),$D25*(1+$G25)^(M$7-$I$7)*IF($F25>1,(1+($F25-1)*(1-$H25)^(M$7-$I$7))/$F25,1),"n/a") -> 239296.88 | N25: =IF(ISNUMBER($D25),$D25*(1+$G25)^(N$7-$I$7)*IF($F25>1,(1+($F25-1)*(1-$H25)^(N$7-$I$7))/$F25,1),"n/a") -> 239296.88 | O25: =IF(ISNUMBER($D25),$D25*(1+$G25)^(O$7-$I$7)*IF($F25>1,(1+($F25-1)*(1-$H25)^(O$7-$I$7))/$F25,1),"n/a") -> 239296.88 | P25: =IF(ISNUMBER($D25),$D25*(1+$G25)^(P$7-$I$7)*IF($F25>1,(1+($F25-1)*(1-$H25)^(P$7-$I$7))/$F25,1),"n/a") -> 239296.88 | ... AK25: =IF(ISNUMBER($D25),$D25*(1+$G25)^(AK$7-$I$7)*IF($F25>1,(1+($F25-1)*(1-$H25)^(AK$7-$I$7))/$F25,1),"n/a") -> 239296.88
A26: 3 | B26: Road - Freight LDV | C26: PHEV | D26: ='Fuel Price'!G85 -> n/a | E26: ='Fuel Price'!$J$85 -> 136355.91 | F26: =IF(ISNUMBER(D26),D26/E26,"n/a") -> n/a | G26: =Assumptions!$E$20 -> 0 | H26: {=INDEX(Assumptions!$B$34:$B$40,MATCH($C26,Assumptions!$A$34:$A$40,0))} -> 0.02 | I26: =IF(ISNUMBER($D26),$D26*(1+$G26)^(I$7-$I$7)*IF($F26>1,(1+($F26-1)*(1-$H26)^(I$7-$I$7))/$F26,1),"n/a") -> n/a | J26: =IF(ISNUMBER($D26),$D26*(1+$G26)^(J$7-$I$7)*IF($F26>1,(1+($F26-1)*(1-$H26)^(J$7-$I$7))/$F26,1),"n/a") -> n/a | K26: =IF(ISNUMBER($D26),$D26*(1+$G26)^(K$7-$I$7)*IF($F26>1,(1+($F26-1)*(1-$H26)^(K$7-$I$7))/$F26,1),"n/a") -> n/a | L26: =IF(ISNUMBER($D26),$D26*(1+$G26)^(L$7-$I$7)*IF($F26>1,(1+($F26-1)*(1-$H26)^(L$7-$I$7))/$F26,1),"n/a") -> n/a | M26: =IF(ISNUMBER($D26),$D26*(1+$G26)^(M$7-$I$7)*IF($F26>1,(1+($F26-1)*(1-$H26)^(M$7-$I$7))/$F26,1),"n/a") -> n/a | N26: =IF(ISNUMBER($D26),$D26*(1+$G26)^(N$7-$I$7)*IF($F26>1,(1+($F26-1)*(1-$H26)^(N$7-$I$7))/$F26,1),"n/a") -> n/a | O26: =IF(ISNUMBER($D26),$D26*(1+$G26)^(O$7-$I$7)*IF($F26>1,(1+($F26-1)*(1-$H26)^(O$7-$I$7))/$F26,1),"n/a") -> n/a | P26: =IF(ISNUMBER($D26),$D26*(1+$G26)^(P$7-$I$7)*IF($F26>1,(1+($F26-1)*(1-$H26)^(P$7-$I$7))/$F26,1),"n/a") -> n/a | ... AK26: =IF(ISNUMBER($D26),$D26*(1+$G26)^(AK$7-$I$7)*IF($F26>1,(1+($F26-1)*(1-$H26)^(AK$7-$I$7))/$F26,1),"n/a") -> n/a
A27: 3 | B27: Road - Freight LDV | C27: LPG | D27: ='Fuel Price'!H85 -> n/a | E27: ='Fuel Price'!$J$85 -> 136355.91 | F27: =IF(ISNUMBER(D27),D27/E27,"n/a") -> n/a | G27: =Assumptions!$E$20 -> 0 | H27: {=INDEX(Assumptions!$B$34:$B$40,MATCH($C27,Assumptions!$A$34:$A$40,0))} -> 0.01 | I27: =IF(ISNUMBER($D27),$D27*(1+$G27)^(I$7-$I$7)*IF($F27>1,(1+($F27-1)*(1-$H27)^(I$7-$I$7))/$F27,1),"n/a") -> n/a | J27: =IF(ISNUMBER($D27),$D27*(1+$G27)^(J$7-$I$7)*IF($F27>1,(1+($F27-1)*(1-$H27)^(J$7-$I$7))/$F27,1),"n/a") -> n/a | K27: =IF(ISNUMBER($D27),$D27*(1+$G27)^(K$7-$I$7)*IF($F27>1,(1+($F27-1)*(1-$H27)^(K$7-$I$7))/$F27,1),"n/a") -> n/a | L27: =IF(ISNUMBER($D27),$D27*(1+$G27)^(L$7-$I$7)*IF($F27>1,(1+($F27-1)*(1-$H27)^(L$7-$I$7))/$F27,1),"n/a") -> n/a | M27: =IF(ISNUMBER($D27),$D27*(1+$G27)^(M$7-$I$7)*IF($F27>1,(1+($F27-1)*(1-$H27)^(M$7-$I$7))/$F27,1),"n/a") -> n/a | N27: =IF(ISNUMBER($D27),$D27*(1+$G27)^(N$7-$I$7)*IF($F27>1,(1+($F27-1)*(1-$H27)^(N$7-$I$7))/$F27,1),"n/a") -> n/a | O27: =IF(ISNUMBER($D27),$D27*(1+$G27)^(O$7-$I$7)*IF($F27>1,(1+($F27-1)*(1-$H27)^(O$7-$I$7))/$F27,1),"n/a") -> n/a | P27: =IF(ISNUMBER($D27),$D27*(1+$G27)^(P$7-$I$7)*IF($F27>1,(1+($F27-1)*(1-$H27)^(P$7-$I$7))/$F27,1),"n/a") -> n/a | ... AK27: =IF(ISNUMBER($D27),$D27*(1+$G27)^(AK$7-$I$7)*IF($F27>1,(1+($F27-1)*(1-$H27)^(AK$7-$I$7))/$F27,1),"n/a") -> n/a
A28: 3 | B28: Road - Freight LDV | C28: Hydrogen | D28: ='Fuel Price'!I85 -> 280649.38 | E28: ='Fuel Price'!$J$85 -> 136355.91 | F28: =IF(ISNUMBER(D28),D28/E28,"n/a") -> 2.0582121 | G28: =Assumptions!$E$20 -> 0 | H28: {=INDEX(Assumptions!$B$34:$B$40,MATCH($C28,Assumptions!$A$34:$A$40,0))} -> 0.03 | I28: =IF(ISNUMBER($D28),$D28*(1+$G28)^(I$7-$I$7)*IF($F28>1,(1+($F28-1)*(1-$H28)^(I$7-$I$7))/$F28,1),"n/a") -> 280649.38 | J28: =IF(ISNUMBER($D28),$D28*(1+$G28)^(J$7-$I$7)*IF($F28>1,(1+($F28-1)*(1-$H28)^(J$7-$I$7))/$F28,1),"n/a") -> 276320.58 | K28: =IF(ISNUMBER($D28),$D28*(1+$G28)^(K$7-$I$7)*IF($F28>1,(1+($F28-1)*(1-$H28)^(K$7-$I$7))/$F28,1),"n/a") -> 272121.64 | L28: =IF(ISNUMBER($D28),$D28*(1+$G28)^(L$7-$I$7)*IF($F28>1,(1+($F28-1)*(1-$H28)^(L$7-$I$7))/$F28,1),"n/a") -> 268048.67 | M28: =IF(ISNUMBER($D28),$D28*(1+$G28)^(M$7-$I$7)*IF($F28>1,(1+($F28-1)*(1-$H28)^(M$7-$I$7))/$F28,1),"n/a") -> 264097.88 | N28: =IF(ISNUMBER($D28),$D28*(1+$G28)^(N$7-$I$7)*IF($F28>1,(1+($F28-1)*(1-$H28)^(N$7-$I$7))/$F28,1),"n/a") -> 260265.62 | O28: =IF(ISNUMBER($D28),$D28*(1+$G28)^(O$7-$I$7)*IF($F28>1,(1+($F28-1)*(1-$H28)^(O$7-$I$7))/$F28,1),"n/a") -> 256548.33 | P28: =IF(ISNUMBER($D28),$D28*(1+$G28)^(P$7-$I$7)*IF($F28>1,(1+($F28-1)*(1-$H28)^(P$7-$I$7))/$F28,1),"n/a") -> 252942.56 | ... AK28: =IF(ISNUMBER($D28),$D28*(1+$G28)^(AK$7-$I$7)*IF($F28>1,(1+($F28-1)*(1-$H28)^(AK$7-$I$7))/$F28,1),"n/a") -> 197853.1
A29: 4 | B29: Road - Freight HDV | C29: BEV | D29: ='Fuel Price'!C86 -> 887554.84 | E29: ='Fuel Price'!$J$86 -> 295851.61 | F29: =IF(ISNUMBER(D29),D29/E29,"n/a") -> 3 | G29: =Assumptions!$E$21 -> 0 | H29: {=INDEX(Assumptions!$B$34:$B$40,MATCH($C29,Assumptions!$A$34:$A$40,0))} -> 0.03 | I29: =IF(ISNUMBER($D29),$D29*(1+$G29)^(I$7-$I$7)*IF($F29>1,(1+($F29-1)*(1-$H29)^(I$7-$I$7))/$F29,1),"n/a") -> 887554.84 | J29: =IF(ISNUMBER($D29),$D29*(1+$G29)^(J$7-$I$7)*IF($F29>1,(1+($F29-1)*(1-$H29)^(J$7-$I$7))/$F29,1),"n/a") -> 869803.74 | K29: =IF(ISNUMBER($D29),$D29*(1+$G29)^(K$7-$I$7)*IF($F29>1,(1+($F29-1)*(1-$H29)^(K$7-$I$7))/$F29,1),"n/a") -> 852585.18 | L29: =IF(ISNUMBER($D29),$D29*(1+$G29)^(L$7-$I$7)*IF($F29>1,(1+($F29-1)*(1-$H29)^(L$7-$I$7))/$F29,1),"n/a") -> 835883.17 | M29: =IF(ISNUMBER($D29),$D29*(1+$G29)^(M$7-$I$7)*IF($F29>1,(1+($F29-1)*(1-$H29)^(M$7-$I$7))/$F29,1),"n/a") -> 819682.22 | N29: =IF(ISNUMBER($D29),$D29*(1+$G29)^(N$7-$I$7)*IF($F29>1,(1+($F29-1)*(1-$H29)^(N$7-$I$7))/$F29,1),"n/a") -> 803967.3 | O29: =IF(ISNUMBER($D29),$D29*(1+$G29)^(O$7-$I$7)*IF($F29>1,(1+($F29-1)*(1-$H29)^(O$7-$I$7))/$F29,1),"n/a") -> 788723.83 | P29: =IF(ISNUMBER($D29),$D29*(1+$G29)^(P$7-$I$7)*IF($F29>1,(1+($F29-1)*(1-$H29)^(P$7-$I$7))/$F29,1),"n/a") -> 773937.67 | ... AK29: =IF(ISNUMBER($D29),$D29*(1+$G29)^(AK$7-$I$7)*IF($F29>1,(1+($F29-1)*(1-$H29)^(AK$7-$I$7))/$F29,1),"n/a") -> 548032.69
A30: 4 | B30: Road - Freight HDV | C30: NGV | D30: ='Fuel Price'!D86 -> 355021.93 | E30: ='Fuel Price'!$J$86 -> 295851.61 | F30: =IF(ISNUMBER(D30),D30/E30,"n/a") -> 1.2 | G30: =Assumptions!$E$21 -> 0 | H30: {=INDEX(Assumptions!$B$34:$B$40,MATCH($C30,Assumptions!$A$34:$A$40,0))} -> 0.01 | I30: =IF(ISNUMBER($D30),$D30*(1+$G30)^(I$7-$I$7)*IF($F30>1,(1+($F30-1)*(1-$H30)^(I$7-$I$7))/$F30,1),"n/a") -> 355021.93 | J30: =IF(ISNUMBER($D30),$D30*(1+$G30)^(J$7-$I$7)*IF($F30>1,(1+($F30-1)*(1-$H30)^(J$7-$I$7))/$F30,1),"n/a") -> 354430.23 | K30: =IF(ISNUMBER($D30),$D30*(1+$G30)^(K$7-$I$7)*IF($F30>1,(1+($F30-1)*(1-$H30)^(K$7-$I$7))/$F30,1),"n/a") -> 353844.44 | L30: =IF(ISNUMBER($D30),$D30*(1+$G30)^(L$7-$I$7)*IF($F30>1,(1+($F30-1)*(1-$H30)^(L$7-$I$7))/$F30,1),"n/a") -> 353264.52 | M30: =IF(ISNUMBER($D30),$D30*(1+$G30)^(M$7-$I$7)*IF($F30>1,(1+($F30-1)*(1-$H30)^(M$7-$I$7))/$F30,1),"n/a") -> 352690.39 | N30: =IF(ISNUMBER($D30),$D30*(1+$G30)^(N$7-$I$7)*IF($F30>1,(1+($F30-1)*(1-$H30)^(N$7-$I$7))/$F30,1),"n/a") -> 352122 | O30: =IF(ISNUMBER($D30),$D30*(1+$G30)^(O$7-$I$7)*IF($F30>1,(1+($F30-1)*(1-$H30)^(O$7-$I$7))/$F30,1),"n/a") -> 351559.3 | P30: =IF(ISNUMBER($D30),$D30*(1+$G30)^(P$7-$I$7)*IF($F30>1,(1+($F30-1)*(1-$H30)^(P$7-$I$7))/$F30,1),"n/a") -> 351002.22 | ... AK30: =IF(ISNUMBER($D30),$D30*(1+$G30)^(AK$7-$I$7)*IF($F30>1,(1+($F30-1)*(1-$H30)^(AK$7-$I$7))/$F30,1),"n/a") -> 340508.6
A31: 4 | B31: Road - Freight HDV | C31: Gasoline | D31: ='Fuel Price'!E86 -> n/a | E31: ='Fuel Price'!$J$86 -> 295851.61 | F31: =IF(ISNUMBER(D31),D31/E31,"n/a") -> n/a | G31: =Assumptions!$E$21 -> 0 | H31: {=INDEX(Assumptions!$B$34:$B$40,MATCH($C31,Assumptions!$A$34:$A$40,0))} -> 0 | I31: =IF(ISNUMBER($D31),$D31*(1+$G31)^(I$7-$I$7)*IF($F31>1,(1+($F31-1)*(1-$H31)^(I$7-$I$7))/$F31,1),"n/a") -> n/a | J31: =IF(ISNUMBER($D31),$D31*(1+$G31)^(J$7-$I$7)*IF($F31>1,(1+($F31-1)*(1-$H31)^(J$7-$I$7))/$F31,1),"n/a") -> n/a | K31: =IF(ISNUMBER($D31),$D31*(1+$G31)^(K$7-$I$7)*IF($F31>1,(1+($F31-1)*(1-$H31)^(K$7-$I$7))/$F31,1),"n/a") -> n/a | L31: =IF(ISNUMBER($D31),$D31*(1+$G31)^(L$7-$I$7)*IF($F31>1,(1+($F31-1)*(1-$H31)^(L$7-$I$7))/$F31,1),"n/a") -> n/a | M31: =IF(ISNUMBER($D31),$D31*(1+$G31)^(M$7-$I$7)*IF($F31>1,(1+($F31-1)*(1-$H31)^(M$7-$I$7))/$F31,1),"n/a") -> n/a | N31: =IF(ISNUMBER($D31),$D31*(1+$G31)^(N$7-$I$7)*IF($F31>1,(1+($F31-1)*(1-$H31)^(N$7-$I$7))/$F31,1),"n/a") -> n/a | O31: =IF(ISNUMBER($D31),$D31*(1+$G31)^(O$7-$I$7)*IF($F31>1,(1+($F31-1)*(1-$H31)^(O$7-$I$7))/$F31,1),"n/a") -> n/a | P31: =IF(ISNUMBER($D31),$D31*(1+$G31)^(P$7-$I$7)*IF($F31>1,(1+($F31-1)*(1-$H31)^(P$7-$I$7))/$F31,1),"n/a") -> n/a | ... AK31: =IF(ISNUMBER($D31),$D31*(1+$G31)^(AK$7-$I$7)*IF($F31>1,(1+($F31-1)*(1-$H31)^(AK$7-$I$7))/$F31,1),"n/a") -> n/a
A32: 4 | B32: Road - Freight HDV | C32: Diesel | D32: ='Fuel Price'!F86 -> 295851.61 | E32: ='Fuel Price'!$J$86 -> 295851.61 | F32: =IF(ISNUMBER(D32),D32/E32,"n/a") -> 1 | G32: =Assumptions!$E$21 -> 0 | H32: {=INDEX(Assumptions!$B$34:$B$40,MATCH($C32,Assumptions!$A$34:$A$40,0))} -> 0 | I32: =IF(ISNUMBER($D32),$D32*(1+$G32)^(I$7-$I$7)*IF($F32>1,(1+($F32-1)*(1-$H32)^(I$7-$I$7))/$F32,1),"n/a") -> 295851.61 | J32: =IF(ISNUMBER($D32),$D32*(1+$G32)^(J$7-$I$7)*IF($F32>1,(1+($F32-1)*(1-$H32)^(J$7-$I$7))/$F32,1),"n/a") -> 295851.61 | K32: =IF(ISNUMBER($D32),$D32*(1+$G32)^(K$7-$I$7)*IF($F32>1,(1+($F32-1)*(1-$H32)^(K$7-$I$7))/$F32,1),"n/a") -> 295851.61 | L32: =IF(ISNUMBER($D32),$D32*(1+$G32)^(L$7-$I$7)*IF($F32>1,(1+($F32-1)*(1-$H32)^(L$7-$I$7))/$F32,1),"n/a") -> 295851.61 | M32: =IF(ISNUMBER($D32),$D32*(1+$G32)^(M$7-$I$7)*IF($F32>1,(1+($F32-1)*(1-$H32)^(M$7-$I$7))/$F32,1),"n/a") -> 295851.61 | N32: =IF(ISNUMBER($D32),$D32*(1+$G32)^(N$7-$I$7)*IF($F32>1,(1+($F32-1)*(1-$H32)^(N$7-$I$7))/$F32,1),"n/a") -> 295851.61 | O32: =IF(ISNUMBER($D32),$D32*(1+$G32)^(O$7-$I$7)*IF($F32>1,(1+($F32-1)*(1-$H32)^(O$7-$I$7))/$F32,1),"n/a") -> 295851.61 | P32: =IF(ISNUMBER($D32),$D32*(1+$G32)^(P$7-$I$7)*IF($F32>1,(1+($F32-1)*(1-$H32)^(P$7-$I$7))/$F32,1),"n/a") -> 295851.61 | ... AK32: =IF(ISNUMBER($D32),$D32*(1+$G32)^(AK$7-$I$7)*IF($F32>1,(1+($F32-1)*(1-$H32)^(AK$7-$I$7))/$F32,1),"n/a") -> 295851.61
A33: 4 | B33: Road - Freight HDV | C33: PHEV | D33: ='Fuel Price'!G86 -> n/a | E33: ='Fuel Price'!$J$86 -> 295851.61 | F33: =IF(ISNUMBER(D33),D33/E33,"n/a") -> n/a | G33: =Assumptions!$E$21 -> 0 | H33: {=INDEX(Assumptions!$B$34:$B$40,MATCH($C33,Assumptions!$A$34:$A$40,0))} -> 0.02 | I33: =IF(ISNUMBER($D33),$D33*(1+$G33)^(I$7-$I$7)*IF($F33>1,(1+($F33-1)*(1-$H33)^(I$7-$I$7))/$F33,1),"n/a") -> n/a | J33: =IF(ISNUMBER($D33),$D33*(1+$G33)^(J$7-$I$7)*IF($F33>1,(1+($F33-1)*(1-$H33)^(J$7-$I$7))/$F33,1),"n/a") -> n/a | K33: =IF(ISNUMBER($D33),$D33*(1+$G33)^(K$7-$I$7)*IF($F33>1,(1+($F33-1)*(1-$H33)^(K$7-$I$7))/$F33,1),"n/a") -> n/a | L33: =IF(ISNUMBER($D33),$D33*(1+$G33)^(L$7-$I$7)*IF($F33>1,(1+($F33-1)*(1-$H33)^(L$7-$I$7))/$F33,1),"n/a") -> n/a | M33: =IF(ISNUMBER($D33),$D33*(1+$G33)^(M$7-$I$7)*IF($F33>1,(1+($F33-1)*(1-$H33)^(M$7-$I$7))/$F33,1),"n/a") -> n/a | N33: =IF(ISNUMBER($D33),$D33*(1+$G33)^(N$7-$I$7)*IF($F33>1,(1+($F33-1)*(1-$H33)^(N$7-$I$7))/$F33,1),"n/a") -> n/a | O33: =IF(ISNUMBER($D33),$D33*(1+$G33)^(O$7-$I$7)*IF($F33>1,(1+($F33-1)*(1-$H33)^(O$7-$I$7))/$F33,1),"n/a") -> n/a | P33: =IF(ISNUMBER($D33),$D33*(1+$G33)^(P$7-$I$7)*IF($F33>1,(1+($F33-1)*(1-$H33)^(P$7-$I$7))/$F33,1),"n/a") -> n/a | ... AK33: =IF(ISNUMBER($D33),$D33*(1+$G33)^(AK$7-$I$7)*IF($F33>1,(1+($F33-1)*(1-$H33)^(AK$7-$I$7))/$F33,1),"n/a") -> n/a
A34: 4 | B34: Road - Freight HDV | C34: LPG | D34: ='Fuel Price'!H86 -> n/a | E34: ='Fuel Price'!$J$86 -> 295851.61 | F34: =IF(ISNUMBER(D34),D34/E34,"n/a") -> n/a | G34: =Assumptions!$E$21 -> 0 | H34: {=INDEX(Assumptions!$B$34:$B$40,MATCH($C34,Assumptions!$A$34:$A$40,0))} -> 0.01 | I34: =IF(ISNUMBER($D34),$D34*(1+$G34)^(I$7-$I$7)*IF($F34>1,(1+($F34-1)*(1-$H34)^(I$7-$I$7))/$F34,1),"n/a") -> n/a | J34: =IF(ISNUMBER($D34),$D34*(1+$G34)^(J$7-$I$7)*IF($F34>1,(1+($F34-1)*(1-$H34)^(J$7-$I$7))/$F34,1),"n/a") -> n/a | K34: =IF(ISNUMBER($D34),$D34*(1+$G34)^(K$7-$I$7)*IF($F34>1,(1+($F34-1)*(1-$H34)^(K$7-$I$7))/$F34,1),"n/a") -> n/a | L34: =IF(ISNUMBER($D34),$D34*(1+$G34)^(L$7-$I$7)*IF($F34>1,(1+($F34-1)*(1-$H34)^(L$7-$I$7))/$F34,1),"n/a") -> n/a | M34: =IF(ISNUMBER($D34),$D34*(1+$G34)^(M$7-$I$7)*IF($F34>1,(1+($F34-1)*(1-$H34)^(M$7-$I$7))/$F34,1),"n/a") -> n/a | N34: =IF(ISNUMBER($D34),$D34*(1+$G34)^(N$7-$I$7)*IF($F34>1,(1+($F34-1)*(1-$H34)^(N$7-$I$7))/$F34,1),"n/a") -> n/a | O34: =IF(ISNUMBER($D34),$D34*(1+$G34)^(O$7-$I$7)*IF($F34>1,(1+($F34-1)*(1-$H34)^(O$7-$I$7))/$F34,1),"n/a") -> n/a | P34: =IF(ISNUMBER($D34),$D34*(1+$G34)^(P$7-$I$7)*IF($F34>1,(1+($F34-1)*(1-$H34)^(P$7-$I$7))/$F34,1),"n/a") -> n/a | ... AK34: =IF(ISNUMBER($D34),$D34*(1+$G34)^(AK$7-$I$7)*IF($F34>1,(1+($F34-1)*(1-$H34)^(AK$7-$I$7))/$F34,1),"n/a") -> n/a
A35: 4 | B35: Road - Freight HDV | C35: Hydrogen | D35: ='Fuel Price'!I86 -> 1331332.3 | E35: ='Fuel Price'!$J$86 -> 295851.61 | F35: =IF(ISNUMBER(D35),D35/E35,"n/a") -> 4.5 | G35: =Assumptions!$E$21 -> 0 | H35: {=INDEX(Assumptions!$B$34:$B$40,MATCH($C35,Assumptions!$A$34:$A$40,0))} -> 0.03 | I35: =IF(ISNUMBER($D35),$D35*(1+$G35)^(I$7-$I$7)*IF($F35>1,(1+($F35-1)*(1-$H35)^(I$7-$I$7))/$F35,1),"n/a") -> 1331332.3 | J35: =IF(ISNUMBER($D35),$D35*(1+$G35)^(J$7-$I$7)*IF($F35>1,(1+($F35-1)*(1-$H35)^(J$7-$I$7))/$F35,1),"n/a") -> 1300267.8 | K35: =IF(ISNUMBER($D35),$D35*(1+$G35)^(K$7-$I$7)*IF($F35>1,(1+($F35-1)*(1-$H35)^(K$7-$I$7))/$F35,1),"n/a") -> 1270135.3 | L35: =IF(ISNUMBER($D35),$D35*(1+$G35)^(L$7-$I$7)*IF($F35>1,(1+($F35-1)*(1-$H35)^(L$7-$I$7))/$F35,1),"n/a") -> 1240906.8 | M35: =IF(ISNUMBER($D35),$D35*(1+$G35)^(M$7-$I$7)*IF($F35>1,(1+($F35-1)*(1-$H35)^(M$7-$I$7))/$F35,1),"n/a") -> 1212555.2 | N35: =IF(ISNUMBER($D35),$D35*(1+$G35)^(N$7-$I$7)*IF($F35>1,(1+($F35-1)*(1-$H35)^(N$7-$I$7))/$F35,1),"n/a") -> 1185054.1 | O35: =IF(ISNUMBER($D35),$D35*(1+$G35)^(O$7-$I$7)*IF($F35>1,(1+($F35-1)*(1-$H35)^(O$7-$I$7))/$F35,1),"n/a") -> 1158378 | P35: =IF(ISNUMBER($D35),$D35*(1+$G35)^(P$7-$I$7)*IF($F35>1,(1+($F35-1)*(1-$H35)^(P$7-$I$7))/$F35,1),"n/a") -> 1132502.2 | ... AK35: =IF(ISNUMBER($D35),$D35*(1+$G35)^(AK$7-$I$7)*IF($F35>1,(1+($F35-1)*(1-$H35)^(AK$7-$I$7))/$F35,1),"n/a") -> 737168.5
A36: 5 | B36: Motorbike - Passenger | C36: BEV | D36: ='Fuel Price'!C87 -> 16014 | E36: ='Fuel Price'!$J$87 -> 11475.445 | F36: =IF(ISNUMBER(D36),D36/E36,"n/a") -> 1.3955015 | G36: =Assumptions!$E$22 -> 0 | H36: {=INDEX(Assumptions!$B$34:$B$40,MATCH($C36,Assumptions!$A$34:$A$40,0))} -> 0.03 | I36: =IF(ISNUMBER($D36),$D36*(1+$G36)^(I$7-$I$7)*IF($F36>1,(1+($F36-1)*(1-$H36)^(I$7-$I$7))/$F36,1),"n/a") -> 16014 | J36: =IF(ISNUMBER($D36),$D36*(1+$G36)^(J$7-$I$7)*IF($F36>1,(1+($F36-1)*(1-$H36)^(J$7-$I$7))/$F36,1),"n/a") -> 15877.843 | K36: =IF(ISNUMBER($D36),$D36*(1+$G36)^(K$7-$I$7)*IF($F36>1,(1+($F36-1)*(1-$H36)^(K$7-$I$7))/$F36,1),"n/a") -> 15745.771 | L36: =IF(ISNUMBER($D36),$D36*(1+$G36)^(L$7-$I$7)*IF($F36>1,(1+($F36-1)*(1-$H36)^(L$7-$I$7))/$F36,1),"n/a") -> 15617.662 | M36: =IF(ISNUMBER($D36),$D36*(1+$G36)^(M$7-$I$7)*IF($F36>1,(1+($F36-1)*(1-$H36)^(M$7-$I$7))/$F36,1),"n/a") -> 15493.395 | N36: =IF(ISNUMBER($D36),$D36*(1+$G36)^(N$7-$I$7)*IF($F36>1,(1+($F36-1)*(1-$H36)^(N$7-$I$7))/$F36,1),"n/a") -> 15372.857 | O36: =IF(ISNUMBER($D36),$D36*(1+$G36)^(O$7-$I$7)*IF($F36>1,(1+($F36-1)*(1-$H36)^(O$7-$I$7))/$F36,1),"n/a") -> 15255.934 | P36: =IF(ISNUMBER($D36),$D36*(1+$G36)^(P$7-$I$7)*IF($F36>1,(1+($F36-1)*(1-$H36)^(P$7-$I$7))/$F36,1),"n/a") -> 15142.52 | ... AK36: =IF(ISNUMBER($D36),$D36*(1+$G36)^(AK$7-$I$7)*IF($F36>1,(1+($F36-1)*(1-$H36)^(AK$7-$I$7))/$F36,1),"n/a") -> 13409.755
A37: 5 | B37: Motorbike - Passenger | C37: NGV | D37: ='Fuel Price'!D87 -> n/a | E37: ='Fuel Price'!$J$87 -> 11475.445 | F37: =IF(ISNUMBER(D37),D37/E37,"n/a") -> n/a | G37: =Assumptions!$E$22 -> 0 | H37: {=INDEX(Assumptions!$B$34:$B$40,MATCH($C37,Assumptions!$A$34:$A$40,0))} -> 0.01 | I37: =IF(ISNUMBER($D37),$D37*(1+$G37)^(I$7-$I$7)*IF($F37>1,(1+($F37-1)*(1-$H37)^(I$7-$I$7))/$F37,1),"n/a") -> n/a | J37: =IF(ISNUMBER($D37),$D37*(1+$G37)^(J$7-$I$7)*IF($F37>1,(1+($F37-1)*(1-$H37)^(J$7-$I$7))/$F37,1),"n/a") -> n/a | K37: =IF(ISNUMBER($D37),$D37*(1+$G37)^(K$7-$I$7)*IF($F37>1,(1+($F37-1)*(1-$H37)^(K$7-$I$7))/$F37,1),"n/a") -> n/a | L37: =IF(ISNUMBER($D37),$D37*(1+$G37)^(L$7-$I$7)*IF($F37>1,(1+($F37-1)*(1-$H37)^(L$7-$I$7))/$F37,1),"n/a") -> n/a | M37: =IF(ISNUMBER($D37),$D37*(1+$G37)^(M$7-$I$7)*IF($F37>1,(1+($F37-1)*(1-$H37)^(M$7-$I$7))/$F37,1),"n/a") -> n/a | N37: =IF(ISNUMBER($D37),$D37*(1+$G37)^(N$7-$I$7)*IF($F37>1,(1+($F37-1)*(1-$H37)^(N$7-$I$7))/$F37,1),"n/a") -> n/a | O37: =IF(ISNUMBER($D37),$D37*(1+$G37)^(O$7-$I$7)*IF($F37>1,(1+($F37-1)*(1-$H37)^(O$7-$I$7))/$F37,1),"n/a") -> n/a | P37: =IF(ISNUMBER($D37),$D37*(1+$G37)^(P$7-$I$7)*IF($F37>1,(1+($F37-1)*(1-$H37)^(P$7-$I$7))/$F37,1),"n/a") -> n/a | ... AK37: =IF(ISNUMBER($D37),$D37*(1+$G37)^(AK$7-$I$7)*IF($F37>1,(1+($F37-1)*(1-$H37)^(AK$7-$I$7))/$F37,1),"n/a") -> n/a
A38: 5 | B38: Motorbike - Passenger | C38: Gasoline | D38: ='Fuel Price'!E87 -> 11475.445 | E38: ='Fuel Price'!$J$87 -> 11475.445 | F38: =IF(ISNUMBER(D38),D38/E38,"n/a") -> 1 | G38: =Assumptions!$E$22 -> 0 | H38: {=INDEX(Assumptions!$B$34:$B$40,MATCH($C38,Assumptions!$A$34:$A$40,0))} -> 0 | I38: =IF(ISNUMBER($D38),$D38*(1+$G38)^(I$7-$I$7)*IF($F38>1,(1+($F38-1)*(1-$H38)^(I$7-$I$7))/$F38,1),"n/a") -> 11475.445 | J38: =IF(ISNUMBER($D38),$D38*(1+$G38)^(J$7-$I$7)*IF($F38>1,(1+($F38-1)*(1-$H38)^(J$7-$I$7))/$F38,1),"n/a") -> 11475.445 | K38: =IF(ISNUMBER($D38),$D38*(1+$G38)^(K$7-$I$7)*IF($F38>1,(1+($F38-1)*(1-$H38)^(K$7-$I$7))/$F38,1),"n/a") -> 11475.445 | L38: =IF(ISNUMBER($D38),$D38*(1+$G38)^(L$7-$I$7)*IF($F38>1,(1+($F38-1)*(1-$H38)^(L$7-$I$7))/$F38,1),"n/a") -> 11475.445 | M38: =IF(ISNUMBER($D38),$D38*(1+$G38)^(M$7-$I$7)*IF($F38>1,(1+($F38-1)*(1-$H38)^(M$7-$I$7))/$F38,1),"n/a") -> 11475.445 | N38: =IF(ISNUMBER($D38),$D38*(1+$G38)^(N$7-$I$7)*IF($F38>1,(1+($F38-1)*(1-$H38)^(N$7-$I$7))/$F38,1),"n/a") -> 11475.445 | O38: =IF(ISNUMBER($D38),$D38*(1+$G38)^(O$7-$I$7)*IF($F38>1,(1+($F38-1)*(1-$H38)^(O$7-$I$7))/$F38,1),"n/a") -> 11475.445 | P38: =IF(ISNUMBER($D38),$D38*(1+$G38)^(P$7-$I$7)*IF($F38>1,(1+($F38-1)*(1-$H38)^(P$7-$I$7))/$F38,1),"n/a") -> 11475.445 | ... AK38: =IF(ISNUMBER($D38),$D38*(1+$G38)^(AK$7-$I$7)*IF($F38>1,(1+($F38-1)*(1-$H38)^(AK$7-$I$7))/$F38,1),"n/a") -> 11475.445
A39: 5 | B39: Motorbike - Passenger | C39: Diesel | D39: ='Fuel Price'!F87 -> n/a | E39: ='Fuel Price'!$J$87 -> 11475.445 | F39: =IF(ISNUMBER(D39),D39/E39,"n/a") -> n/a | G39: =Assumptions!$E$22 -> 0 | H39: {=INDEX(Assumptions!$B$34:$B$40,MATCH($C39,Assumptions!$A$34:$A$40,0))} -> 0 | I39: =IF(ISNUMBER($D39),$D39*(1+$G39)^(I$7-$I$7)*IF($F39>1,(1+($F39-1)*(1-$H39)^(I$7-$I$7))/$F39,1),"n/a") -> n/a | J39: =IF(ISNUMBER($D39),$D39*(1+$G39)^(J$7-$I$7)*IF($F39>1,(1+($F39-1)*(1-$H39)^(J$7-$I$7))/$F39,1),"n/a") -> n/a | K39: =IF(ISNUMBER($D39),$D39*(1+$G39)^(K$7-$I$7)*IF($F39>1,(1+($F39-1)*(1-$H39)^(K$7-$I$7))/$F39,1),"n/a") -> n/a | L39: =IF(ISNUMBER($D39),$D39*(1+$G39)^(L$7-$I$7)*IF($F39>1,(1+($F39-1)*(1-$H39)^(L$7-$I$7))/$F39,1),"n/a") -> n/a | M39: =IF(ISNUMBER($D39),$D39*(1+$G39)^(M$7-$I$7)*IF($F39>1,(1+($F39-1)*(1-$H39)^(M$7-$I$7))/$F39,1),"n/a") -> n/a | N39: =IF(ISNUMBER($D39),$D39*(1+$G39)^(N$7-$I$7)*IF($F39>1,(1+($F39-1)*(1-$H39)^(N$7-$I$7))/$F39,1),"n/a") -> n/a | O39: =IF(ISNUMBER($D39),$D39*(1+$G39)^(O$7-$I$7)*IF($F39>1,(1+($F39-1)*(1-$H39)^(O$7-$I$7))/$F39,1),"n/a") -> n/a | P39: =IF(ISNUMBER($D39),$D39*(1+$G39)^(P$7-$I$7)*IF($F39>1,(1+($F39-1)*(1-$H39)^(P$7-$I$7))/$F39,1),"n/a") -> n/a | ... AK39: =IF(ISNUMBER($D39),$D39*(1+$G39)^(AK$7-$I$7)*IF($F39>1,(1+($F39-1)*(1-$H39)^(AK$7-$I$7))/$F39,1),"n/a") -> n/a
A40: 5 | B40: Motorbike - Passenger | C40: PHEV | D40: ='Fuel Price'!G87 -> n/a | E40: ='Fuel Price'!$J$87 -> 11475.445 | F40: =IF(ISNUMBER(D40),D40/E40,"n/a") -> n/a | G40: =Assumptions!$E$22 -> 0 | H40: {=INDEX(Assumptions!$B$34:$B$40,MATCH($C40,Assumptions!$A$34:$A$40,0))} -> 0.02 | I40: =IF(ISNUMBER($D40),$D40*(1+$G40)^(I$7-$I$7)*IF($F40>1,(1+($F40-1)*(1-$H40)^(I$7-$I$7))/$F40,1),"n/a") -> n/a | J40: =IF(ISNUMBER($D40),$D40*(1+$G40)^(J$7-$I$7)*IF($F40>1,(1+($F40-1)*(1-$H40)^(J$7-$I$7))/$F40,1),"n/a") -> n/a | K40: =IF(ISNUMBER($D40),$D40*(1+$G40)^(K$7-$I$7)*IF($F40>1,(1+($F40-1)*(1-$H40)^(K$7-$I$7))/$F40,1),"n/a") -> n/a | L40: =IF(ISNUMBER($D40),$D40*(1+$G40)^(L$7-$I$7)*IF($F40>1,(1+($F40-1)*(1-$H40)^(L$7-$I$7))/$F40,1),"n/a") -> n/a | M40: =IF(ISNUMBER($D40),$D40*(1+$G40)^(M$7-$I$7)*IF($F40>1,(1+($F40-1)*(1-$H40)^(M$7-$I$7))/$F40,1),"n/a") -> n/a | N40: =IF(ISNUMBER($D40),$D40*(1+$G40)^(N$7-$I$7)*IF($F40>1,(1+($F40-1)*(1-$H40)^(N$7-$I$7))/$F40,1),"n/a") -> n/a | O40: =IF(ISNUMBER($D40),$D40*(1+$G40)^(O$7-$I$7)*IF($F40>1,(1+($F40-1)*(1-$H40)^(O$7-$I$7))/$F40,1),"n/a") -> n/a | P40: =IF(ISNUMBER($D40),$D40*(1+$G40)^(P$7-$I$7)*IF($F40>1,(1+($F40-1)*(1-$H40)^(P$7-$I$7))/$F40,1),"n/a") -> n/a | ... AK40: =IF(ISNUMBER($D40),$D40*(1+$G40)^(AK$7-$I$7)*IF($F40>1,(1+($F40-1)*(1-$H40)^(AK$7-$I$7))/$F40,1),"n/a") -> n/a
A41: 5 | B41: Motorbike - Passenger | C41: LPG | D41: ='Fuel Price'!H87 -> n/a | E41: ='Fuel Price'!$J$87 -> 11475.445 | F41: =IF(ISNUMBER(D41),D41/E41,"n/a") -> n/a | G41: =Assumptions!$E$22 -> 0 | H41: {=INDEX(Assumptions!$B$34:$B$40,MATCH($C41,Assumptions!$A$34:$A$40,0))} -> 0.01 | I41: =IF(ISNUMBER($D41),$D41*(1+$G41)^(I$7-$I$7)*IF($F41>1,(1+($F41-1)*(1-$H41)^(I$7-$I$7))/$F41,1),"n/a") -> n/a | J41: =IF(ISNUMBER($D41),$D41*(1+$G41)^(J$7-$I$7)*IF($F41>1,(1+($F41-1)*(1-$H41)^(J$7-$I$7))/$F41,1),"n/a") -> n/a | K41: =IF(ISNUMBER($D41),$D41*(1+$G41)^(K$7-$I$7)*IF($F41>1,(1+($F41-1)*(1-$H41)^(K$7-$I$7))/$F41,1),"n/a") -> n/a | L41: =IF(ISNUMBER($D41),$D41*(1+$G41)^(L$7-$I$7)*IF($F41>1,(1+($F41-1)*(1-$H41)^(L$7-$I$7))/$F41,1),"n/a") -> n/a | M41: =IF(ISNUMBER($D41),$D41*(1+$G41)^(M$7-$I$7)*IF($F41>1,(1+($F41-1)*(1-$H41)^(M$7-$I$7))/$F41,1),"n/a") -> n/a | N41: =IF(ISNUMBER($D41),$D41*(1+$G41)^(N$7-$I$7)*IF($F41>1,(1+($F41-1)*(1-$H41)^(N$7-$I$7))/$F41,1),"n/a") -> n/a | O41: =IF(ISNUMBER($D41),$D41*(1+$G41)^(O$7-$I$7)*IF($F41>1,(1+($F41-1)*(1-$H41)^(O$7-$I$7))/$F41,1),"n/a") -> n/a | P41: =IF(ISNUMBER($D41),$D41*(1+$G41)^(P$7-$I$7)*IF($F41>1,(1+($F41-1)*(1-$H41)^(P$7-$I$7))/$F41,1),"n/a") -> n/a | ... AK41: =IF(ISNUMBER($D41),$D41*(1+$G41)^(AK$7-$I$7)*IF($F41>1,(1+($F41-1)*(1-$H41)^(AK$7-$I$7))/$F41,1),"n/a") -> n/a
A42: 5 | B42: Motorbike - Passenger | C42: Hydrogen | D42: ='Fuel Price'!I87 -> n/a | E42: ='Fuel Price'!$J$87 -> 11475.445 | F42: =IF(ISNUMBER(D42),D42/E42,"n/a") -> n/a | G42: =Assumptions!$E$22 -> 0 | H42: {=INDEX(Assumptions!$B$34:$B$40,MATCH($C42,Assumptions!$A$34:$A$40,0))} -> 0.03 | I42: =IF(ISNUMBER($D42),$D42*(1+$G42)^(I$7-$I$7)*IF($F42>1,(1+($F42-1)*(1-$H42)^(I$7-$I$7))/$F42,1),"n/a") -> n/a | J42: =IF(ISNUMBER($D42),$D42*(1+$G42)^(J$7-$I$7)*IF($F42>1,(1+($F42-1)*(1-$H42)^(J$7-$I$7))/$F42,1),"n/a") -> n/a | K42: =IF(ISNUMBER($D42),$D42*(1+$G42)^(K$7-$I$7)*IF($F42>1,(1+($F42-1)*(1-$H42)^(K$7-$I$7))/$F42,1),"n/a") -> n/a | L42: =IF(ISNUMBER($D42),$D42*(1+$G42)^(L$7-$I$7)*IF($F42>1,(1+($F42-1)*(1-$H42)^(L$7-$I$7))/$F42,1),"n/a") -> n/a | M42: =IF(ISNUMBER($D42),$D42*(1+$G42)^(M$7-$I$7)*IF($F42>1,(1+($F42-1)*(1-$H42)^(M$7-$I$7))/$F42,1),"n/a") -> n/a | N42: =IF(ISNUMBER($D42),$D42*(1+$G42)^(N$7-$I$7)*IF($F42>1,(1+($F42-1)*(1-$H42)^(N$7-$I$7))/$F42,1),"n/a") -> n/a | O42: =IF(ISNUMBER($D42),$D42*(1+$G42)^(O$7-$I$7)*IF($F42>1,(1+($F42-1)*(1-$H42)^(O$7-$I$7))/$F42,1),"n/a") -> n/a | P42: =IF(ISNUMBER($D42),$D42*(1+$G42)^(P$7-$I$7)*IF($F42>1,(1+($F42-1)*(1-$H42)^(P$7-$I$7))/$F42,1),"n/a") -> n/a | ... AK42: =IF(ISNUMBER($D42),$D42*(1+$G42)^(AK$7-$I$7)*IF($F42>1,(1+($F42-1)*(1-$H42)^(AK$7-$I$7))/$F42,1),"n/a") -> n/a
A43: 6 | B43: Motorbike - Freight | C43: BEV | D43: ='Fuel Price'!C88 -> 17566.321 | E43: ='Fuel Price'!$J$88 -> 12587.82 | F43: =IF(ISNUMBER(D43),D43/E43,"n/a") -> 1.3955015 | G43: =Assumptions!$E$23 -> 0 | H43: {=INDEX(Assumptions!$B$34:$B$40,MATCH($C43,Assumptions!$A$34:$A$40,0))} -> 0.03 | I43: =IF(ISNUMBER($D43),$D43*(1+$G43)^(I$7-$I$7)*IF($F43>1,(1+($F43-1)*(1-$H43)^(I$7-$I$7))/$F43,1),"n/a") -> 17566.321 | J43: =IF(ISNUMBER($D43),$D43*(1+$G43)^(J$7-$I$7)*IF($F43>1,(1+($F43-1)*(1-$H43)^(J$7-$I$7))/$F43,1),"n/a") -> 17416.966 | K43: =IF(ISNUMBER($D43),$D43*(1+$G43)^(K$7-$I$7)*IF($F43>1,(1+($F43-1)*(1-$H43)^(K$7-$I$7))/$F43,1),"n/a") -> 17272.092 | L43: =IF(ISNUMBER($D43),$D43*(1+$G43)^(L$7-$I$7)*IF($F43>1,(1+($F43-1)*(1-$H43)^(L$7-$I$7))/$F43,1),"n/a") -> 17131.564 | M43: =IF(ISNUMBER($D43),$D43*(1+$G43)^(M$7-$I$7)*IF($F43>1,(1+($F43-1)*(1-$H43)^(M$7-$I$7))/$F43,1),"n/a") -> 16995.251 | N43: =IF(ISNUMBER($D43),$D43*(1+$G43)^(N$7-$I$7)*IF($F43>1,(1+($F43-1)*(1-$H43)^(N$7-$I$7))/$F43,1),"n/a") -> 16863.028 | O43: =IF(ISNUMBER($D43),$D43*(1+$G43)^(O$7-$I$7)*IF($F43>1,(1+($F43-1)*(1-$H43)^(O$7-$I$7))/$F43,1),"n/a") -> 16734.772 | P43: =IF(ISNUMBER($D43),$D43*(1+$G43)^(P$7-$I$7)*IF($F43>1,(1+($F43-1)*(1-$H43)^(P$7-$I$7))/$F43,1),"n/a") -> 16610.364 | ... AK43: =IF(ISNUMBER($D43),$D43*(1+$G43)^(AK$7-$I$7)*IF($F43>1,(1+($F43-1)*(1-$H43)^(AK$7-$I$7))/$F43,1),"n/a") -> 14709.633
A44: 6 | B44: Motorbike - Freight | C44: NGV | D44: ='Fuel Price'!D88 -> n/a | E44: ='Fuel Price'!$J$88 -> 12587.82 | F44: =IF(ISNUMBER(D44),D44/E44,"n/a") -> n/a | G44: =Assumptions!$E$23 -> 0 | H44: {=INDEX(Assumptions!$B$34:$B$40,MATCH($C44,Assumptions!$A$34:$A$40,0))} -> 0.01 | I44: =IF(ISNUMBER($D44),$D44*(1+$G44)^(I$7-$I$7)*IF($F44>1,(1+($F44-1)*(1-$H44)^(I$7-$I$7))/$F44,1),"n/a") -> n/a | J44: =IF(ISNUMBER($D44),$D44*(1+$G44)^(J$7-$I$7)*IF($F44>1,(1+($F44-1)*(1-$H44)^(J$7-$I$7))/$F44,1),"n/a") -> n/a | K44: =IF(ISNUMBER($D44),$D44*(1+$G44)^(K$7-$I$7)*IF($F44>1,(1+($F44-1)*(1-$H44)^(K$7-$I$7))/$F44,1),"n/a") -> n/a | L44: =IF(ISNUMBER($D44),$D44*(1+$G44)^(L$7-$I$7)*IF($F44>1,(1+($F44-1)*(1-$H44)^(L$7-$I$7))/$F44,1),"n/a") -> n/a | M44: =IF(ISNUMBER($D44),$D44*(1+$G44)^(M$7-$I$7)*IF($F44>1,(1+($F44-1)*(1-$H44)^(M$7-$I$7))/$F44,1),"n/a") -> n/a | N44: =IF(ISNUMBER($D44),$D44*(1+$G44)^(N$7-$I$7)*IF($F44>1,(1+($F44-1)*(1-$H44)^(N$7-$I$7))/$F44,1),"n/a") -> n/a | O44: =IF(ISNUMBER($D44),$D44*(1+$G44)^(O$7-$I$7)*IF($F44>1,(1+($F44-1)*(1-$H44)^(O$7-$I$7))/$F44,1),"n/a") -> n/a | P44: =IF(ISNUMBER($D44),$D44*(1+$G44)^(P$7-$I$7)*IF($F44>1,(1+($F44-1)*(1-$H44)^(P$7-$I$7))/$F44,1),"n/a") -> n/a | ... AK44: =IF(ISNUMBER($D44),$D44*(1+$G44)^(AK$7-$I$7)*IF($F44>1,(1+($F44-1)*(1-$H44)^(AK$7-$I$7))/$F44,1),"n/a") -> n/a
A45: 6 | B45: Motorbike - Freight | C45: Gasoline | D45: ='Fuel Price'!E88 -> 12587.82 | E45: ='Fuel Price'!$J$88 -> 12587.82 | F45: =IF(ISNUMBER(D45),D45/E45,"n/a") -> 1 | G45: =Assumptions!$E$23 -> 0 | H45: {=INDEX(Assumptions!$B$34:$B$40,MATCH($C45,Assumptions!$A$34:$A$40,0))} -> 0 | I45: =IF(ISNUMBER($D45),$D45*(1+$G45)^(I$7-$I$7)*IF($F45>1,(1+($F45-1)*(1-$H45)^(I$7-$I$7))/$F45,1),"n/a") -> 12587.82 | J45: =IF(ISNUMBER($D45),$D45*(1+$G45)^(J$7-$I$7)*IF($F45>1,(1+($F45-1)*(1-$H45)^(J$7-$I$7))/$F45,1),"n/a") -> 12587.82 | K45: =IF(ISNUMBER($D45),$D45*(1+$G45)^(K$7-$I$7)*IF($F45>1,(1+($F45-1)*(1-$H45)^(K$7-$I$7))/$F45,1),"n/a") -> 12587.82 | L45: =IF(ISNUMBER($D45),$D45*(1+$G45)^(L$7-$I$7)*IF($F45>1,(1+($F45-1)*(1-$H45)^(L$7-$I$7))/$F45,1),"n/a") -> 12587.82 | M45: =IF(ISNUMBER($D45),$D45*(1+$G45)^(M$7-$I$7)*IF($F45>1,(1+($F45-1)*(1-$H45)^(M$7-$I$7))/$F45,1),"n/a") -> 12587.82 | N45: =IF(ISNUMBER($D45),$D45*(1+$G45)^(N$7-$I$7)*IF($F45>1,(1+($F45-1)*(1-$H45)^(N$7-$I$7))/$F45,1),"n/a") -> 12587.82 | O45: =IF(ISNUMBER($D45),$D45*(1+$G45)^(O$7-$I$7)*IF($F45>1,(1+($F45-1)*(1-$H45)^(O$7-$I$7))/$F45,1),"n/a") -> 12587.82 | P45: =IF(ISNUMBER($D45),$D45*(1+$G45)^(P$7-$I$7)*IF($F45>1,(1+($F45-1)*(1-$H45)^(P$7-$I$7))/$F45,1),"n/a") -> 12587.82 | ... AK45: =IF(ISNUMBER($D45),$D45*(1+$G45)^(AK$7-$I$7)*IF($F45>1,(1+($F45-1)*(1-$H45)^(AK$7-$I$7))/$F45,1),"n/a") -> 12587.82
A46: 6 | B46: Motorbike - Freight | C46: Diesel | D46: ='Fuel Price'!F88 -> n/a | E46: ='Fuel Price'!$J$88 -> 12587.82 | F46: =IF(ISNUMBER(D46),D46/E46,"n/a") -> n/a | G46: =Assumptions!$E$23 -> 0 | H46: {=INDEX(Assumptions!$B$34:$B$40,MATCH($C46,Assumptions!$A$34:$A$40,0))} -> 0 | I46: =IF(ISNUMBER($D46),$D46*(1+$G46)^(I$7-$I$7)*IF($F46>1,(1+($F46-1)*(1-$H46)^(I$7-$I$7))/$F46,1),"n/a") -> n/a | J46: =IF(ISNUMBER($D46),$D46*(1+$G46)^(J$7-$I$7)*IF($F46>1,(1+($F46-1)*(1-$H46)^(J$7-$I$7))/$F46,1),"n/a") -> n/a | K46: =IF(ISNUMBER($D46),$D46*(1+$G46)^(K$7-$I$7)*IF($F46>1,(1+($F46-1)*(1-$H46)^(K$7-$I$7))/$F46,1),"n/a") -> n/a | L46: =IF(ISNUMBER($D46),$D46*(1+$G46)^(L$7-$I$7)*IF($F46>1,(1+($F46-1)*(1-$H46)^(L$7-$I$7))/$F46,1),"n/a") -> n/a | M46: =IF(ISNUMBER($D46),$D46*(1+$G46)^(M$7-$I$7)*IF($F46>1,(1+($F46-1)*(1-$H46)^(M$7-$I$7))/$F46,1),"n/a") -> n/a | N46: =IF(ISNUMBER($D46),$D46*(1+$G46)^(N$7-$I$7)*IF($F46>1,(1+($F46-1)*(1-$H46)^(N$7-$I$7))/$F46,1),"n/a") -> n/a | O46: =IF(ISNUMBER($D46),$D46*(1+$G46)^(O$7-$I$7)*IF($F46>1,(1+($F46-1)*(1-$H46)^(O$7-$I$7))/$F46,1),"n/a") -> n/a | P46: =IF(ISNUMBER($D46),$D46*(1+$G46)^(P$7-$I$7)*IF($F46>1,(1+($F46-1)*(1-$H46)^(P$7-$I$7))/$F46,1),"n/a") -> n/a | ... AK46: =IF(ISNUMBER($D46),$D46*(1+$G46)^(AK$7-$I$7)*IF($F46>1,(1+($F46-1)*(1-$H46)^(AK$7-$I$7))/$F46,1),"n/a") -> n/a
A47: 6 | B47: Motorbike - Freight | C47: PHEV | D47: ='Fuel Price'!G88 -> n/a | E47: ='Fuel Price'!$J$88 -> 12587.82 | F47: =IF(ISNUMBER(D47),D47/E47,"n/a") -> n/a | G47: =Assumptions!$E$23 -> 0 | H47: {=INDEX(Assumptions!$B$34:$B$40,MATCH($C47,Assumptions!$A$34:$A$40,0))} -> 0.02 | I47: =IF(ISNUMBER($D47),$D47*(1+$G47)^(I$7-$I$7)*IF($F47>1,(1+($F47-1)*(1-$H47)^(I$7-$I$7))/$F47,1),"n/a") -> n/a | J47: =IF(ISNUMBER($D47),$D47*(1+$G47)^(J$7-$I$7)*IF($F47>1,(1+($F47-1)*(1-$H47)^(J$7-$I$7))/$F47,1),"n/a") -> n/a | K47: =IF(ISNUMBER($D47),$D47*(1+$G47)^(K$7-$I$7)*IF($F47>1,(1+($F47-1)*(1-$H47)^(K$7-$I$7))/$F47,1),"n/a") -> n/a | L47: =IF(ISNUMBER($D47),$D47*(1+$G47)^(L$7-$I$7)*IF($F47>1,(1+($F47-1)*(1-$H47)^(L$7-$I$7))/$F47,1),"n/a") -> n/a | M47: =IF(ISNUMBER($D47),$D47*(1+$G47)^(M$7-$I$7)*IF($F47>1,(1+($F47-1)*(1-$H47)^(M$7-$I$7))/$F47,1),"n/a") -> n/a | N47: =IF(ISNUMBER($D47),$D47*(1+$G47)^(N$7-$I$7)*IF($F47>1,(1+($F47-1)*(1-$H47)^(N$7-$I$7))/$F47,1),"n/a") -> n/a | O47: =IF(ISNUMBER($D47),$D47*(1+$G47)^(O$7-$I$7)*IF($F47>1,(1+($F47-1)*(1-$H47)^(O$7-$I$7))/$F47,1),"n/a") -> n/a | P47: =IF(ISNUMBER($D47),$D47*(1+$G47)^(P$7-$I$7)*IF($F47>1,(1+($F47-1)*(1-$H47)^(P$7-$I$7))/$F47,1),"n/a") -> n/a | ... AK47: =IF(ISNUMBER($D47),$D47*(1+$G47)^(AK$7-$I$7)*IF($F47>1,(1+($F47-1)*(1-$H47)^(AK$7-$I$7))/$F47,1),"n/a") -> n/a
A48: 6 | B48: Motorbike - Freight | C48: LPG | D48: ='Fuel Price'!H88 -> n/a | E48: ='Fuel Price'!$J$88 -> 12587.82 | F48: =IF(ISNUMBER(D48),D48/E48,"n/a") -> n/a | G48: =Assumptions!$E$23 -> 0 | H48: {=INDEX(Assumptions!$B$34:$B$40,MATCH($C48,Assumptions!$A$34:$A$40,0))} -> 0.01 | I48: =IF(ISNUMBER($D48),$D48*(1+$G48)^(I$7-$I$7)*IF($F48>1,(1+($F48-1)*(1-$H48)^(I$7-$I$7))/$F48,1),"n/a") -> n/a | J48: =IF(ISNUMBER($D48),$D48*(1+$G48)^(J$7-$I$7)*IF($F48>1,(1+($F48-1)*(1-$H48)^(J$7-$I$7))/$F48,1),"n/a") -> n/a | K48: =IF(ISNUMBER($D48),$D48*(1+$G48)^(K$7-$I$7)*IF($F48>1,(1+($F48-1)*(1-$H48)^(K$7-$I$7))/$F48,1),"n/a") -> n/a | L48: =IF(ISNUMBER($D48),$D48*(1+$G48)^(L$7-$I$7)*IF($F48>1,(1+($F48-1)*(1-$H48)^(L$7-$I$7))/$F48,1),"n/a") -> n/a | M48: =IF(ISNUMBER($D48),$D48*(1+$G48)^(M$7-$I$7)*IF($F48>1,(1+($F48-1)*(1-$H48)^(M$7-$I$7))/$F48,1),"n/a") -> n/a | N48: =IF(ISNUMBER($D48),$D48*(1+$G48)^(N$7-$I$7)*IF($F48>1,(1+($F48-1)*(1-$H48)^(N$7-$I$7))/$F48,1),"n/a") -> n/a | O48: =IF(ISNUMBER($D48),$D48*(1+$G48)^(O$7-$I$7)*IF($F48>1,(1+($F48-1)*(1-$H48)^(O$7-$I$7))/$F48,1),"n/a") -> n/a | P48: =IF(ISNUMBER($D48),$D48*(1+$G48)^(P$7-$I$7)*IF($F48>1,(1+($F48-1)*(1-$H48)^(P$7-$I$7))/$F48,1),"n/a") -> n/a | ... AK48: =IF(ISNUMBER($D48),$D48*(1+$G48)^(AK$7-$I$7)*IF($F48>1,(1+($F48-1)*(1-$H48)^(AK$7-$I$7))/$F48,1),"n/a") -> n/a
A49: 6 | B49: Motorbike - Freight | C49: Hydrogen | D49: ='Fuel Price'!I88 -> n/a | E49: ='Fuel Price'!$J$88 -> 12587.82 | F49: =IF(ISNUMBER(D49),D49/E49,"n/a") -> n/a | G49: =Assumptions!$E$23 -> 0 | H49: {=INDEX(Assumptions!$B$34:$B$40,MATCH($C49,Assumptions!$A$34:$A$40,0))} -> 0.03 | I49: =IF(ISNUMBER($D49),$D49*(1+$G49)^(I$7-$I$7)*IF($F49>1,(1+($F49-1)*(1-$H49)^(I$7-$I$7))/$F49,1),"n/a") -> n/a | J49: =IF(ISNUMBER($D49),$D49*(1+$G49)^(J$7-$I$7)*IF($F49>1,(1+($F49-1)*(1-$H49)^(J$7-$I$7))/$F49,1),"n/a") -> n/a | K49: =IF(ISNUMBER($D49),$D49*(1+$G49)^(K$7-$I$7)*IF($F49>1,(1+($F49-1)*(1-$H49)^(K$7-$I$7))/$F49,1),"n/a") -> n/a | L49: =IF(ISNUMBER($D49),$D49*(1+$G49)^(L$7-$I$7)*IF($F49>1,(1+($F49-1)*(1-$H49)^(L$7-$I$7))/$F49,1),"n/a") -> n/a | M49: =IF(ISNUMBER($D49),$D49*(1+$G49)^(M$7-$I$7)*IF($F49>1,(1+($F49-1)*(1-$H49)^(M$7-$I$7))/$F49,1),"n/a") -> n/a | N49: =IF(ISNUMBER($D49),$D49*(1+$G49)^(N$7-$I$7)*IF($F49>1,(1+($F49-1)*(1-$H49)^(N$7-$I$7))/$F49,1),"n/a") -> n/a | O49: =IF(ISNUMBER($D49),$D49*(1+$G49)^(O$7-$I$7)*IF($F49>1,(1+($F49-1)*(1-$H49)^(O$7-$I$7))/$F49,1),"n/a") -> n/a | P49: =IF(ISNUMBER($D49),$D49*(1+$G49)^(P$7-$I$7)*IF($F49>1,(1+($F49-1)*(1-$H49)^(P$7-$I$7))/$F49,1),"n/a") -> n/a | ... AK49: =IF(ISNUMBER($D49),$D49*(1+$G49)^(AK$7-$I$7)*IF($F49>1,(1+($F49-1)*(1-$H49)^(AK$7-$I$7))/$F49,1),"n/a") -> n/a
A50: 7 | B50: Aircraft - Passenger | C50: BEV | D50: ='Fuel Price'!C89 -> n/a | E50: ='Fuel Price'!$J$89 -> 2.2354408e+08 | F50: =IF(ISNUMBER(D50),D50/E50,"n/a") -> n/a | G50: =Assumptions!$E$24 -> 0 | H50: {=INDEX(Assumptions!$B$34:$B$40,MATCH($C50,Assumptions!$A$34:$A$40,0))} -> 0.03 | I50: =IF(ISNUMBER($D50),$D50*(1+$G50)^(I$7-$I$7)*IF($F50>1,(1+($F50-1)*(1-$H50)^(I$7-$I$7))/$F50,1),"n/a") -> n/a | J50: =IF(ISNUMBER($D50),$D50*(1+$G50)^(J$7-$I$7)*IF($F50>1,(1+($F50-1)*(1-$H50)^(J$7-$I$7))/$F50,1),"n/a") -> n/a | K50: =IF(ISNUMBER($D50),$D50*(1+$G50)^(K$7-$I$7)*IF($F50>1,(1+($F50-1)*(1-$H50)^(K$7-$I$7))/$F50,1),"n/a") -> n/a | L50: =IF(ISNUMBER($D50),$D50*(1+$G50)^(L$7-$I$7)*IF($F50>1,(1+($F50-1)*(1-$H50)^(L$7-$I$7))/$F50,1),"n/a") -> n/a | M50: =IF(ISNUMBER($D50),$D50*(1+$G50)^(M$7-$I$7)*IF($F50>1,(1+($F50-1)*(1-$H50)^(M$7-$I$7))/$F50,1),"n/a") -> n/a | N50: =IF(ISNUMBER($D50),$D50*(1+$G50)^(N$7-$I$7)*IF($F50>1,(1+($F50-1)*(1-$H50)^(N$7-$I$7))/$F50,1),"n/a") -> n/a | O50: =IF(ISNUMBER($D50),$D50*(1+$G50)^(O$7-$I$7)*IF($F50>1,(1+($F50-1)*(1-$H50)^(O$7-$I$7))/$F50,1),"n/a") -> n/a | P50: =IF(ISNUMBER($D50),$D50*(1+$G50)^(P$7-$I$7)*IF($F50>1,(1+($F50-1)*(1-$H50)^(P$7-$I$7))/$F50,1),"n/a") -> n/a | ... AK50: =IF(ISNUMBER($D50),$D50*(1+$G50)^(AK$7-$I$7)*IF($F50>1,(1+($F50-1)*(1-$H50)^(AK$7-$I$7))/$F50,1),"n/a") -> n/a
A51: 7 | B51: Aircraft - Passenger | C51: NGV | D51: ='Fuel Price'!D89 -> n/a | E51: ='Fuel Price'!$J$89 -> 2.2354408e+08 | F51: =IF(ISNUMBER(D51),D51/E51,"n/a") -> n/a | G51: =Assumptions!$E$24 -> 0 | H51: {=INDEX(Assumptions!$B$34:$B$40,MATCH($C51,Assumptions!$A$34:$A$40,0))} -> 0.01 | I51: =IF(ISNUMBER($D51),$D51*(1+$G51)^(I$7-$I$7)*IF($F51>1,(1+($F51-1)*(1-$H51)^(I$7-$I$7))/$F51,1),"n/a") -> n/a | J51: =IF(ISNUMBER($D51),$D51*(1+$G51)^(J$7-$I$7)*IF($F51>1,(1+($F51-1)*(1-$H51)^(J$7-$I$7))/$F51,1),"n/a") -> n/a | K51: =IF(ISNUMBER($D51),$D51*(1+$G51)^(K$7-$I$7)*IF($F51>1,(1+($F51-1)*(1-$H51)^(K$7-$I$7))/$F51,1),"n/a") -> n/a | L51: =IF(ISNUMBER($D51),$D51*(1+$G51)^(L$7-$I$7)*IF($F51>1,(1+($F51-1)*(1-$H51)^(L$7-$I$7))/$F51,1),"n/a") -> n/a | M51: =IF(ISNUMBER($D51),$D51*(1+$G51)^(M$7-$I$7)*IF($F51>1,(1+($F51-1)*(1-$H51)^(M$7-$I$7))/$F51,1),"n/a") -> n/a | N51: =IF(ISNUMBER($D51),$D51*(1+$G51)^(N$7-$I$7)*IF($F51>1,(1+($F51-1)*(1-$H51)^(N$7-$I$7))/$F51,1),"n/a") -> n/a | O51: =IF(ISNUMBER($D51),$D51*(1+$G51)^(O$7-$I$7)*IF($F51>1,(1+($F51-1)*(1-$H51)^(O$7-$I$7))/$F51,1),"n/a") -> n/a | P51: =IF(ISNUMBER($D51),$D51*(1+$G51)^(P$7-$I$7)*IF($F51>1,(1+($F51-1)*(1-$H51)^(P$7-$I$7))/$F51,1),"n/a") -> n/a | ... AK51: =IF(ISNUMBER($D51),$D51*(1+$G51)^(AK$7-$I$7)*IF($F51>1,(1+($F51-1)*(1-$H51)^(AK$7-$I$7))/$F51,1),"n/a") -> n/a
A52: 7 | B52: Aircraft - Passenger | C52: Gasoline | D52: ='Fuel Price'!E89 -> 2.2354408e+08 | E52: ='Fuel Price'!$J$89 -> 2.2354408e+08 | F52: =IF(ISNUMBER(D52),D52/E52,"n/a") -> 1 | G52: =Assumptions!$E$24 -> 0 | H52: {=INDEX(Assumptions!$B$34:$B$40,MATCH($C52,Assumptions!$A$34:$A$40,0))} -> 0 | I52: =IF(ISNUMBER($D52),$D52*(1+$G52)^(I$7-$I$7)*IF($F52>1,(1+($F52-1)*(1-$H52)^(I$7-$I$7))/$F52,1),"n/a") -> 2.2354408e+08 | J52: =IF(ISNUMBER($D52),$D52*(1+$G52)^(J$7-$I$7)*IF($F52>1,(1+($F52-1)*(1-$H52)^(J$7-$I$7))/$F52,1),"n/a") -> 2.2354408e+08 | K52: =IF(ISNUMBER($D52),$D52*(1+$G52)^(K$7-$I$7)*IF($F52>1,(1+($F52-1)*(1-$H52)^(K$7-$I$7))/$F52,1),"n/a") -> 2.2354408e+08 | L52: =IF(ISNUMBER($D52),$D52*(1+$G52)^(L$7-$I$7)*IF($F52>1,(1+($F52-1)*(1-$H52)^(L$7-$I$7))/$F52,1),"n/a") -> 2.2354408e+08 | M52: =IF(ISNUMBER($D52),$D52*(1+$G52)^(M$7-$I$7)*IF($F52>1,(1+($F52-1)*(1-$H52)^(M$7-$I$7))/$F52,1),"n/a") -> 2.2354408e+08 | N52: =IF(ISNUMBER($D52),$D52*(1+$G52)^(N$7-$I$7)*IF($F52>1,(1+($F52-1)*(1-$H52)^(N$7-$I$7))/$F52,1),"n/a") -> 2.2354408e+08 | O52: =IF(ISNUMBER($D52),$D52*(1+$G52)^(O$7-$I$7)*IF($F52>1,(1+($F52-1)*(1-$H52)^(O$7-$I$7))/$F52,1),"n/a") -> 2.2354408e+08 | P52: =IF(ISNUMBER($D52),$D52*(1+$G52)^(P$7-$I$7)*IF($F52>1,(1+($F52-1)*(1-$H52)^(P$7-$I$7))/$F52,1),"n/a") -> 2.2354408e+08 | ... AK52: =IF(ISNUMBER($D52),$D52*(1+$G52)^(AK$7-$I$7)*IF($F52>1,(1+($F52-1)*(1-$H52)^(AK$7-$I$7))/$F52,1),"n/a") -> 2.2354408e+08
A53: 7 | B53: Aircraft - Passenger | C53: Diesel | D53: ='Fuel Price'!F89 -> n/a | E53: ='Fuel Price'!$J$89 -> 2.2354408e+08 | F53: =IF(ISNUMBER(D53),D53/E53,"n/a") -> n/a | G53: =Assumptions!$E$24 -> 0 | H53: {=INDEX(Assumptions!$B$34:$B$40,MATCH($C53,Assumptions!$A$34:$A$40,0))} -> 0 | I53: =IF(ISNUMBER($D53),$D53*(1+$G53)^(I$7-$I$7)*IF($F53>1,(1+($F53-1)*(1-$H53)^(I$7-$I$7))/$F53,1),"n/a") -> n/a | J53: =IF(ISNUMBER($D53),$D53*(1+$G53)^(J$7-$I$7)*IF($F53>1,(1+($F53-1)*(1-$H53)^(J$7-$I$7))/$F53,1),"n/a") -> n/a | K53: =IF(ISNUMBER($D53),$D53*(1+$G53)^(K$7-$I$7)*IF($F53>1,(1+($F53-1)*(1-$H53)^(K$7-$I$7))/$F53,1),"n/a") -> n/a | L53: =IF(ISNUMBER($D53),$D53*(1+$G53)^(L$7-$I$7)*IF($F53>1,(1+($F53-1)*(1-$H53)^(L$7-$I$7))/$F53,1),"n/a") -> n/a | M53: =IF(ISNUMBER($D53),$D53*(1+$G53)^(M$7-$I$7)*IF($F53>1,(1+($F53-1)*(1-$H53)^(M$7-$I$7))/$F53,1),"n/a") -> n/a | N53: =IF(ISNUMBER($D53),$D53*(1+$G53)^(N$7-$I$7)*IF($F53>1,(1+($F53-1)*(1-$H53)^(N$7-$I$7))/$F53,1),"n/a") -> n/a | O53: =IF(ISNUMBER($D53),$D53*(1+$G53)^(O$7-$I$7)*IF($F53>1,(1+($F53-1)*(1-$H53)^(O$7-$I$7))/$F53,1),"n/a") -> n/a | P53: =IF(ISNUMBER($D53),$D53*(1+$G53)^(P$7-$I$7)*IF($F53>1,(1+($F53-1)*(1-$H53)^(P$7-$I$7))/$F53,1),"n/a") -> n/a | ... AK53: =IF(ISNUMBER($D53),$D53*(1+$G53)^(AK$7-$I$7)*IF($F53>1,(1+($F53-1)*(1-$H53)^(AK$7-$I$7))/$F53,1),"n/a") -> n/a
A54: 7 | B54: Aircraft - Passenger | C54: PHEV | D54: ='Fuel Price'!G89 -> n/a | E54: ='Fuel Price'!$J$89 -> 2.2354408e+08 | F54: =IF(ISNUMBER(D54),D54/E54,"n/a") -> n/a | G54: =Assumptions!$E$24 -> 0 | H54: {=INDEX(Assumptions!$B$34:$B$40,MATCH($C54,Assumptions!$A$34:$A$40,0))} -> 0.02 | I54: =IF(ISNUMBER($D54),$D54*(1+$G54)^(I$7-$I$7)*IF($F54>1,(1+($F54-1)*(1-$H54)^(I$7-$I$7))/$F54,1),"n/a") -> n/a | J54: =IF(ISNUMBER($D54),$D54*(1+$G54)^(J$7-$I$7)*IF($F54>1,(1+($F54-1)*(1-$H54)^(J$7-$I$7))/$F54,1),"n/a") -> n/a | K54: =IF(ISNUMBER($D54),$D54*(1+$G54)^(K$7-$I$7)*IF($F54>1,(1+($F54-1)*(1-$H54)^(K$7-$I$7))/$F54,1),"n/a") -> n/a | L54: =IF(ISNUMBER($D54),$D54*(1+$G54)^(L$7-$I$7)*IF($F54>1,(1+($F54-1)*(1-$H54)^(L$7-$I$7))/$F54,1),"n/a") -> n/a | M54: =IF(ISNUMBER($D54),$D54*(1+$G54)^(M$7-$I$7)*IF($F54>1,(1+($F54-1)*(1-$H54)^(M$7-$I$7))/$F54,1),"n/a") -> n/a | N54: =IF(ISNUMBER($D54),$D54*(1+$G54)^(N$7-$I$7)*IF($F54>1,(1+($F54-1)*(1-$H54)^(N$7-$I$7))/$F54,1),"n/a") -> n/a | O54: =IF(ISNUMBER($D54),$D54*(1+$G54)^(O$7-$I$7)*IF($F54>1,(1+($F54-1)*(1-$H54)^(O$7-$I$7))/$F54,1),"n/a") -> n/a | P54: =IF(ISNUMBER($D54),$D54*(1+$G54)^(P$7-$I$7)*IF($F54>1,(1+($F54-1)*(1-$H54)^(P$7-$I$7))/$F54,1),"n/a") -> n/a | ... AK54: =IF(ISNUMBER($D54),$D54*(1+$G54)^(AK$7-$I$7)*IF($F54>1,(1+($F54-1)*(1-$H54)^(AK$7-$I$7))/$F54,1),"n/a") -> n/a
A55: 7 | B55: Aircraft - Passenger | C55: LPG | D55: ='Fuel Price'!H89 -> n/a | E55: ='Fuel Price'!$J$89 -> 2.2354408e+08 | F55: =IF(ISNUMBER(D55),D55/E55,"n/a") -> n/a | G55: =Assumptions!$E$24 -> 0 | H55: {=INDEX(Assumptions!$B$34:$B$40,MATCH($C55,Assumptions!$A$34:$A$40,0))} -> 0.01 | I55: =IF(ISNUMBER($D55),$D55*(1+$G55)^(I$7-$I$7)*IF($F55>1,(1+($F55-1)*(1-$H55)^(I$7-$I$7))/$F55,1),"n/a") -> n/a | J55: =IF(ISNUMBER($D55),$D55*(1+$G55)^(J$7-$I$7)*IF($F55>1,(1+($F55-1)*(1-$H55)^(J$7-$I$7))/$F55,1),"n/a") -> n/a | K55: =IF(ISNUMBER($D55),$D55*(1+$G55)^(K$7-$I$7)*IF($F55>1,(1+($F55-1)*(1-$H55)^(K$7-$I$7))/$F55,1),"n/a") -> n/a | L55: =IF(ISNUMBER($D55),$D55*(1+$G55)^(L$7-$I$7)*IF($F55>1,(1+($F55-1)*(1-$H55)^(L$7-$I$7))/$F55,1),"n/a") -> n/a | M55: =IF(ISNUMBER($D55),$D55*(1+$G55)^(M$7-$I$7)*IF($F55>1,(1+($F55-1)*(1-$H55)^(M$7-$I$7))/$F55,1),"n/a") -> n/a | N55: =IF(ISNUMBER($D55),$D55*(1+$G55)^(N$7-$I$7)*IF($F55>1,(1+($F55-1)*(1-$H55)^(N$7-$I$7))/$F55,1),"n/a") -> n/a | O55: =IF(ISNUMBER($D55),$D55*(1+$G55)^(O$7-$I$7)*IF($F55>1,(1+($F55-1)*(1-$H55)^(O$7-$I$7))/$F55,1),"n/a") -> n/a | P55: =IF(ISNUMBER($D55),$D55*(1+$G55)^(P$7-$I$7)*IF($F55>1,(1+($F55-1)*(1-$H55)^(P$7-$I$7))/$F55,1),"n/a") -> n/a | ... AK55: =IF(ISNUMBER($D55),$D55*(1+$G55)^(AK$7-$I$7)*IF($F55>1,(1+($F55-1)*(1-$H55)^(AK$7-$I$7))/$F55,1),"n/a") -> n/a
A56: 7 | B56: Aircraft - Passenger | C56: Hydrogen | D56: ='Fuel Price'!I89 -> n/a | E56: ='Fuel Price'!$J$89 -> 2.2354408e+08 | F56: =IF(ISNUMBER(D56),D56/E56,"n/a") -> n/a | G56: =Assumptions!$E$24 -> 0 | H56: {=INDEX(Assumptions!$B$34:$B$40,MATCH($C56,Assumptions!$A$34:$A$40,0))} -> 0.03 | I56: =IF(ISNUMBER($D56),$D56*(1+$G56)^(I$7-$I$7)*IF($F56>1,(1+($F56-1)*(1-$H56)^(I$7-$I$7))/$F56,1),"n/a") -> n/a | J56: =IF(ISNUMBER($D56),$D56*(1+$G56)^(J$7-$I$7)*IF($F56>1,(1+($F56-1)*(1-$H56)^(J$7-$I$7))/$F56,1),"n/a") -> n/a | K56: =IF(ISNUMBER($D56),$D56*(1+$G56)^(K$7-$I$7)*IF($F56>1,(1+($F56-1)*(1-$H56)^(K$7-$I$7))/$F56,1),"n/a") -> n/a | L56: =IF(ISNUMBER($D56),$D56*(1+$G56)^(L$7-$I$7)*IF($F56>1,(1+($F56-1)*(1-$H56)^(L$7-$I$7))/$F56,1),"n/a") -> n/a | M56: =IF(ISNUMBER($D56),$D56*(1+$G56)^(M$7-$I$7)*IF($F56>1,(1+($F56-1)*(1-$H56)^(M$7-$I$7))/$F56,1),"n/a") -> n/a | N56: =IF(ISNUMBER($D56),$D56*(1+$G56)^(N$7-$I$7)*IF($F56>1,(1+($F56-1)*(1-$H56)^(N$7-$I$7))/$F56,1),"n/a") -> n/a | O56: =IF(ISNUMBER($D56),$D56*(1+$G56)^(O$7-$I$7)*IF($F56>1,(1+($F56-1)*(1-$H56)^(O$7-$I$7))/$F56,1),"n/a") -> n/a | P56: =IF(ISNUMBER($D56),$D56*(1+$G56)^(P$7-$I$7)*IF($F56>1,(1+($F56-1)*(1-$H56)^(P$7-$I$7))/$F56,1),"n/a") -> n/a | ... AK56: =IF(ISNUMBER($D56),$D56*(1+$G56)^(AK$7-$I$7)*IF($F56>1,(1+($F56-1)*(1-$H56)^(AK$7-$I$7))/$F56,1),"n/a") -> n/a
A57: 8 | B57: Aircraft - Freight | C57: BEV | D57: ='Fuel Price'!C90 -> n/a | E57: ='Fuel Price'!$J$90 -> 1.1367651e+08 | F57: =IF(ISNUMBER(D57),D57/E57,"n/a") -> n/a | G57: =Assumptions!$E$25 -> 0 | H57: {=INDEX(Assumptions!$B$34:$B$40,MATCH($C57,Assumptions!$A$34:$A$40,0))} -> 0.03 | I57: =IF(ISNUMBER($D57),$D57*(1+$G57)^(I$7-$I$7)*IF($F57>1,(1+($F57-1)*(1-$H57)^(I$7-$I$7))/$F57,1),"n/a") -> n/a | J57: =IF(ISNUMBER($D57),$D57*(1+$G57)^(J$7-$I$7)*IF($F57>1,(1+($F57-1)*(1-$H57)^(J$7-$I$7))/$F57,1),"n/a") -> n/a | K57: =IF(ISNUMBER($D57),$D57*(1+$G57)^(K$7-$I$7)*IF($F57>1,(1+($F57-1)*(1-$H57)^(K$7-$I$7))/$F57,1),"n/a") -> n/a | L57: =IF(ISNUMBER($D57),$D57*(1+$G57)^(L$7-$I$7)*IF($F57>1,(1+($F57-1)*(1-$H57)^(L$7-$I$7))/$F57,1),"n/a") -> n/a | M57: =IF(ISNUMBER($D57),$D57*(1+$G57)^(M$7-$I$7)*IF($F57>1,(1+($F57-1)*(1-$H57)^(M$7-$I$7))/$F57,1),"n/a") -> n/a | N57: =IF(ISNUMBER($D57),$D57*(1+$G57)^(N$7-$I$7)*IF($F57>1,(1+($F57-1)*(1-$H57)^(N$7-$I$7))/$F57,1),"n/a") -> n/a | O57: =IF(ISNUMBER($D57),$D57*(1+$G57)^(O$7-$I$7)*IF($F57>1,(1+($F57-1)*(1-$H57)^(O$7-$I$7))/$F57,1),"n/a") -> n/a | P57: =IF(ISNUMBER($D57),$D57*(1+$G57)^(P$7-$I$7)*IF($F57>1,(1+($F57-1)*(1-$H57)^(P$7-$I$7))/$F57,1),"n/a") -> n/a | ... AK57: =IF(ISNUMBER($D57),$D57*(1+$G57)^(AK$7-$I$7)*IF($F57>1,(1+($F57-1)*(1-$H57)^(AK$7-$I$7))/$F57,1),"n/a") -> n/a
A58: 8 | B58: Aircraft - Freight | C58: NGV | D58: ='Fuel Price'!D90 -> n/a | E58: ='Fuel Price'!$J$90 -> 1.1367651e+08 | F58: =IF(ISNUMBER(D58),D58/E58,"n/a") -> n/a | G58: =Assumptions!$E$25 -> 0 | H58: {=INDEX(Assumptions!$B$34:$B$40,MATCH($C58,Assumptions!$A$34:$A$40,0))} -> 0.01 | I58: =IF(ISNUMBER($D58),$D58*(1+$G58)^(I$7-$I$7)*IF($F58>1,(1+($F58-1)*(1-$H58)^(I$7-$I$7))/$F58,1),"n/a") -> n/a | J58: =IF(ISNUMBER($D58),$D58*(1+$G58)^(J$7-$I$7)*IF($F58>1,(1+($F58-1)*(1-$H58)^(J$7-$I$7))/$F58,1),"n/a") -> n/a | K58: =IF(ISNUMBER($D58),$D58*(1+$G58)^(K$7-$I$7)*IF($F58>1,(1+($F58-1)*(1-$H58)^(K$7-$I$7))/$F58,1),"n/a") -> n/a | L58: =IF(ISNUMBER($D58),$D58*(1+$G58)^(L$7-$I$7)*IF($F58>1,(1+($F58-1)*(1-$H58)^(L$7-$I$7))/$F58,1),"n/a") -> n/a | M58: =IF(ISNUMBER($D58),$D58*(1+$G58)^(M$7-$I$7)*IF($F58>1,(1+($F58-1)*(1-$H58)^(M$7-$I$7))/$F58,1),"n/a") -> n/a | N58: =IF(ISNUMBER($D58),$D58*(1+$G58)^(N$7-$I$7)*IF($F58>1,(1+($F58-1)*(1-$H58)^(N$7-$I$7))/$F58,1),"n/a") -> n/a | O58: =IF(ISNUMBER($D58),$D58*(1+$G58)^(O$7-$I$7)*IF($F58>1,(1+($F58-1)*(1-$H58)^(O$7-$I$7))/$F58,1),"n/a") -> n/a | P58: =IF(ISNUMBER($D58),$D58*(1+$G58)^(P$7-$I$7)*IF($F58>1,(1+($F58-1)*(1-$H58)^(P$7-$I$7))/$F58,1),"n/a") -> n/a | ... AK58: =IF(ISNUMBER($D58),$D58*(1+$G58)^(AK$7-$I$7)*IF($F58>1,(1+($F58-1)*(1-$H58)^(AK$7-$I$7))/$F58,1),"n/a") -> n/a
A59: 8 | B59: Aircraft - Freight | C59: Gasoline | D59: ='Fuel Price'!E90 -> 1.1367651e+08 | E59: ='Fuel Price'!$J$90 -> 1.1367651e+08 | F59: =IF(ISNUMBER(D59),D59/E59,"n/a") -> 1 | G59: =Assumptions!$E$25 -> 0 | H59: {=INDEX(Assumptions!$B$34:$B$40,MATCH($C59,Assumptions!$A$34:$A$40,0))} -> 0 | I59: =IF(ISNUMBER($D59),$D59*(1+$G59)^(I$7-$I$7)*IF($F59>1,(1+($F59-1)*(1-$H59)^(I$7-$I$7))/$F59,1),"n/a") -> 1.1367651e+08 | J59: =IF(ISNUMBER($D59),$D59*(1+$G59)^(J$7-$I$7)*IF($F59>1,(1+($F59-1)*(1-$H59)^(J$7-$I$7))/$F59,1),"n/a") -> 1.1367651e+08 | K59: =IF(ISNUMBER($D59),$D59*(1+$G59)^(K$7-$I$7)*IF($F59>1,(1+($F59-1)*(1-$H59)^(K$7-$I$7))/$F59,1),"n/a") -> 1.1367651e+08 | L59: =IF(ISNUMBER($D59),$D59*(1+$G59)^(L$7-$I$7)*IF($F59>1,(1+($F59-1)*(1-$H59)^(L$7-$I$7))/$F59,1),"n/a") -> 1.1367651e+08 | M59: =IF(ISNUMBER($D59),$D59*(1+$G59)^(M$7-$I$7)*IF($F59>1,(1+($F59-1)*(1-$H59)^(M$7-$I$7))/$F59,1),"n/a") -> 1.1367651e+08 | N59: =IF(ISNUMBER($D59),$D59*(1+$G59)^(N$7-$I$7)*IF($F59>1,(1+($F59-1)*(1-$H59)^(N$7-$I$7))/$F59,1),"n/a") -> 1.1367651e+08 | O59: =IF(ISNUMBER($D59),$D59*(1+$G59)^(O$7-$I$7)*IF($F59>1,(1+($F59-1)*(1-$H59)^(O$7-$I$7))/$F59,1),"n/a") -> 1.1367651e+08 | P59: =IF(ISNUMBER($D59),$D59*(1+$G59)^(P$7-$I$7)*IF($F59>1,(1+($F59-1)*(1-$H59)^(P$7-$I$7))/$F59,1),"n/a") -> 1.1367651e+08 | ... AK59: =IF(ISNUMBER($D59),$D59*(1+$G59)^(AK$7-$I$7)*IF($F59>1,(1+($F59-1)*(1-$H59)^(AK$7-$I$7))/$F59,1),"n/a") -> 1.1367651e+08
A60: 8 | B60: Aircraft - Freight | C60: Diesel | D60: ='Fuel Price'!F90 -> n/a | E60: ='Fuel Price'!$J$90 -> 1.1367651e+08 | F60: =IF(ISNUMBER(D60),D60/E60,"n/a") -> n/a | G60: =Assumptions!$E$25 -> 0 | H60: {=INDEX(Assumptions!$B$34:$B$40,MATCH($C60,Assumptions!$A$34:$A$40,0))} -> 0 | I60: =IF(ISNUMBER($D60),$D60*(1+$G60)^(I$7-$I$7)*IF($F60>1,(1+($F60-1)*(1-$H60)^(I$7-$I$7))/$F60,1),"n/a") -> n/a | J60: =IF(ISNUMBER($D60),$D60*(1+$G60)^(J$7-$I$7)*IF($F60>1,(1+($F60-1)*(1-$H60)^(J$7-$I$7))/$F60,1),"n/a") -> n/a | K60: =IF(ISNUMBER($D60),$D60*(1+$G60)^(K$7-$I$7)*IF($F60>1,(1+($F60-1)*(1-$H60)^(K$7-$I$7))/$F60,1),"n/a") -> n/a | L60: =IF(ISNUMBER($D60),$D60*(1+$G60)^(L$7-$I$7)*IF($F60>1,(1+($F60-1)*(1-$H60)^(L$7-$I$7))/$F60,1),"n/a") -> n/a | M60: =IF(ISNUMBER($D60),$D60*(1+$G60)^(M$7-$I$7)*IF($F60>1,(1+($F60-1)*(1-$H60)^(M$7-$I$7))/$F60,1),"n/a") -> n/a | N60: =IF(ISNUMBER($D60),$D60*(1+$G60)^(N$7-$I$7)*IF($F60>1,(1+($F60-1)*(1-$H60)^(N$7-$I$7))/$F60,1),"n/a") -> n/a | O60: =IF(ISNUMBER($D60),$D60*(1+$G60)^(O$7-$I$7)*IF($F60>1,(1+($F60-1)*(1-$H60)^(O$7-$I$7))/$F60,1),"n/a") -> n/a | P60: =IF(ISNUMBER($D60),$D60*(1+$G60)^(P$7-$I$7)*IF($F60>1,(1+($F60-1)*(1-$H60)^(P$7-$I$7))/$F60,1),"n/a") -> n/a | ... AK60: =IF(ISNUMBER($D60),$D60*(1+$G60)^(AK$7-$I$7)*IF($F60>1,(1+($F60-1)*(1-$H60)^(AK$7-$I$7))/$F60,1),"n/a") -> n/a
A61: 8 | B61: Aircraft - Freight | C61: PHEV | D61: ='Fuel Price'!G90 -> n/a | E61: ='Fuel Price'!$J$90 -> 1.1367651e+08 | F61: =IF(ISNUMBER(D61),D61/E61,"n/a") -> n/a | G61: =Assumptions!$E$25 -> 0 | H61: {=INDEX(Assumptions!$B$34:$B$40,MATCH($C61,Assumptions!$A$34:$A$40,0))} -> 0.02 | I61: =IF(ISNUMBER($D61),$D61*(1+$G61)^(I$7-$I$7)*IF($F61>1,(1+($F61-1)*(1-$H61)^(I$7-$I$7))/$F61,1),"n/a") -> n/a | J61: =IF(ISNUMBER($D61),$D61*(1+$G61)^(J$7-$I$7)*IF($F61>1,(1+($F61-1)*(1-$H61)^(J$7-$I$7))/$F61,1),"n/a") -> n/a | K61: =IF(ISNUMBER($D61),$D61*(1+$G61)^(K$7-$I$7)*IF($F61>1,(1+($F61-1)*(1-$H61)^(K$7-$I$7))/$F61,1),"n/a") -> n/a | L61: =IF(ISNUMBER($D61),$D61*(1+$G61)^(L$7-$I$7)*IF($F61>1,(1+($F61-1)*(1-$H61)^(L$7-$I$7))/$F61,1),"n/a") -> n/a | M61: =IF(ISNUMBER($D61),$D61*(1+$G61)^(M$7-$I$7)*IF($F61>1,(1+($F61-1)*(1-$H61)^(M$7-$I$7))/$F61,1),"n/a") -> n/a | N61: =IF(ISNUMBER($D61),$D61*(1+$G61)^(N$7-$I$7)*IF($F61>1,(1+($F61-1)*(1-$H61)^(N$7-$I$7))/$F61,1),"n/a") -> n/a | O61: =IF(ISNUMBER($D61),$D61*(1+$G61)^(O$7-$I$7)*IF($F61>1,(1+($F61-1)*(1-$H61)^(O$7-$I$7))/$F61,1),"n/a") -> n/a | P61: =IF(ISNUMBER($D61),$D61*(1+$G61)^(P$7-$I$7)*IF($F61>1,(1+($F61-1)*(1-$H61)^(P$7-$I$7))/$F61,1),"n/a") -> n/a | ... AK61: =IF(ISNUMBER($D61),$D61*(1+$G61)^(AK$7-$I$7)*IF($F61>1,(1+($F61-1)*(1-$H61)^(AK$7-$I$7))/$F61,1),"n/a") -> n/a
A62: 8 | B62: Aircraft - Freight | C62: LPG | D62: ='Fuel Price'!H90 -> n/a | E62: ='Fuel Price'!$J$90 -> 1.1367651e+08 | F62: =IF(ISNUMBER(D62),D62/E62,"n/a") -> n/a | G62: =Assumptions!$E$25 -> 0 | H62: {=INDEX(Assumptions!$B$34:$B$40,MATCH($C62,Assumptions!$A$34:$A$40,0))} -> 0.01 | I62: =IF(ISNUMBER($D62),$D62*(1+$G62)^(I$7-$I$7)*IF($F62>1,(1+($F62-1)*(1-$H62)^(I$7-$I$7))/$F62,1),"n/a") -> n/a | J62: =IF(ISNUMBER($D62),$D62*(1+$G62)^(J$7-$I$7)*IF($F62>1,(1+($F62-1)*(1-$H62)^(J$7-$I$7))/$F62,1),"n/a") -> n/a | K62: =IF(ISNUMBER($D62),$D62*(1+$G62)^(K$7-$I$7)*IF($F62>1,(1+($F62-1)*(1-$H62)^(K$7-$I$7))/$F62,1),"n/a") -> n/a | L62: =IF(ISNUMBER($D62),$D62*(1+$G62)^(L$7-$I$7)*IF($F62>1,(1+($F62-1)*(1-$H62)^(L$7-$I$7))/$F62,1),"n/a") -> n/a | M62: =IF(ISNUMBER($D62),$D62*(1+$G62)^(M$7-$I$7)*IF($F62>1,(1+($F62-1)*(1-$H62)^(M$7-$I$7))/$F62,1),"n/a") -> n/a | N62: =IF(ISNUMBER($D62),$D62*(1+$G62)^(N$7-$I$7)*IF($F62>1,(1+($F62-1)*(1-$H62)^(N$7-$I$7))/$F62,1),"n/a") -> n/a | O62: =IF(ISNUMBER($D62),$D62*(1+$G62)^(O$7-$I$7)*IF($F62>1,(1+($F62-1)*(1-$H62)^(O$7-$I$7))/$F62,1),"n/a") -> n/a | P62: =IF(ISNUMBER($D62),$D62*(1+$G62)^(P$7-$I$7)*IF($F62>1,(1+($F62-1)*(1-$H62)^(P$7-$I$7))/$F62,1),"n/a") -> n/a | ... AK62: =IF(ISNUMBER($D62),$D62*(1+$G62)^(AK$7-$I$7)*IF($F62>1,(1+($F62-1)*(1-$H62)^(AK$7-$I$7))/$F62,1),"n/a") -> n/a
A63: 8 | B63: Aircraft - Freight | C63: Hydrogen | D63: ='Fuel Price'!I90 -> n/a | E63: ='Fuel Price'!$J$90 -> 1.1367651e+08 | F63: =IF(ISNUMBER(D63),D63/E63,"n/a") -> n/a | G63: =Assumptions!$E$25 -> 0 | H63: {=INDEX(Assumptions!$B$34:$B$40,MATCH($C63,Assumptions!$A$34:$A$40,0))} -> 0.03 | I63: =IF(ISNUMBER($D63),$D63*(1+$G63)^(I$7-$I$7)*IF($F63>1,(1+($F63-1)*(1-$H63)^(I$7-$I$7))/$F63,1),"n/a") -> n/a | J63: =IF(ISNUMBER($D63),$D63*(1+$G63)^(J$7-$I$7)*IF($F63>1,(1+($F63-1)*(1-$H63)^(J$7-$I$7))/$F63,1),"n/a") -> n/a | K63: =IF(ISNUMBER($D63),$D63*(1+$G63)^(K$7-$I$7)*IF($F63>1,(1+($F63-1)*(1-$H63)^(K$7-$I$7))/$F63,1),"n/a") -> n/a | L63: =IF(ISNUMBER($D63),$D63*(1+$G63)^(L$7-$I$7)*IF($F63>1,(1+($F63-1)*(1-$H63)^(L$7-$I$7))/$F63,1),"n/a") -> n/a | M63: =IF(ISNUMBER($D63),$D63*(1+$G63)^(M$7-$I$7)*IF($F63>1,(1+($F63-1)*(1-$H63)^(M$7-$I$7))/$F63,1),"n/a") -> n/a | N63: =IF(ISNUMBER($D63),$D63*(1+$G63)^(N$7-$I$7)*IF($F63>1,(1+($F63-1)*(1-$H63)^(N$7-$I$7))/$F63,1),"n/a") -> n/a | O63: =IF(ISNUMBER($D63),$D63*(1+$G63)^(O$7-$I$7)*IF($F63>1,(1+($F63-1)*(1-$H63)^(O$7-$I$7))/$F63,1),"n/a") -> n/a | P63: =IF(ISNUMBER($D63),$D63*(1+$G63)^(P$7-$I$7)*IF($F63>1,(1+($F63-1)*(1-$H63)^(P$7-$I$7))/$F63,1),"n/a") -> n/a | ... AK63: =IF(ISNUMBER($D63),$D63*(1+$G63)^(AK$7-$I$7)*IF($F63>1,(1+($F63-1)*(1-$H63)^(AK$7-$I$7))/$F63,1),"n/a") -> n/a
A64: 9 | B64: Ship - Passenger | C64: BEV | D64: ='Fuel Price'!C91 -> 1.2002961e+08 | E64: ='Fuel Price'!$J$91 -> 75018509 | F64: =IF(ISNUMBER(D64),D64/E64,"n/a") -> 1.6 | G64: =Assumptions!$E$26 -> 0 | H64: {=INDEX(Assumptions!$B$34:$B$40,MATCH($C64,Assumptions!$A$34:$A$40,0))} -> 0.03 | I64: =IF(ISNUMBER($D64),$D64*(1+$G64)^(I$7-$I$7)*IF($F64>1,(1+($F64-1)*(1-$H64)^(I$7-$I$7))/$F64,1),"n/a") -> 1.2002961e+08 | J64: =IF(ISNUMBER($D64),$D64*(1+$G64)^(J$7-$I$7)*IF($F64>1,(1+($F64-1)*(1-$H64)^(J$7-$I$7))/$F64,1),"n/a") -> 1.1867928e+08 | K64: =IF(ISNUMBER($D64),$D64*(1+$G64)^(K$7-$I$7)*IF($F64>1,(1+($F64-1)*(1-$H64)^(K$7-$I$7))/$F64,1),"n/a") -> 1.1736946e+08 | L64: =IF(ISNUMBER($D64),$D64*(1+$G64)^(L$7-$I$7)*IF($F64>1,(1+($F64-1)*(1-$H64)^(L$7-$I$7))/$F64,1),"n/a") -> 1.1609893e+08 | M64: =IF(ISNUMBER($D64),$D64*(1+$G64)^(M$7-$I$7)*IF($F64>1,(1+($F64-1)*(1-$H64)^(M$7-$I$7))/$F64,1),"n/a") -> 1.1486652e+08 | N64: =IF(ISNUMBER($D64),$D64*(1+$G64)^(N$7-$I$7)*IF($F64>1,(1+($F64-1)*(1-$H64)^(N$7-$I$7))/$F64,1),"n/a") -> 1.1367108e+08 | O64: =IF(ISNUMBER($D64),$D64*(1+$G64)^(O$7-$I$7)*IF($F64>1,(1+($F64-1)*(1-$H64)^(O$7-$I$7))/$F64,1),"n/a") -> 1.125115e+08 | P64: =IF(ISNUMBER($D64),$D64*(1+$G64)^(P$7-$I$7)*IF($F64>1,(1+($F64-1)*(1-$H64)^(P$7-$I$7))/$F64,1),"n/a") -> 1.1138671e+08 | ... AK64: =IF(ISNUMBER($D64),$D64*(1+$G64)^(AK$7-$I$7)*IF($F64>1,(1+($F64-1)*(1-$H64)^(AK$7-$I$7))/$F64,1),"n/a") -> 94202026
A65: 9 | B65: Ship - Passenger | C65: NGV | D65: ='Fuel Price'!D91 -> 86271285 | E65: ='Fuel Price'!$J$91 -> 75018509 | F65: =IF(ISNUMBER(D65),D65/E65,"n/a") -> 1.15 | G65: =Assumptions!$E$26 -> 0 | H65: {=INDEX(Assumptions!$B$34:$B$40,MATCH($C65,Assumptions!$A$34:$A$40,0))} -> 0.01 | I65: =IF(ISNUMBER($D65),$D65*(1+$G65)^(I$7-$I$7)*IF($F65>1,(1+($F65-1)*(1-$H65)^(I$7-$I$7))/$F65,1),"n/a") -> 86271285 | J65: =IF(ISNUMBER($D65),$D65*(1+$G65)^(J$7-$I$7)*IF($F65>1,(1+($F65-1)*(1-$H65)^(J$7-$I$7))/$F65,1),"n/a") -> 86158758 | K65: =IF(ISNUMBER($D65),$D65*(1+$G65)^(K$7-$I$7)*IF($F65>1,(1+($F65-1)*(1-$H65)^(K$7-$I$7))/$F65,1),"n/a") -> 86047355 | L65: =IF(ISNUMBER($D65),$D65*(1+$G65)^(L$7-$I$7)*IF($F65>1,(1+($F65-1)*(1-$H65)^(L$7-$I$7))/$F65,1),"n/a") -> 85937067 | M65: =IF(ISNUMBER($D65),$D65*(1+$G65)^(M$7-$I$7)*IF($F65>1,(1+($F65-1)*(1-$H65)^(M$7-$I$7))/$F65,1),"n/a") -> 85827881 | N65: =IF(ISNUMBER($D65),$D65*(1+$G65)^(N$7-$I$7)*IF($F65>1,(1+($F65-1)*(1-$H65)^(N$7-$I$7))/$F65,1),"n/a") -> 85719787 | O65: =IF(ISNUMBER($D65),$D65*(1+$G65)^(O$7-$I$7)*IF($F65>1,(1+($F65-1)*(1-$H65)^(O$7-$I$7))/$F65,1),"n/a") -> 85612774 | P65: =IF(ISNUMBER($D65),$D65*(1+$G65)^(P$7-$I$7)*IF($F65>1,(1+($F65-1)*(1-$H65)^(P$7-$I$7))/$F65,1),"n/a") -> 85506832 | ... AK65: =IF(ISNUMBER($D65),$D65*(1+$G65)^(AK$7-$I$7)*IF($F65>1,(1+($F65-1)*(1-$H65)^(AK$7-$I$7))/$F65,1),"n/a") -> 83511196
A66: 9 | B66: Ship - Passenger | C66: Gasoline | D66: ='Fuel Price'!E91 -> n/a | E66: ='Fuel Price'!$J$91 -> 75018509 | F66: =IF(ISNUMBER(D66),D66/E66,"n/a") -> n/a | G66: =Assumptions!$E$26 -> 0 | H66: {=INDEX(Assumptions!$B$34:$B$40,MATCH($C66,Assumptions!$A$34:$A$40,0))} -> 0 | I66: =IF(ISNUMBER($D66),$D66*(1+$G66)^(I$7-$I$7)*IF($F66>1,(1+($F66-1)*(1-$H66)^(I$7-$I$7))/$F66,1),"n/a") -> n/a | J66: =IF(ISNUMBER($D66),$D66*(1+$G66)^(J$7-$I$7)*IF($F66>1,(1+($F66-1)*(1-$H66)^(J$7-$I$7))/$F66,1),"n/a") -> n/a | K66: =IF(ISNUMBER($D66),$D66*(1+$G66)^(K$7-$I$7)*IF($F66>1,(1+($F66-1)*(1-$H66)^(K$7-$I$7))/$F66,1),"n/a") -> n/a | L66: =IF(ISNUMBER($D66),$D66*(1+$G66)^(L$7-$I$7)*IF($F66>1,(1+($F66-1)*(1-$H66)^(L$7-$I$7))/$F66,1),"n/a") -> n/a | M66: =IF(ISNUMBER($D66),$D66*(1+$G66)^(M$7-$I$7)*IF($F66>1,(1+($F66-1)*(1-$H66)^(M$7-$I$7))/$F66,1),"n/a") -> n/a | N66: =IF(ISNUMBER($D66),$D66*(1+$G66)^(N$7-$I$7)*IF($F66>1,(1+($F66-1)*(1-$H66)^(N$7-$I$7))/$F66,1),"n/a") -> n/a | O66: =IF(ISNUMBER($D66),$D66*(1+$G66)^(O$7-$I$7)*IF($F66>1,(1+($F66-1)*(1-$H66)^(O$7-$I$7))/$F66,1),"n/a") -> n/a | P66: =IF(ISNUMBER($D66),$D66*(1+$G66)^(P$7-$I$7)*IF($F66>1,(1+($F66-1)*(1-$H66)^(P$7-$I$7))/$F66,1),"n/a") -> n/a | ... AK66: =IF(ISNUMBER($D66),$D66*(1+$G66)^(AK$7-$I$7)*IF($F66>1,(1+($F66-1)*(1-$H66)^(AK$7-$I$7))/$F66,1),"n/a") -> n/a
A67: 9 | B67: Ship - Passenger | C67: Diesel | D67: ='Fuel Price'!F91 -> 75018509 | E67: ='Fuel Price'!$J$91 -> 75018509 | F67: =IF(ISNUMBER(D67),D67/E67,"n/a") -> 1 | G67: =Assumptions!$E$26 -> 0 | H67: {=INDEX(Assumptions!$B$34:$B$40,MATCH($C67,Assumptions!$A$34:$A$40,0))} -> 0 | I67: =IF(ISNUMBER($D67),$D67*(1+$G67)^(I$7-$I$7)*IF($F67>1,(1+($F67-1)*(1-$H67)^(I$7-$I$7))/$F67,1),"n/a") -> 75018509 | J67: =IF(ISNUMBER($D67),$D67*(1+$G67)^(J$7-$I$7)*IF($F67>1,(1+($F67-1)*(1-$H67)^(J$7-$I$7))/$F67,1),"n/a") -> 75018509 | K67: =IF(ISNUMBER($D67),$D67*(1+$G67)^(K$7-$I$7)*IF($F67>1,(1+($F67-1)*(1-$H67)^(K$7-$I$7))/$F67,1),"n/a") -> 75018509 | L67: =IF(ISNUMBER($D67),$D67*(1+$G67)^(L$7-$I$7)*IF($F67>1,(1+($F67-1)*(1-$H67)^(L$7-$I$7))/$F67,1),"n/a") -> 75018509 | M67: =IF(ISNUMBER($D67),$D67*(1+$G67)^(M$7-$I$7)*IF($F67>1,(1+($F67-1)*(1-$H67)^(M$7-$I$7))/$F67,1),"n/a") -> 75018509 | N67: =IF(ISNUMBER($D67),$D67*(1+$G67)^(N$7-$I$7)*IF($F67>1,(1+($F67-1)*(1-$H67)^(N$7-$I$7))/$F67,1),"n/a") -> 75018509 | O67: =IF(ISNUMBER($D67),$D67*(1+$G67)^(O$7-$I$7)*IF($F67>1,(1+($F67-1)*(1-$H67)^(O$7-$I$7))/$F67,1),"n/a") -> 75018509 | P67: =IF(ISNUMBER($D67),$D67*(1+$G67)^(P$7-$I$7)*IF($F67>1,(1+($F67-1)*(1-$H67)^(P$7-$I$7))/$F67,1),"n/a") -> 75018509 | ... AK67: =IF(ISNUMBER($D67),$D67*(1+$G67)^(AK$7-$I$7)*IF($F67>1,(1+($F67-1)*(1-$H67)^(AK$7-$I$7))/$F67,1),"n/a") -> 75018509
A68: 9 | B68: Ship - Passenger | C68: PHEV | D68: ='Fuel Price'!G91 -> 93773136 | E68: ='Fuel Price'!$J$91 -> 75018509 | F68: =IF(ISNUMBER(D68),D68/E68,"n/a") -> 1.25 | G68: =Assumptions!$E$26 -> 0 | H68: {=INDEX(Assumptions!$B$34:$B$40,MATCH($C68,Assumptions!$A$34:$A$40,0))} -> 0.02 | I68: =IF(ISNUMBER($D68),$D68*(1+$G68)^(I$7-$I$7)*IF($F68>1,(1+($F68-1)*(1-$H68)^(I$7-$I$7))/$F68,1),"n/a") -> 93773136 | J68: =IF(ISNUMBER($D68),$D68*(1+$G68)^(J$7-$I$7)*IF($F68>1,(1+($F68-1)*(1-$H68)^(J$7-$I$7))/$F68,1),"n/a") -> 93398044 | K68: =IF(ISNUMBER($D68),$D68*(1+$G68)^(K$7-$I$7)*IF($F68>1,(1+($F68-1)*(1-$H68)^(K$7-$I$7))/$F68,1),"n/a") -> 93030453 | L68: =IF(ISNUMBER($D68),$D68*(1+$G68)^(L$7-$I$7)*IF($F68>1,(1+($F68-1)*(1-$H68)^(L$7-$I$7))/$F68,1),"n/a") -> 92670214 | M68: =IF(ISNUMBER($D68),$D68*(1+$G68)^(M$7-$I$7)*IF($F68>1,(1+($F68-1)*(1-$H68)^(M$7-$I$7))/$F68,1),"n/a") -> 92317180 | N68: =IF(ISNUMBER($D68),$D68*(1+$G68)^(N$7-$I$7)*IF($F68>1,(1+($F68-1)*(1-$H68)^(N$7-$I$7))/$F68,1),"n/a") -> 91971207 | O68: =IF(ISNUMBER($D68),$D68*(1+$G68)^(O$7-$I$7)*IF($F68>1,(1+($F68-1)*(1-$H68)^(O$7-$I$7))/$F68,1),"n/a") -> 91632153 | P68: =IF(ISNUMBER($D68),$D68*(1+$G68)^(P$7-$I$7)*IF($F68>1,(1+($F68-1)*(1-$H68)^(P$7-$I$7))/$F68,1),"n/a") -> 91299880 | ... AK68: =IF(ISNUMBER($D68),$D68*(1+$G68)^(AK$7-$I$7)*IF($F68>1,(1+($F68-1)*(1-$H68)^(AK$7-$I$7))/$F68,1),"n/a") -> 85670690
A69: 9 | B69: Ship - Passenger | C69: LPG | D69: ='Fuel Price'!H91 -> 82520360 | E69: ='Fuel Price'!$J$91 -> 75018509 | F69: =IF(ISNUMBER(D69),D69/E69,"n/a") -> 1.1 | G69: =Assumptions!$E$26 -> 0 | H69: {=INDEX(Assumptions!$B$34:$B$40,MATCH($C69,Assumptions!$A$34:$A$40,0))} -> 0.01 | I69: =IF(ISNUMBER($D69),$D69*(1+$G69)^(I$7-$I$7)*IF($F69>1,(1+($F69-1)*(1-$H69)^(I$7-$I$7))/$F69,1),"n/a") -> 82520360 | J69: =IF(ISNUMBER($D69),$D69*(1+$G69)^(J$7-$I$7)*IF($F69>1,(1+($F69-1)*(1-$H69)^(J$7-$I$7))/$F69,1),"n/a") -> 82445341 | K69: =IF(ISNUMBER($D69),$D69*(1+$G69)^(K$7-$I$7)*IF($F69>1,(1+($F69-1)*(1-$H69)^(K$7-$I$7))/$F69,1),"n/a") -> 82371073 | L69: =IF(ISNUMBER($D69),$D69*(1+$G69)^(L$7-$I$7)*IF($F69>1,(1+($F69-1)*(1-$H69)^(L$7-$I$7))/$F69,1),"n/a") -> 82297547 | M69: =IF(ISNUMBER($D69),$D69*(1+$G69)^(M$7-$I$7)*IF($F69>1,(1+($F69-1)*(1-$H69)^(M$7-$I$7))/$F69,1),"n/a") -> 82224757 | N69: =IF(ISNUMBER($D69),$D69*(1+$G69)^(N$7-$I$7)*IF($F69>1,(1+($F69-1)*(1-$H69)^(N$7-$I$7))/$F69,1),"n/a") -> 82152694 | O69: =IF(ISNUMBER($D69),$D69*(1+$G69)^(O$7-$I$7)*IF($F69>1,(1+($F69-1)*(1-$H69)^(O$7-$I$7))/$F69,1),"n/a") -> 82081353 | P69: =IF(ISNUMBER($D69),$D69*(1+$G69)^(P$7-$I$7)*IF($F69>1,(1+($F69-1)*(1-$H69)^(P$7-$I$7))/$F69,1),"n/a") -> 82010724 | ... AK69: =IF(ISNUMBER($D69),$D69*(1+$G69)^(AK$7-$I$7)*IF($F69>1,(1+($F69-1)*(1-$H69)^(AK$7-$I$7))/$F69,1),"n/a") -> 80680300
A70: 9 | B70: Ship - Passenger | C70: Hydrogen | D70: ='Fuel Price'!I91 -> 1.8754627e+08 | E70: ='Fuel Price'!$J$91 -> 75018509 | F70: =IF(ISNUMBER(D70),D70/E70,"n/a") -> 2.5 | G70: =Assumptions!$E$26 -> 0 | H70: {=INDEX(Assumptions!$B$34:$B$40,MATCH($C70,Assumptions!$A$34:$A$40,0))} -> 0.03 | I70: =IF(ISNUMBER($D70),$D70*(1+$G70)^(I$7-$I$7)*IF($F70>1,(1+($F70-1)*(1-$H70)^(I$7-$I$7))/$F70,1),"n/a") -> 1.8754627e+08 | J70: =IF(ISNUMBER($D70),$D70*(1+$G70)^(J$7-$I$7)*IF($F70>1,(1+($F70-1)*(1-$H70)^(J$7-$I$7))/$F70,1),"n/a") -> 1.8417044e+08 | K70: =IF(ISNUMBER($D70),$D70*(1+$G70)^(K$7-$I$7)*IF($F70>1,(1+($F70-1)*(1-$H70)^(K$7-$I$7))/$F70,1),"n/a") -> 1.8089588e+08 | L70: =IF(ISNUMBER($D70),$D70*(1+$G70)^(L$7-$I$7)*IF($F70>1,(1+($F70-1)*(1-$H70)^(L$7-$I$7))/$F70,1),"n/a") -> 1.7771956e+08 | M70: =IF(ISNUMBER($D70),$D70*(1+$G70)^(M$7-$I$7)*IF($F70>1,(1+($F70-1)*(1-$H70)^(M$7-$I$7))/$F70,1),"n/a") -> 1.7463853e+08 | N70: =IF(ISNUMBER($D70),$D70*(1+$G70)^(N$7-$I$7)*IF($F70>1,(1+($F70-1)*(1-$H70)^(N$7-$I$7))/$F70,1),"n/a") -> 1.7164993e+08 | O70: =IF(ISNUMBER($D70),$D70*(1+$G70)^(O$7-$I$7)*IF($F70>1,(1+($F70-1)*(1-$H70)^(O$7-$I$7))/$F70,1),"n/a") -> 1.6875099e+08 | P70: =IF(ISNUMBER($D70),$D70*(1+$G70)^(P$7-$I$7)*IF($F70>1,(1+($F70-1)*(1-$H70)^(P$7-$I$7))/$F70,1),"n/a") -> 1.6593901e+08 | ... AK70: =IF(ISNUMBER($D70),$D70*(1+$G70)^(AK$7-$I$7)*IF($F70>1,(1+($F70-1)*(1-$H70)^(AK$7-$I$7))/$F70,1),"n/a") -> 1.229773e+08
A71: 10 | B71: Ship - Freight | C71: BEV | D71: ='Fuel Price'!C92 -> n/a | E71: ='Fuel Price'!$J$92 -> 4.0037794e+08 | F71: =IF(ISNUMBER(D71),D71/E71,"n/a") -> n/a | G71: =Assumptions!$E$27 -> 0 | H71: {=INDEX(Assumptions!$B$34:$B$40,MATCH($C71,Assumptions!$A$34:$A$40,0))} -> 0.03 | I71: =IF(ISNUMBER($D71),$D71*(1+$G71)^(I$7-$I$7)*IF($F71>1,(1+($F71-1)*(1-$H71)^(I$7-$I$7))/$F71,1),"n/a") -> n/a | J71: =IF(ISNUMBER($D71),$D71*(1+$G71)^(J$7-$I$7)*IF($F71>1,(1+($F71-1)*(1-$H71)^(J$7-$I$7))/$F71,1),"n/a") -> n/a | K71: =IF(ISNUMBER($D71),$D71*(1+$G71)^(K$7-$I$7)*IF($F71>1,(1+($F71-1)*(1-$H71)^(K$7-$I$7))/$F71,1),"n/a") -> n/a | L71: =IF(ISNUMBER($D71),$D71*(1+$G71)^(L$7-$I$7)*IF($F71>1,(1+($F71-1)*(1-$H71)^(L$7-$I$7))/$F71,1),"n/a") -> n/a | M71: =IF(ISNUMBER($D71),$D71*(1+$G71)^(M$7-$I$7)*IF($F71>1,(1+($F71-1)*(1-$H71)^(M$7-$I$7))/$F71,1),"n/a") -> n/a | N71: =IF(ISNUMBER($D71),$D71*(1+$G71)^(N$7-$I$7)*IF($F71>1,(1+($F71-1)*(1-$H71)^(N$7-$I$7))/$F71,1),"n/a") -> n/a | O71: =IF(ISNUMBER($D71),$D71*(1+$G71)^(O$7-$I$7)*IF($F71>1,(1+($F71-1)*(1-$H71)^(O$7-$I$7))/$F71,1),"n/a") -> n/a | P71: =IF(ISNUMBER($D71),$D71*(1+$G71)^(P$7-$I$7)*IF($F71>1,(1+($F71-1)*(1-$H71)^(P$7-$I$7))/$F71,1),"n/a") -> n/a | ... AK71: =IF(ISNUMBER($D71),$D71*(1+$G71)^(AK$7-$I$7)*IF($F71>1,(1+($F71-1)*(1-$H71)^(AK$7-$I$7))/$F71,1),"n/a") -> n/a
A72: 10 | B72: Ship - Freight | C72: NGV | D72: ='Fuel Price'!D92 -> 4.6043463e+08 | E72: ='Fuel Price'!$J$92 -> 4.0037794e+08 | F72: =IF(ISNUMBER(D72),D72/E72,"n/a") -> 1.15 | G72: =Assumptions!$E$27 -> 0 | H72: {=INDEX(Assumptions!$B$34:$B$40,MATCH($C72,Assumptions!$A$34:$A$40,0))} -> 0.01 | I72: =IF(ISNUMBER($D72),$D72*(1+$G72)^(I$7-$I$7)*IF($F72>1,(1+($F72-1)*(1-$H72)^(I$7-$I$7))/$F72,1),"n/a") -> 4.6043463e+08 | J72: =IF(ISNUMBER($D72),$D72*(1+$G72)^(J$7-$I$7)*IF($F72>1,(1+($F72-1)*(1-$H72)^(J$7-$I$7))/$F72,1),"n/a") -> 4.5983406e+08 | K72: =IF(ISNUMBER($D72),$D72*(1+$G72)^(K$7-$I$7)*IF($F72>1,(1+($F72-1)*(1-$H72)^(K$7-$I$7))/$F72,1),"n/a") -> 4.592395e+08 | L72: =IF(ISNUMBER($D72),$D72*(1+$G72)^(L$7-$I$7)*IF($F72>1,(1+($F72-1)*(1-$H72)^(L$7-$I$7))/$F72,1),"n/a") -> 4.5865089e+08 | M72: =IF(ISNUMBER($D72),$D72*(1+$G72)^(M$7-$I$7)*IF($F72>1,(1+($F72-1)*(1-$H72)^(M$7-$I$7))/$F72,1),"n/a") -> 4.5806816e+08 | N72: =IF(ISNUMBER($D72),$D72*(1+$G72)^(N$7-$I$7)*IF($F72>1,(1+($F72-1)*(1-$H72)^(N$7-$I$7))/$F72,1),"n/a") -> 4.5749125e+08 | O72: =IF(ISNUMBER($D72),$D72*(1+$G72)^(O$7-$I$7)*IF($F72>1,(1+($F72-1)*(1-$H72)^(O$7-$I$7))/$F72,1),"n/a") -> 4.5692012e+08 | P72: =IF(ISNUMBER($D72),$D72*(1+$G72)^(P$7-$I$7)*IF($F72>1,(1+($F72-1)*(1-$H72)^(P$7-$I$7))/$F72,1),"n/a") -> 4.563547e+08 | ... AK72: =IF(ISNUMBER($D72),$D72*(1+$G72)^(AK$7-$I$7)*IF($F72>1,(1+($F72-1)*(1-$H72)^(AK$7-$I$7))/$F72,1),"n/a") -> 4.4570388e+08
A73: 10 | B73: Ship - Freight | C73: Gasoline | D73: ='Fuel Price'!E92 -> n/a | E73: ='Fuel Price'!$J$92 -> 4.0037794e+08 | F73: =IF(ISNUMBER(D73),D73/E73,"n/a") -> n/a | G73: =Assumptions!$E$27 -> 0 | H73: {=INDEX(Assumptions!$B$34:$B$40,MATCH($C73,Assumptions!$A$34:$A$40,0))} -> 0 | I73: =IF(ISNUMBER($D73),$D73*(1+$G73)^(I$7-$I$7)*IF($F73>1,(1+($F73-1)*(1-$H73)^(I$7-$I$7))/$F73,1),"n/a") -> n/a | J73: =IF(ISNUMBER($D73),$D73*(1+$G73)^(J$7-$I$7)*IF($F73>1,(1+($F73-1)*(1-$H73)^(J$7-$I$7))/$F73,1),"n/a") -> n/a | K73: =IF(ISNUMBER($D73),$D73*(1+$G73)^(K$7-$I$7)*IF($F73>1,(1+($F73-1)*(1-$H73)^(K$7-$I$7))/$F73,1),"n/a") -> n/a | L73: =IF(ISNUMBER($D73),$D73*(1+$G73)^(L$7-$I$7)*IF($F73>1,(1+($F73-1)*(1-$H73)^(L$7-$I$7))/$F73,1),"n/a") -> n/a | M73: =IF(ISNUMBER($D73),$D73*(1+$G73)^(M$7-$I$7)*IF($F73>1,(1+($F73-1)*(1-$H73)^(M$7-$I$7))/$F73,1),"n/a") -> n/a | N73: =IF(ISNUMBER($D73),$D73*(1+$G73)^(N$7-$I$7)*IF($F73>1,(1+($F73-1)*(1-$H73)^(N$7-$I$7))/$F73,1),"n/a") -> n/a | O73: =IF(ISNUMBER($D73),$D73*(1+$G73)^(O$7-$I$7)*IF($F73>1,(1+($F73-1)*(1-$H73)^(O$7-$I$7))/$F73,1),"n/a") -> n/a | P73: =IF(ISNUMBER($D73),$D73*(1+$G73)^(P$7-$I$7)*IF($F73>1,(1+($F73-1)*(1-$H73)^(P$7-$I$7))/$F73,1),"n/a") -> n/a | ... AK73: =IF(ISNUMBER($D73),$D73*(1+$G73)^(AK$7-$I$7)*IF($F73>1,(1+($F73-1)*(1-$H73)^(AK$7-$I$7))/$F73,1),"n/a") -> n/a
A74: 10 | B74: Ship - Freight | C74: Diesel | D74: ='Fuel Price'!F92 -> 4.0037794e+08 | E74: ='Fuel Price'!$J$92 -> 4.0037794e+08 | F74: =IF(ISNUMBER(D74),D74/E74,"n/a") -> 1 | G74: =Assumptions!$E$27 -> 0 | H74: {=INDEX(Assumptions!$B$34:$B$40,MATCH($C74,Assumptions!$A$34:$A$40,0))} -> 0 | I74: =IF(ISNUMBER($D74),$D74*(1+$G74)^(I$7-$I$7)*IF($F74>1,(1+($F74-1)*(1-$H74)^(I$7-$I$7))/$F74,1),"n/a") -> 4.0037794e+08 | J74: =IF(ISNUMBER($D74),$D74*(1+$G74)^(J$7-$I$7)*IF($F74>1,(1+($F74-1)*(1-$H74)^(J$7-$I$7))/$F74,1),"n/a") -> 4.0037794e+08 | K74: =IF(ISNUMBER($D74),$D74*(1+$G74)^(K$7-$I$7)*IF($F74>1,(1+($F74-1)*(1-$H74)^(K$7-$I$7))/$F74,1),"n/a") -> 4.0037794e+08 | L74: =IF(ISNUMBER($D74),$D74*(1+$G74)^(L$7-$I$7)*IF($F74>1,(1+($F74-1)*(1-$H74)^(L$7-$I$7))/$F74,1),"n/a") -> 4.0037794e+08 | M74: =IF(ISNUMBER($D74),$D74*(1+$G74)^(M$7-$I$7)*IF($F74>1,(1+($F74-1)*(1-$H74)^(M$7-$I$7))/$F74,1),"n/a") -> 4.0037794e+08 | N74: =IF(ISNUMBER($D74),$D74*(1+$G74)^(N$7-$I$7)*IF($F74>1,(1+($F74-1)*(1-$H74)^(N$7-$I$7))/$F74,1),"n/a") -> 4.0037794e+08 | O74: =IF(ISNUMBER($D74),$D74*(1+$G74)^(O$7-$I$7)*IF($F74>1,(1+($F74-1)*(1-$H74)^(O$7-$I$7))/$F74,1),"n/a") -> 4.0037794e+08 | P74: =IF(ISNUMBER($D74),$D74*(1+$G74)^(P$7-$I$7)*IF($F74>1,(1+($F74-1)*(1-$H74)^(P$7-$I$7))/$F74,1),"n/a") -> 4.0037794e+08 | ... AK74: =IF(ISNUMBER($D74),$D74*(1+$G74)^(AK$7-$I$7)*IF($F74>1,(1+($F74-1)*(1-$H74)^(AK$7-$I$7))/$F74,1),"n/a") -> 4.0037794e+08
A75: 10 | B75: Ship - Freight | C75: PHEV | D75: ='Fuel Price'!G92 -> 4.6043463e+08 | E75: ='Fuel Price'!$J$92 -> 4.0037794e+08 | F75: =IF(ISNUMBER(D75),D75/E75,"n/a") -> 1.15 | G75: =Assumptions!$E$27 -> 0 | H75: {=INDEX(Assumptions!$B$34:$B$40,MATCH($C75,Assumptions!$A$34:$A$40,0))} -> 0.02 | I75: =IF(ISNUMBER($D75),$D75*(1+$G75)^(I$7-$I$7)*IF($F75>1,(1+($F75-1)*(1-$H75)^(I$7-$I$7))/$F75,1),"n/a") -> 4.6043463e+08 | J75: =IF(ISNUMBER($D75),$D75*(1+$G75)^(J$7-$I$7)*IF($F75>1,(1+($F75-1)*(1-$H75)^(J$7-$I$7))/$F75,1),"n/a") -> 4.592335e+08 | K75: =IF(ISNUMBER($D75),$D75*(1+$G75)^(K$7-$I$7)*IF($F75>1,(1+($F75-1)*(1-$H75)^(K$7-$I$7))/$F75,1),"n/a") -> 4.5805639e+08 | L75: =IF(ISNUMBER($D75),$D75*(1+$G75)^(L$7-$I$7)*IF($F75>1,(1+($F75-1)*(1-$H75)^(L$7-$I$7))/$F75,1),"n/a") -> 4.5690282e+08 | M75: =IF(ISNUMBER($D75),$D75*(1+$G75)^(M$7-$I$7)*IF($F75>1,(1+($F75-1)*(1-$H75)^(M$7-$I$7))/$F75,1),"n/a") -> 4.5577232e+08 | N75: =IF(ISNUMBER($D75),$D75*(1+$G75)^(N$7-$I$7)*IF($F75>1,(1+($F75-1)*(1-$H75)^(N$7-$I$7))/$F75,1),"n/a") -> 4.5466443e+08 | O75: =IF(ISNUMBER($D75),$D75*(1+$G75)^(O$7-$I$7)*IF($F75>1,(1+($F75-1)*(1-$H75)^(O$7-$I$7))/$F75,1),"n/a") -> 4.535787e+08 | P75: =IF(ISNUMBER($D75),$D75*(1+$G75)^(P$7-$I$7)*IF($F75>1,(1+($F75-1)*(1-$H75)^(P$7-$I$7))/$F75,1),"n/a") -> 4.5251469e+08 | ... AK75: =IF(ISNUMBER($D75),$D75*(1+$G75)^(AK$7-$I$7)*IF($F75>1,(1+($F75-1)*(1-$H75)^(AK$7-$I$7))/$F75,1),"n/a") -> 4.3448871e+08
A76: 10 | B76: Ship - Freight | C76: LPG | D76: ='Fuel Price'!H92 -> 4.4041573e+08 | E76: ='Fuel Price'!$J$92 -> 4.0037794e+08 | F76: =IF(ISNUMBER(D76),D76/E76,"n/a") -> 1.1 | G76: =Assumptions!$E$27 -> 0 | H76: {=INDEX(Assumptions!$B$34:$B$40,MATCH($C76,Assumptions!$A$34:$A$40,0))} -> 0.01 | I76: =IF(ISNUMBER($D76),$D76*(1+$G76)^(I$7-$I$7)*IF($F76>1,(1+($F76-1)*(1-$H76)^(I$7-$I$7))/$F76,1),"n/a") -> 4.4041573e+08 | J76: =IF(ISNUMBER($D76),$D76*(1+$G76)^(J$7-$I$7)*IF($F76>1,(1+($F76-1)*(1-$H76)^(J$7-$I$7))/$F76,1),"n/a") -> 4.4001536e+08 | K76: =IF(ISNUMBER($D76),$D76*(1+$G76)^(K$7-$I$7)*IF($F76>1,(1+($F76-1)*(1-$H76)^(K$7-$I$7))/$F76,1),"n/a") -> 4.3961898e+08 | L76: =IF(ISNUMBER($D76),$D76*(1+$G76)^(L$7-$I$7)*IF($F76>1,(1+($F76-1)*(1-$H76)^(L$7-$I$7))/$F76,1),"n/a") -> 4.3922657e+08 | M76: =IF(ISNUMBER($D76),$D76*(1+$G76)^(M$7-$I$7)*IF($F76>1,(1+($F76-1)*(1-$H76)^(M$7-$I$7))/$F76,1),"n/a") -> 4.3883808e+08 | N76: =IF(ISNUMBER($D76),$D76*(1+$G76)^(N$7-$I$7)*IF($F76>1,(1+($F76-1)*(1-$H76)^(N$7-$I$7))/$F76,1),"n/a") -> 4.3845348e+08 | O76: =IF(ISNUMBER($D76),$D76*(1+$G76)^(O$7-$I$7)*IF($F76>1,(1+($F76-1)*(1-$H76)^(O$7-$I$7))/$F76,1),"n/a") -> 4.3807273e+08 | P76: =IF(ISNUMBER($D76),$D76*(1+$G76)^(P$7-$I$7)*IF($F76>1,(1+($F76-1)*(1-$H76)^(P$7-$I$7))/$F76,1),"n/a") -> 4.3769578e+08 | ... AK76: =IF(ISNUMBER($D76),$D76*(1+$G76)^(AK$7-$I$7)*IF($F76>1,(1+($F76-1)*(1-$H76)^(AK$7-$I$7))/$F76,1),"n/a") -> 4.3059523e+08
A77: 10 | B77: Ship - Freight | C77: Hydrogen | D77: ='Fuel Price'!I92 -> n/a | E77: ='Fuel Price'!$J$92 -> 4.0037794e+08 | F77: =IF(ISNUMBER(D77),D77/E77,"n/a") -> n/a | G77: =Assumptions!$E$27 -> 0 | H77: {=INDEX(Assumptions!$B$34:$B$40,MATCH($C77,Assumptions!$A$34:$A$40,0))} -> 0.03 | I77: =IF(ISNUMBER($D77),$D77*(1+$G77)^(I$7-$I$7)*IF($F77>1,(1+($F77-1)*(1-$H77)^(I$7-$I$7))/$F77,1),"n/a") -> n/a | J77: =IF(ISNUMBER($D77),$D77*(1+$G77)^(J$7-$I$7)*IF($F77>1,(1+($F77-1)*(1-$H77)^(J$7-$I$7))/$F77,1),"n/a") -> n/a | K77: =IF(ISNUMBER($D77),$D77*(1+$G77)^(K$7-$I$7)*IF($F77>1,(1+($F77-1)*(1-$H77)^(K$7-$I$7))/$F77,1),"n/a") -> n/a | L77: =IF(ISNUMBER($D77),$D77*(1+$G77)^(L$7-$I$7)*IF($F77>1,(1+($F77-1)*(1-$H77)^(L$7-$I$7))/$F77,1),"n/a") -> n/a | M77: =IF(ISNUMBER($D77),$D77*(1+$G77)^(M$7-$I$7)*IF($F77>1,(1+($F77-1)*(1-$H77)^(M$7-$I$7))/$F77,1),"n/a") -> n/a | N77: =IF(ISNUMBER($D77),$D77*(1+$G77)^(N$7-$I$7)*IF($F77>1,(1+($F77-1)*(1-$H77)^(N$7-$I$7))/$F77,1),"n/a") -> n/a | O77: =IF(ISNUMBER($D77),$D77*(1+$G77)^(O$7-$I$7)*IF($F77>1,(1+($F77-1)*(1-$H77)^(O$7-$I$7))/$F77,1),"n/a") -> n/a | P77: =IF(ISNUMBER($D77),$D77*(1+$G77)^(P$7-$I$7)*IF($F77>1,(1+($F77-1)*(1-$H77)^(P$7-$I$7))/$F77,1),"n/a") -> n/a | ... AK77: =IF(ISNUMBER($D77),$D77*(1+$G77)^(AK$7-$I$7)*IF($F77>1,(1+($F77-1)*(1-$H77)^(AK$7-$I$7))/$F77,1),"n/a") -> n/a
A78: 11 | B78: Rail - Passenger | C78: BEV | D78: ='Fuel Price'!C93 -> 64329558 | E78: ='Fuel Price'!$J$93 -> 64329558 | F78: =IF(ISNUMBER(D78),D78/E78,"n/a") -> 1 | G78: =Assumptions!$E$28 -> 0 | H78: {=INDEX(Assumptions!$B$34:$B$40,MATCH($C78,Assumptions!$A$34:$A$40,0))} -> 0.03 | I78: =IF(ISNUMBER($D78),$D78*(1+$G78)^(I$7-$I$7)*IF($F78>1,(1+($F78-1)*(1-$H78)^(I$7-$I$7))/$F78,1),"n/a") -> 64329558 | J78: =IF(ISNUMBER($D78),$D78*(1+$G78)^(J$7-$I$7)*IF($F78>1,(1+($F78-1)*(1-$H78)^(J$7-$I$7))/$F78,1),"n/a") -> 64329558 | K78: =IF(ISNUMBER($D78),$D78*(1+$G78)^(K$7-$I$7)*IF($F78>1,(1+($F78-1)*(1-$H78)^(K$7-$I$7))/$F78,1),"n/a") -> 64329558 | L78: =IF(ISNUMBER($D78),$D78*(1+$G78)^(L$7-$I$7)*IF($F78>1,(1+($F78-1)*(1-$H78)^(L$7-$I$7))/$F78,1),"n/a") -> 64329558 | M78: =IF(ISNUMBER($D78),$D78*(1+$G78)^(M$7-$I$7)*IF($F78>1,(1+($F78-1)*(1-$H78)^(M$7-$I$7))/$F78,1),"n/a") -> 64329558 | N78: =IF(ISNUMBER($D78),$D78*(1+$G78)^(N$7-$I$7)*IF($F78>1,(1+($F78-1)*(1-$H78)^(N$7-$I$7))/$F78,1),"n/a") -> 64329558 | O78: =IF(ISNUMBER($D78),$D78*(1+$G78)^(O$7-$I$7)*IF($F78>1,(1+($F78-1)*(1-$H78)^(O$7-$I$7))/$F78,1),"n/a") -> 64329558 | P78: =IF(ISNUMBER($D78),$D78*(1+$G78)^(P$7-$I$7)*IF($F78>1,(1+($F78-1)*(1-$H78)^(P$7-$I$7))/$F78,1),"n/a") -> 64329558 | ... AK78: =IF(ISNUMBER($D78),$D78*(1+$G78)^(AK$7-$I$7)*IF($F78>1,(1+($F78-1)*(1-$H78)^(AK$7-$I$7))/$F78,1),"n/a") -> 64329558
A79: 11 | B79: Rail - Passenger | C79: NGV | D79: ='Fuel Price'!D93 -> n/a | E79: ='Fuel Price'!$J$93 -> 64329558 | F79: =IF(ISNUMBER(D79),D79/E79,"n/a") -> n/a | G79: =Assumptions!$E$28 -> 0 | H79: {=INDEX(Assumptions!$B$34:$B$40,MATCH($C79,Assumptions!$A$34:$A$40,0))} -> 0.01 | I79: =IF(ISNUMBER($D79),$D79*(1+$G79)^(I$7-$I$7)*IF($F79>1,(1+($F79-1)*(1-$H79)^(I$7-$I$7))/$F79,1),"n/a") -> n/a | J79: =IF(ISNUMBER($D79),$D79*(1+$G79)^(J$7-$I$7)*IF($F79>1,(1+($F79-1)*(1-$H79)^(J$7-$I$7))/$F79,1),"n/a") -> n/a | K79: =IF(ISNUMBER($D79),$D79*(1+$G79)^(K$7-$I$7)*IF($F79>1,(1+($F79-1)*(1-$H79)^(K$7-$I$7))/$F79,1),"n/a") -> n/a | L79: =IF(ISNUMBER($D79),$D79*(1+$G79)^(L$7-$I$7)*IF($F79>1,(1+($F79-1)*(1-$H79)^(L$7-$I$7))/$F79,1),"n/a") -> n/a | M79: =IF(ISNUMBER($D79),$D79*(1+$G79)^(M$7-$I$7)*IF($F79>1,(1+($F79-1)*(1-$H79)^(M$7-$I$7))/$F79,1),"n/a") -> n/a | N79: =IF(ISNUMBER($D79),$D79*(1+$G79)^(N$7-$I$7)*IF($F79>1,(1+($F79-1)*(1-$H79)^(N$7-$I$7))/$F79,1),"n/a") -> n/a | O79: =IF(ISNUMBER($D79),$D79*(1+$G79)^(O$7-$I$7)*IF($F79>1,(1+($F79-1)*(1-$H79)^(O$7-$I$7))/$F79,1),"n/a") -> n/a | P79: =IF(ISNUMBER($D79),$D79*(1+$G79)^(P$7-$I$7)*IF($F79>1,(1+($F79-1)*(1-$H79)^(P$7-$I$7))/$F79,1),"n/a") -> n/a | ... AK79: =IF(ISNUMBER($D79),$D79*(1+$G79)^(AK$7-$I$7)*IF($F79>1,(1+($F79-1)*(1-$H79)^(AK$7-$I$7))/$F79,1),"n/a") -> n/a
A80: 11 | B80: Rail - Passenger | C80: Gasoline | D80: ='Fuel Price'!E93 -> n/a | E80: ='Fuel Price'!$J$93 -> 64329558 | F80: =IF(ISNUMBER(D80),D80/E80,"n/a") -> n/a | G80: =Assumptions!$E$28 -> 0 | H80: {=INDEX(Assumptions!$B$34:$B$40,MATCH($C80,Assumptions!$A$34:$A$40,0))} -> 0 | I80: =IF(ISNUMBER($D80),$D80*(1+$G80)^(I$7-$I$7)*IF($F80>1,(1+($F80-1)*(1-$H80)^(I$7-$I$7))/$F80,1),"n/a") -> n/a | J80: =IF(ISNUMBER($D80),$D80*(1+$G80)^(J$7-$I$7)*IF($F80>1,(1+($F80-1)*(1-$H80)^(J$7-$I$7))/$F80,1),"n/a") -> n/a | K80: =IF(ISNUMBER($D80),$D80*(1+$G80)^(K$7-$I$7)*IF($F80>1,(1+($F80-1)*(1-$H80)^(K$7-$I$7))/$F80,1),"n/a") -> n/a | L80: =IF(ISNUMBER($D80),$D80*(1+$G80)^(L$7-$I$7)*IF($F80>1,(1+($F80-1)*(1-$H80)^(L$7-$I$7))/$F80,1),"n/a") -> n/a | M80: =IF(ISNUMBER($D80),$D80*(1+$G80)^(M$7-$I$7)*IF($F80>1,(1+($F80-1)*(1-$H80)^(M$7-$I$7))/$F80,1),"n/a") -> n/a | N80: =IF(ISNUMBER($D80),$D80*(1+$G80)^(N$7-$I$7)*IF($F80>1,(1+($F80-1)*(1-$H80)^(N$7-$I$7))/$F80,1),"n/a") -> n/a | O80: =IF(ISNUMBER($D80),$D80*(1+$G80)^(O$7-$I$7)*IF($F80>1,(1+($F80-1)*(1-$H80)^(O$7-$I$7))/$F80,1),"n/a") -> n/a | P80: =IF(ISNUMBER($D80),$D80*(1+$G80)^(P$7-$I$7)*IF($F80>1,(1+($F80-1)*(1-$H80)^(P$7-$I$7))/$F80,1),"n/a") -> n/a | ... AK80: =IF(ISNUMBER($D80),$D80*(1+$G80)^(AK$7-$I$7)*IF($F80>1,(1+($F80-1)*(1-$H80)^(AK$7-$I$7))/$F80,1),"n/a") -> n/a
A81: 11 | B81: Rail - Passenger | C81: Diesel | D81: ='Fuel Price'!F93 -> 51463646 | E81: ='Fuel Price'!$J$93 -> 64329558 | F81: =IF(ISNUMBER(D81),D81/E81,"n/a") -> 0.8 | G81: =Assumptions!$E$28 -> 0 | H81: {=INDEX(Assumptions!$B$34:$B$40,MATCH($C81,Assumptions!$A$34:$A$40,0))} -> 0 | I81: =IF(ISNUMBER($D81),$D81*(1+$G81)^(I$7-$I$7)*IF($F81>1,(1+($F81-1)*(1-$H81)^(I$7-$I$7))/$F81,1),"n/a") -> 51463646 | J81: =IF(ISNUMBER($D81),$D81*(1+$G81)^(J$7-$I$7)*IF($F81>1,(1+($F81-1)*(1-$H81)^(J$7-$I$7))/$F81,1),"n/a") -> 51463646 | K81: =IF(ISNUMBER($D81),$D81*(1+$G81)^(K$7-$I$7)*IF($F81>1,(1+($F81-1)*(1-$H81)^(K$7-$I$7))/$F81,1),"n/a") -> 51463646 | L81: =IF(ISNUMBER($D81),$D81*(1+$G81)^(L$7-$I$7)*IF($F81>1,(1+($F81-1)*(1-$H81)^(L$7-$I$7))/$F81,1),"n/a") -> 51463646 | M81: =IF(ISNUMBER($D81),$D81*(1+$G81)^(M$7-$I$7)*IF($F81>1,(1+($F81-1)*(1-$H81)^(M$7-$I$7))/$F81,1),"n/a") -> 51463646 | N81: =IF(ISNUMBER($D81),$D81*(1+$G81)^(N$7-$I$7)*IF($F81>1,(1+($F81-1)*(1-$H81)^(N$7-$I$7))/$F81,1),"n/a") -> 51463646 | O81: =IF(ISNUMBER($D81),$D81*(1+$G81)^(O$7-$I$7)*IF($F81>1,(1+($F81-1)*(1-$H81)^(O$7-$I$7))/$F81,1),"n/a") -> 51463646 | P81: =IF(ISNUMBER($D81),$D81*(1+$G81)^(P$7-$I$7)*IF($F81>1,(1+($F81-1)*(1-$H81)^(P$7-$I$7))/$F81,1),"n/a") -> 51463646 | ... AK81: =IF(ISNUMBER($D81),$D81*(1+$G81)^(AK$7-$I$7)*IF($F81>1,(1+($F81-1)*(1-$H81)^(AK$7-$I$7))/$F81,1),"n/a") -> 51463646
A82: 11 | B82: Rail - Passenger | C82: PHEV | D82: ='Fuel Price'!G93 -> n/a | E82: ='Fuel Price'!$J$93 -> 64329558 | F82: =IF(ISNUMBER(D82),D82/E82,"n/a") -> n/a | G82: =Assumptions!$E$28 -> 0 | H82: {=INDEX(Assumptions!$B$34:$B$40,MATCH($C82,Assumptions!$A$34:$A$40,0))} -> 0.02 | I82: =IF(ISNUMBER($D82),$D82*(1+$G82)^(I$7-$I$7)*IF($F82>1,(1+($F82-1)*(1-$H82)^(I$7-$I$7))/$F82,1),"n/a") -> n/a | J82: =IF(ISNUMBER($D82),$D82*(1+$G82)^(J$7-$I$7)*IF($F82>1,(1+($F82-1)*(1-$H82)^(J$7-$I$7))/$F82,1),"n/a") -> n/a | K82: =IF(ISNUMBER($D82),$D82*(1+$G82)^(K$7-$I$7)*IF($F82>1,(1+($F82-1)*(1-$H82)^(K$7-$I$7))/$F82,1),"n/a") -> n/a | L82: =IF(ISNUMBER($D82),$D82*(1+$G82)^(L$7-$I$7)*IF($F82>1,(1+($F82-1)*(1-$H82)^(L$7-$I$7))/$F82,1),"n/a") -> n/a | M82: =IF(ISNUMBER($D82),$D82*(1+$G82)^(M$7-$I$7)*IF($F82>1,(1+($F82-1)*(1-$H82)^(M$7-$I$7))/$F82,1),"n/a") -> n/a | N82: =IF(ISNUMBER($D82),$D82*(1+$G82)^(N$7-$I$7)*IF($F82>1,(1+($F82-1)*(1-$H82)^(N$7-$I$7))/$F82,1),"n/a") -> n/a | O82: =IF(ISNUMBER($D82),$D82*(1+$G82)^(O$7-$I$7)*IF($F82>1,(1+($F82-1)*(1-$H82)^(O$7-$I$7))/$F82,1),"n/a") -> n/a | P82: =IF(ISNUMBER($D82),$D82*(1+$G82)^(P$7-$I$7)*IF($F82>1,(1+($F82-1)*(1-$H82)^(P$7-$I$7))/$F82,1),"n/a") -> n/a | ... AK82: =IF(ISNUMBER($D82),$D82*(1+$G82)^(AK$7-$I$7)*IF($F82>1,(1+($F82-1)*(1-$H82)^(AK$7-$I$7))/$F82,1),"n/a") -> n/a
A83: 11 | B83: Rail - Passenger | C83: LPG | D83: ='Fuel Price'!H93 -> n/a | E83: ='Fuel Price'!$J$93 -> 64329558 | F83: =IF(ISNUMBER(D83),D83/E83,"n/a") -> n/a | G83: =Assumptions!$E$28 -> 0 | H83: {=INDEX(Assumptions!$B$34:$B$40,MATCH($C83,Assumptions!$A$34:$A$40,0))} -> 0.01 | I83: =IF(ISNUMBER($D83),$D83*(1+$G83)^(I$7-$I$7)*IF($F83>1,(1+($F83-1)*(1-$H83)^(I$7-$I$7))/$F83,1),"n/a") -> n/a | J83: =IF(ISNUMBER($D83),$D83*(1+$G83)^(J$7-$I$7)*IF($F83>1,(1+($F83-1)*(1-$H83)^(J$7-$I$7))/$F83,1),"n/a") -> n/a | K83: =IF(ISNUMBER($D83),$D83*(1+$G83)^(K$7-$I$7)*IF($F83>1,(1+($F83-1)*(1-$H83)^(K$7-$I$7))/$F83,1),"n/a") -> n/a | L83: =IF(ISNUMBER($D83),$D83*(1+$G83)^(L$7-$I$7)*IF($F83>1,(1+($F83-1)*(1-$H83)^(L$7-$I$7))/$F83,1),"n/a") -> n/a | M83: =IF(ISNUMBER($D83),$D83*(1+$G83)^(M$7-$I$7)*IF($F83>1,(1+($F83-1)*(1-$H83)^(M$7-$I$7))/$F83,1),"n/a") -> n/a | N83: =IF(ISNUMBER($D83),$D83*(1+$G83)^(N$7-$I$7)*IF($F83>1,(1+($F83-1)*(1-$H83)^(N$7-$I$7))/$F83,1),"n/a") -> n/a | O83: =IF(ISNUMBER($D83),$D83*(1+$G83)^(O$7-$I$7)*IF($F83>1,(1+($F83-1)*(1-$H83)^(O$7-$I$7))/$F83,1),"n/a") -> n/a | P83: =IF(ISNUMBER($D83),$D83*(1+$G83)^(P$7-$I$7)*IF($F83>1,(1+($F83-1)*(1-$H83)^(P$7-$I$7))/$F83,1),"n/a") -> n/a | ... AK83: =IF(ISNUMBER($D83),$D83*(1+$G83)^(AK$7-$I$7)*IF($F83>1,(1+($F83-1)*(1-$H83)^(AK$7-$I$7))/$F83,1),"n/a") -> n/a
A84: 11 | B84: Rail - Passenger | C84: Hydrogen | D84: ='Fuel Price'!I93 -> 96494337 | E84: ='Fuel Price'!$J$93 -> 64329558 | F84: =IF(ISNUMBER(D84),D84/E84,"n/a") -> 1.5 | G84: =Assumptions!$E$28 -> 0 | H84: {=INDEX(Assumptions!$B$34:$B$40,MATCH($C84,Assumptions!$A$34:$A$40,0))} -> 0.03 | I84: =IF(ISNUMBER($D84),$D84*(1+$G84)^(I$7-$I$7)*IF($F84>1,(1+($F84-1)*(1-$H84)^(I$7-$I$7))/$F84,1),"n/a") -> 96494337 | J84: =IF(ISNUMBER($D84),$D84*(1+$G84)^(J$7-$I$7)*IF($F84>1,(1+($F84-1)*(1-$H84)^(J$7-$I$7))/$F84,1),"n/a") -> 95529394 | K84: =IF(ISNUMBER($D84),$D84*(1+$G84)^(K$7-$I$7)*IF($F84>1,(1+($F84-1)*(1-$H84)^(K$7-$I$7))/$F84,1),"n/a") -> 94593398 | L84: =IF(ISNUMBER($D84),$D84*(1+$G84)^(L$7-$I$7)*IF($F84>1,(1+($F84-1)*(1-$H84)^(L$7-$I$7))/$F84,1),"n/a") -> 93685483 | M84: =IF(ISNUMBER($D84),$D84*(1+$G84)^(M$7-$I$7)*IF($F84>1,(1+($F84-1)*(1-$H84)^(M$7-$I$7))/$F84,1),"n/a") -> 92804805 | N84: =IF(ISNUMBER($D84),$D84*(1+$G84)^(N$7-$I$7)*IF($F84>1,(1+($F84-1)*(1-$H84)^(N$7-$I$7))/$F84,1),"n/a") -> 91950548 | O84: =IF(ISNUMBER($D84),$D84*(1+$G84)^(O$7-$I$7)*IF($F84>1,(1+($F84-1)*(1-$H84)^(O$7-$I$7))/$F84,1),"n/a") -> 91121918 | P84: =IF(ISNUMBER($D84),$D84*(1+$G84)^(P$7-$I$7)*IF($F84>1,(1+($F84-1)*(1-$H84)^(P$7-$I$7))/$F84,1),"n/a") -> 90318148 | ... AK84: =IF(ISNUMBER($D84),$D84*(1+$G84)^(AK$7-$I$7)*IF($F84>1,(1+($F84-1)*(1-$H84)^(AK$7-$I$7))/$F84,1),"n/a") -> 78038033
A85: 12 | B85: Rail - Freight | C85: BEV | D85: ='Fuel Price'!C94 -> 29252627 | E85: ='Fuel Price'!$J$94 -> 19501752 | F85: =IF(ISNUMBER(D85),D85/E85,"n/a") -> 1.5 | G85: =Assumptions!$E$29 -> 0 | H85: {=INDEX(Assumptions!$B$34:$B$40,MATCH($C85,Assumptions!$A$34:$A$40,0))} -> 0.03 | I85: =IF(ISNUMBER($D85),$D85*(1+$G85)^(I$7-$I$7)*IF($F85>1,(1+($F85-1)*(1-$H85)^(I$7-$I$7))/$F85,1),"n/a") -> 29252627 | J85: =IF(ISNUMBER($D85),$D85*(1+$G85)^(J$7-$I$7)*IF($F85>1,(1+($F85-1)*(1-$H85)^(J$7-$I$7))/$F85,1),"n/a") -> 28960101 | K85: =IF(ISNUMBER($D85),$D85*(1+$G85)^(K$7-$I$7)*IF($F85>1,(1+($F85-1)*(1-$H85)^(K$7-$I$7))/$F85,1),"n/a") -> 28676351 | L85: =IF(ISNUMBER($D85),$D85*(1+$G85)^(L$7-$I$7)*IF($F85>1,(1+($F85-1)*(1-$H85)^(L$7-$I$7))/$F85,1),"n/a") -> 28401113 | M85: =IF(ISNUMBER($D85),$D85*(1+$G85)^(M$7-$I$7)*IF($F85>1,(1+($F85-1)*(1-$H85)^(M$7-$I$7))/$F85,1),"n/a") -> 28134132 | N85: =IF(ISNUMBER($D85),$D85*(1+$G85)^(N$7-$I$7)*IF($F85>1,(1+($F85-1)*(1-$H85)^(N$7-$I$7))/$F85,1),"n/a") -> 27875160 | O85: =IF(ISNUMBER($D85),$D85*(1+$G85)^(O$7-$I$7)*IF($F85>1,(1+($F85-1)*(1-$H85)^(O$7-$I$7))/$F85,1),"n/a") -> 27623958 | P85: =IF(ISNUMBER($D85),$D85*(1+$G85)^(P$7-$I$7)*IF($F85>1,(1+($F85-1)*(1-$H85)^(P$7-$I$7))/$F85,1),"n/a") -> 27380292 | ... AK85: =IF(ISNUMBER($D85),$D85*(1+$G85)^(AK$7-$I$7)*IF($F85>1,(1+($F85-1)*(1-$H85)^(AK$7-$I$7))/$F85,1),"n/a") -> 23657528
A86: 12 | B86: Rail - Freight | C86: NGV | D86: ='Fuel Price'!D94 -> 23402102 | E86: ='Fuel Price'!$J$94 -> 19501752 | F86: =IF(ISNUMBER(D86),D86/E86,"n/a") -> 1.2 | G86: =Assumptions!$E$29 -> 0 | H86: {=INDEX(Assumptions!$B$34:$B$40,MATCH($C86,Assumptions!$A$34:$A$40,0))} -> 0.01 | I86: =IF(ISNUMBER($D86),$D86*(1+$G86)^(I$7-$I$7)*IF($F86>1,(1+($F86-1)*(1-$H86)^(I$7-$I$7))/$F86,1),"n/a") -> 23402102 | J86: =IF(ISNUMBER($D86),$D86*(1+$G86)^(J$7-$I$7)*IF($F86>1,(1+($F86-1)*(1-$H86)^(J$7-$I$7))/$F86,1),"n/a") -> 23363098 | K86: =IF(ISNUMBER($D86),$D86*(1+$G86)^(K$7-$I$7)*IF($F86>1,(1+($F86-1)*(1-$H86)^(K$7-$I$7))/$F86,1),"n/a") -> 23324485 | L86: =IF(ISNUMBER($D86),$D86*(1+$G86)^(L$7-$I$7)*IF($F86>1,(1+($F86-1)*(1-$H86)^(L$7-$I$7))/$F86,1),"n/a") -> 23286258 | M86: =IF(ISNUMBER($D86),$D86*(1+$G86)^(M$7-$I$7)*IF($F86>1,(1+($F86-1)*(1-$H86)^(M$7-$I$7))/$F86,1),"n/a") -> 23248413 | N86: =IF(ISNUMBER($D86),$D86*(1+$G86)^(N$7-$I$7)*IF($F86>1,(1+($F86-1)*(1-$H86)^(N$7-$I$7))/$F86,1),"n/a") -> 23210946 | O86: =IF(ISNUMBER($D86),$D86*(1+$G86)^(O$7-$I$7)*IF($F86>1,(1+($F86-1)*(1-$H86)^(O$7-$I$7))/$F86,1),"n/a") -> 23173854 | P86: =IF(ISNUMBER($D86),$D86*(1+$G86)^(P$7-$I$7)*IF($F86>1,(1+($F86-1)*(1-$H86)^(P$7-$I$7))/$F86,1),"n/a") -> 23137133 | ... AK86: =IF(ISNUMBER($D86),$D86*(1+$G86)^(AK$7-$I$7)*IF($F86>1,(1+($F86-1)*(1-$H86)^(AK$7-$I$7))/$F86,1),"n/a") -> 22445421
A87: 12 | B87: Rail - Freight | C87: Gasoline | D87: ='Fuel Price'!E94 -> n/a | E87: ='Fuel Price'!$J$94 -> 19501752 | F87: =IF(ISNUMBER(D87),D87/E87,"n/a") -> n/a | G87: =Assumptions!$E$29 -> 0 | H87: {=INDEX(Assumptions!$B$34:$B$40,MATCH($C87,Assumptions!$A$34:$A$40,0))} -> 0 | I87: =IF(ISNUMBER($D87),$D87*(1+$G87)^(I$7-$I$7)*IF($F87>1,(1+($F87-1)*(1-$H87)^(I$7-$I$7))/$F87,1),"n/a") -> n/a | J87: =IF(ISNUMBER($D87),$D87*(1+$G87)^(J$7-$I$7)*IF($F87>1,(1+($F87-1)*(1-$H87)^(J$7-$I$7))/$F87,1),"n/a") -> n/a | K87: =IF(ISNUMBER($D87),$D87*(1+$G87)^(K$7-$I$7)*IF($F87>1,(1+($F87-1)*(1-$H87)^(K$7-$I$7))/$F87,1),"n/a") -> n/a | L87: =IF(ISNUMBER($D87),$D87*(1+$G87)^(L$7-$I$7)*IF($F87>1,(1+($F87-1)*(1-$H87)^(L$7-$I$7))/$F87,1),"n/a") -> n/a | M87: =IF(ISNUMBER($D87),$D87*(1+$G87)^(M$7-$I$7)*IF($F87>1,(1+($F87-1)*(1-$H87)^(M$7-$I$7))/$F87,1),"n/a") -> n/a | N87: =IF(ISNUMBER($D87),$D87*(1+$G87)^(N$7-$I$7)*IF($F87>1,(1+($F87-1)*(1-$H87)^(N$7-$I$7))/$F87,1),"n/a") -> n/a | O87: =IF(ISNUMBER($D87),$D87*(1+$G87)^(O$7-$I$7)*IF($F87>1,(1+($F87-1)*(1-$H87)^(O$7-$I$7))/$F87,1),"n/a") -> n/a | P87: =IF(ISNUMBER($D87),$D87*(1+$G87)^(P$7-$I$7)*IF($F87>1,(1+($F87-1)*(1-$H87)^(P$7-$I$7))/$F87,1),"n/a") -> n/a | ... AK87: =IF(ISNUMBER($D87),$D87*(1+$G87)^(AK$7-$I$7)*IF($F87>1,(1+($F87-1)*(1-$H87)^(AK$7-$I$7))/$F87,1),"n/a") -> n/a
A88: 12 | B88: Rail - Freight | C88: Diesel | D88: ='Fuel Price'!F94 -> 19501752 | E88: ='Fuel Price'!$J$94 -> 19501752 | F88: =IF(ISNUMBER(D88),D88/E88,"n/a") -> 1 | G88: =Assumptions!$E$29 -> 0 | H88: {=INDEX(Assumptions!$B$34:$B$40,MATCH($C88,Assumptions!$A$34:$A$40,0))} -> 0 | I88: =IF(ISNUMBER($D88),$D88*(1+$G88)^(I$7-$I$7)*IF($F88>1,(1+($F88-1)*(1-$H88)^(I$7-$I$7))/$F88,1),"n/a") -> 19501752 | J88: =IF(ISNUMBER($D88),$D88*(1+$G88)^(J$7-$I$7)*IF($F88>1,(1+($F88-1)*(1-$H88)^(J$7-$I$7))/$F88,1),"n/a") -> 19501752 | K88: =IF(ISNUMBER($D88),$D88*(1+$G88)^(K$7-$I$7)*IF($F88>1,(1+($F88-1)*(1-$H88)^(K$7-$I$7))/$F88,1),"n/a") -> 19501752 | L88: =IF(ISNUMBER($D88),$D88*(1+$G88)^(L$7-$I$7)*IF($F88>1,(1+($F88-1)*(1-$H88)^(L$7-$I$7))/$F88,1),"n/a") -> 19501752 | M88: =IF(ISNUMBER($D88),$D88*(1+$G88)^(M$7-$I$7)*IF($F88>1,(1+($F88-1)*(1-$H88)^(M$7-$I$7))/$F88,1),"n/a") -> 19501752 | N88: =IF(ISNUMBER($D88),$D88*(1+$G88)^(N$7-$I$7)*IF($F88>1,(1+($F88-1)*(1-$H88)^(N$7-$I$7))/$F88,1),"n/a") -> 19501752 | O88: =IF(ISNUMBER($D88),$D88*(1+$G88)^(O$7-$I$7)*IF($F88>1,(1+($F88-1)*(1-$H88)^(O$7-$I$7))/$F88,1),"n/a") -> 19501752 | P88: =IF(ISNUMBER($D88),$D88*(1+$G88)^(P$7-$I$7)*IF($F88>1,(1+($F88-1)*(1-$H88)^(P$7-$I$7))/$F88,1),"n/a") -> 19501752 | ... AK88: =IF(ISNUMBER($D88),$D88*(1+$G88)^(AK$7-$I$7)*IF($F88>1,(1+($F88-1)*(1-$H88)^(AK$7-$I$7))/$F88,1),"n/a") -> 19501752
A89: 12 | B89: Rail - Freight | C89: PHEV | D89: ='Fuel Price'!G94 -> 23402102 | E89: ='Fuel Price'!$J$94 -> 19501752 | F89: =IF(ISNUMBER(D89),D89/E89,"n/a") -> 1.2 | G89: =Assumptions!$E$29 -> 0 | H89: {=INDEX(Assumptions!$B$34:$B$40,MATCH($C89,Assumptions!$A$34:$A$40,0))} -> 0.02 | I89: =IF(ISNUMBER($D89),$D89*(1+$G89)^(I$7-$I$7)*IF($F89>1,(1+($F89-1)*(1-$H89)^(I$7-$I$7))/$F89,1),"n/a") -> 23402102 | J89: =IF(ISNUMBER($D89),$D89*(1+$G89)^(J$7-$I$7)*IF($F89>1,(1+($F89-1)*(1-$H89)^(J$7-$I$7))/$F89,1),"n/a") -> 23324095 | K89: =IF(ISNUMBER($D89),$D89*(1+$G89)^(K$7-$I$7)*IF($F89>1,(1+($F89-1)*(1-$H89)^(K$7-$I$7))/$F89,1),"n/a") -> 23247648 | L89: =IF(ISNUMBER($D89),$D89*(1+$G89)^(L$7-$I$7)*IF($F89>1,(1+($F89-1)*(1-$H89)^(L$7-$I$7))/$F89,1),"n/a") -> 23172730 | M89: =IF(ISNUMBER($D89),$D89*(1+$G89)^(M$7-$I$7)*IF($F89>1,(1+($F89-1)*(1-$H89)^(M$7-$I$7))/$F89,1),"n/a") -> 23099311 | N89: =IF(ISNUMBER($D89),$D89*(1+$G89)^(N$7-$I$7)*IF($F89>1,(1+($F89-1)*(1-$H89)^(N$7-$I$7))/$F89,1),"n/a") -> 23027359 | O89: =IF(ISNUMBER($D89),$D89*(1+$G89)^(O$7-$I$7)*IF($F89>1,(1+($F89-1)*(1-$H89)^(O$7-$I$7))/$F89,1),"n/a") -> 22956847 | P89: =IF(ISNUMBER($D89),$D89*(1+$G89)^(P$7-$I$7)*IF($F89>1,(1+($F89-1)*(1-$H89)^(P$7-$I$7))/$F89,1),"n/a") -> 22887745 | ... AK89: =IF(ISNUMBER($D89),$D89*(1+$G89)^(AK$7-$I$7)*IF($F89>1,(1+($F89-1)*(1-$H89)^(AK$7-$I$7))/$F89,1),"n/a") -> 21717058
A90: 12 | B90: Rail - Freight | C90: LPG | D90: ='Fuel Price'!H94 -> n/a | E90: ='Fuel Price'!$J$94 -> 19501752 | F90: =IF(ISNUMBER(D90),D90/E90,"n/a") -> n/a | G90: =Assumptions!$E$29 -> 0 | H90: {=INDEX(Assumptions!$B$34:$B$40,MATCH($C90,Assumptions!$A$34:$A$40,0))} -> 0.01 | I90: =IF(ISNUMBER($D90),$D90*(1+$G90)^(I$7-$I$7)*IF($F90>1,(1+($F90-1)*(1-$H90)^(I$7-$I$7))/$F90,1),"n/a") -> n/a | J90: =IF(ISNUMBER($D90),$D90*(1+$G90)^(J$7-$I$7)*IF($F90>1,(1+($F90-1)*(1-$H90)^(J$7-$I$7))/$F90,1),"n/a") -> n/a | K90: =IF(ISNUMBER($D90),$D90*(1+$G90)^(K$7-$I$7)*IF($F90>1,(1+($F90-1)*(1-$H90)^(K$7-$I$7))/$F90,1),"n/a") -> n/a | L90: =IF(ISNUMBER($D90),$D90*(1+$G90)^(L$7-$I$7)*IF($F90>1,(1+($F90-1)*(1-$H90)^(L$7-$I$7))/$F90,1),"n/a") -> n/a | M90: =IF(ISNUMBER($D90),$D90*(1+$G90)^(M$7-$I$7)*IF($F90>1,(1+($F90-1)*(1-$H90)^(M$7-$I$7))/$F90,1),"n/a") -> n/a | N90: =IF(ISNUMBER($D90),$D90*(1+$G90)^(N$7-$I$7)*IF($F90>1,(1+($F90-1)*(1-$H90)^(N$7-$I$7))/$F90,1),"n/a") -> n/a | O90: =IF(ISNUMBER($D90),$D90*(1+$G90)^(O$7-$I$7)*IF($F90>1,(1+($F90-1)*(1-$H90)^(O$7-$I$7))/$F90,1),"n/a") -> n/a | P90: =IF(ISNUMBER($D90),$D90*(1+$G90)^(P$7-$I$7)*IF($F90>1,(1+($F90-1)*(1-$H90)^(P$7-$I$7))/$F90,1),"n/a") -> n/a | ... AK90: =IF(ISNUMBER($D90),$D90*(1+$G90)^(AK$7-$I$7)*IF($F90>1,(1+($F90-1)*(1-$H90)^(AK$7-$I$7))/$F90,1),"n/a") -> n/a
A91: 12 | B91: Rail - Freight | C91: Hydrogen | D91: ='Fuel Price'!I94 -> 39003503 | E91: ='Fuel Price'!$J$94 -> 19501752 | F91: =IF(ISNUMBER(D91),D91/E91,"n/a") -> 2 | G91: =Assumptions!$E$29 -> 0 | H91: {=INDEX(Assumptions!$B$34:$B$40,MATCH($C91,Assumptions!$A$34:$A$40,0))} -> 0.03 | I91: =IF(ISNUMBER($D91),$D91*(1+$G91)^(I$7-$I$7)*IF($F91>1,(1+($F91-1)*(1-$H91)^(I$7-$I$7))/$F91,1),"n/a") -> 39003503 | J91: =IF(ISNUMBER($D91),$D91*(1+$G91)^(J$7-$I$7)*IF($F91>1,(1+($F91-1)*(1-$H91)^(J$7-$I$7))/$F91,1),"n/a") -> 38418451 | K91: =IF(ISNUMBER($D91),$D91*(1+$G91)^(K$7-$I$7)*IF($F91>1,(1+($F91-1)*(1-$H91)^(K$7-$I$7))/$F91,1),"n/a") -> 37850950 | L91: =IF(ISNUMBER($D91),$D91*(1+$G91)^(L$7-$I$7)*IF($F91>1,(1+($F91-1)*(1-$H91)^(L$7-$I$7))/$F91,1),"n/a") -> 37300474 | M91: =IF(ISNUMBER($D91),$D91*(1+$G91)^(M$7-$I$7)*IF($F91>1,(1+($F91-1)*(1-$H91)^(M$7-$I$7))/$F91,1),"n/a") -> 36766512 | N91: =IF(ISNUMBER($D91),$D91*(1+$G91)^(N$7-$I$7)*IF($F91>1,(1+($F91-1)*(1-$H91)^(N$7-$I$7))/$F91,1),"n/a") -> 36248569 | O91: =IF(ISNUMBER($D91),$D91*(1+$G91)^(O$7-$I$7)*IF($F91>1,(1+($F91-1)*(1-$H91)^(O$7-$I$7))/$F91,1),"n/a") -> 35746165 | P91: =IF(ISNUMBER($D91),$D91*(1+$G91)^(P$7-$I$7)*IF($F91>1,(1+($F91-1)*(1-$H91)^(P$7-$I$7))/$F91,1),"n/a") -> 35258832 | ... AK91: =IF(ISNUMBER($D91),$D91*(1+$G91)^(AK$7-$I$7)*IF($F91>1,(1+($F91-1)*(1-$H91)^(AK$7-$I$7))/$F91,1),"n/a") -> 27813305
A95: B. Nominal price by fuel (R$)
A96: ID | B96: Vehicle type | C96: Fuel | D96: Price 2022 (R$) | E96: Reference price (R$) | F96: Ratio to reference | G96: Real growth (%/yr) | H96: Convergence (%/yr) | I96: =I$7 -> 2022 | J96: =J$7 -> 2023 | K96: =K$7 -> 2024 | L96: =L$7 -> 2025 | M96: =M$7 -> 2026 | N96: =N$7 -> 2027 | O96: =O$7 -> 2028 | P96: =P$7 -> 2029 | ... AK96: =AK$7 -> 2050
A97: 1 | B97: Road - Passenger LDV | C97: BEV | I97: {=IF(ISNUMBER(I8),I8*INDEX(Forecast!$E$7:$AG$7,MATCH(I$96,Forecast!$E$5:$AG$5,0)),"n/a")} -> 147487.33 | J97: {=IF(ISNUMBER(J8),J8*INDEX(Forecast!$E$7:$AG$7,MATCH(J$96,Forecast!$E$5:$AG$5,0)),"n/a")} -> 154301.25 | K97: {=IF(ISNUMBER(K8),K8*INDEX(Forecast!$E$7:$AG$7,MATCH(K$96,Forecast!$E$5:$AG$5,0)),"n/a")} -> 161754 | L97: {=IF(ISNUMBER(L8),L8*INDEX(Forecast!$E$7:$AG$7,MATCH(L$96,Forecast!$E$5:$AG$5,0)),"n/a")} -> 168644.72 | M97: {=IF(ISNUMBER(M8),M8*INDEX(Forecast!$E$7:$AG$7,MATCH(M$96,Forecast!$E$5:$AG$5,0)),"n/a")} -> 175761.53 | N97: {=IF(ISNUMBER(N8),N8*INDEX(Forecast!$E$7:$AG$7,MATCH(N$96,Forecast!$E$5:$AG$5,0)),"n/a")} -> 181034.37 | O97: {=IF(ISNUMBER(O8),O8*INDEX(Forecast!$E$7:$AG$7,MATCH(O$96,Forecast!$E$5:$AG$5,0)),"n/a")} -> 186465.4 | P97: {=IF(ISNUMBER(P8),P8*INDEX(Forecast!$E$7:$AG$7,MATCH(P$96,Forecast!$E$5:$AG$5,0)),"n/a")} -> 192059.37 | ... AK97: {=IF(ISNUMBER(AK8),AK8*INDEX(Forecast!$E$7:$AG$7,MATCH(AK$96,Forecast!$E$5:$AG$5,0)),"n/a")} -> 357287
A98: 1 | B98: Road - Passenger LDV | C98: NGV | I98: {=IF(ISNUMBER(I9),I9*INDEX(Forecast!$E$7:$AG$7,MATCH(I$96,Forecast!$E$5:$AG$5,0)),"n/a")} -> 427580.76 | J98: {=IF(ISNUMBER(J9),J9*INDEX(Forecast!$E$7:$AG$7,MATCH(J$96,Forecast!$E$5:$AG$5,0)),"n/a")} -> 447282.68 | K98: {=IF(ISNUMBER(K9),K9*INDEX(Forecast!$E$7:$AG$7,MATCH(K$96,Forecast!$E$5:$AG$5,0)),"n/a")} -> 468832.14 | L98: {=IF(ISNUMBER(L9),L9*INDEX(Forecast!$E$7:$AG$7,MATCH(L$96,Forecast!$E$5:$AG$5,0)),"n/a")} -> 488748.36 | M98: {=IF(ISNUMBER(M9),M9*INDEX(Forecast!$E$7:$AG$7,MATCH(M$96,Forecast!$E$5:$AG$5,0)),"n/a")} -> 509315.72 | N98: {=IF(ISNUMBER(N9),N9*INDEX(Forecast!$E$7:$AG$7,MATCH(N$96,Forecast!$E$5:$AG$5,0)),"n/a")} -> 524536.24 | O98: {=IF(ISNUMBER(O9),O9*INDEX(Forecast!$E$7:$AG$7,MATCH(O$96,Forecast!$E$5:$AG$5,0)),"n/a")} -> 540212.21 | P98: {=IF(ISNUMBER(P9),P9*INDEX(Forecast!$E$7:$AG$7,MATCH(P$96,Forecast!$E$5:$AG$5,0)),"n/a")} -> 556357.28 | ... AK98: {=IF(ISNUMBER(AK9),AK9*INDEX(Forecast!$E$7:$AG$7,MATCH(AK$96,Forecast!$E$5:$AG$5,0)),"n/a")} -> 1032840.3
A99: 1 | B99: Road - Passenger LDV | C99: Gasoline | I99: {=IF(ISNUMBER(I10),I10*INDEX(Forecast!$E$7:$AG$7,MATCH(I$96,Forecast!$E$5:$AG$5,0)),"n/a")} -> 422580.76 | J99: {=IF(ISNUMBER(J10),J10*INDEX(Forecast!$E$7:$AG$7,MATCH(J$96,Forecast!$E$5:$AG$5,0)),"n/a")} -> 442103.99 | K99: {=IF(ISNUMBER(K10),K10*INDEX(Forecast!$E$7:$AG$7,MATCH(K$96,Forecast!$E$5:$AG$5,0)),"n/a")} -> 463457.61 | L99: {=IF(ISNUMBER(L10),L10*INDEX(Forecast!$E$7:$AG$7,MATCH(L$96,Forecast!$E$5:$AG$5,0)),"n/a")} -> 483200.91 | M99: {=IF(ISNUMBER(M10),M10*INDEX(Forecast!$E$7:$AG$7,MATCH(M$96,Forecast!$E$5:$AG$5,0)),"n/a")} -> 503591.98 | N99: {=IF(ISNUMBER(N10),N10*INDEX(Forecast!$E$7:$AG$7,MATCH(N$96,Forecast!$E$5:$AG$5,0)),"n/a")} -> 518699.74 | O99: {=IF(ISNUMBER(O10),O10*INDEX(Forecast!$E$7:$AG$7,MATCH(O$96,Forecast!$E$5:$AG$5,0)),"n/a")} -> 534260.74 | P99: {=IF(ISNUMBER(P10),P10*INDEX(Forecast!$E$7:$AG$7,MATCH(P$96,Forecast!$E$5:$AG$5,0)),"n/a")} -> 550288.56 | ... AK99: {=IF(ISNUMBER(AK10),AK10*INDEX(Forecast!$E$7:$AG$7,MATCH(AK$96,Forecast!$E$5:$AG$5,0)),"n/a")} -> 1023698.8
A100: 1 | B100: Road - Passenger LDV | C100: Diesel | I100: {=IF(ISNUMBER(I11),I11*INDEX(Forecast!$E$7:$AG$7,MATCH(I$96,Forecast!$E$5:$AG$5,0)),"n/a")} -> 384177.66 | J100: {=IF(ISNUMBER(J11),J11*INDEX(Forecast!$E$7:$AG$7,MATCH(J$96,Forecast!$E$5:$AG$5,0)),"n/a")} -> 401926.66 | K100: {=IF(ISNUMBER(K11),K11*INDEX(Forecast!$E$7:$AG$7,MATCH(K$96,Forecast!$E$5:$AG$5,0)),"n/a")} -> 421339.72 | L100: {=IF(ISNUMBER(L11),L11*INDEX(Forecast!$E$7:$AG$7,MATCH(L$96,Forecast!$E$5:$AG$5,0)),"n/a")} -> 439288.79 | M100: {=IF(ISNUMBER(M11),M11*INDEX(Forecast!$E$7:$AG$7,MATCH(M$96,Forecast!$E$5:$AG$5,0)),"n/a")} -> 457826.78 | N100: {=IF(ISNUMBER(N11),N11*INDEX(Forecast!$E$7:$AG$7,MATCH(N$96,Forecast!$E$5:$AG$5,0)),"n/a")} -> 471561.58 | O100: {=IF(ISNUMBER(O11),O11*INDEX(Forecast!$E$7:$AG$7,MATCH(O$96,Forecast!$E$5:$AG$5,0)),"n/a")} -> 485708.43 | P100: {=IF(ISNUMBER(P11),P11*INDEX(Forecast!$E$7:$AG$7,MATCH(P$96,Forecast!$E$5:$AG$5,0)),"n/a")} -> 500279.68 | ... AK100: {=IF(ISNUMBER(AK11),AK11*INDEX(Forecast!$E$7:$AG$7,MATCH(AK$96,Forecast!$E$5:$AG$5,0)),"n/a")} -> 930667.58
A101: 1 | B101: Road - Passenger LDV | C101: PHEV | I101: {=IF(ISNUMBER(I12),I12*INDEX(Forecast!$E$7:$AG$7,MATCH(I$96,Forecast!$E$5:$AG$5,0)),"n/a")} -> 602925.26 | J101: {=IF(ISNUMBER(J12),J12*INDEX(Forecast!$E$7:$AG$7,MATCH(J$96,Forecast!$E$5:$AG$5,0)),"n/a")} -> 627006.88 | K101: {=IF(ISNUMBER(K12),K12*INDEX(Forecast!$E$7:$AG$7,MATCH(K$96,Forecast!$E$5:$AG$5,0)),"n/a")} -> 653414.63 | L101: {=IF(ISNUMBER(L12),L12*INDEX(Forecast!$E$7:$AG$7,MATCH(L$96,Forecast!$E$5:$AG$5,0)),"n/a")} -> 677289.11 | M101: {=IF(ISNUMBER(M12),M12*INDEX(Forecast!$E$7:$AG$7,MATCH(M$96,Forecast!$E$5:$AG$5,0)),"n/a")} -> 701825.14 | N101: {=IF(ISNUMBER(N12),N12*INDEX(Forecast!$E$7:$AG$7,MATCH(N$96,Forecast!$E$5:$AG$5,0)),"n/a")} -> 718796.29 | O101: {=IF(ISNUMBER(O12),O12*INDEX(Forecast!$E$7:$AG$7,MATCH(O$96,Forecast!$E$5:$AG$5,0)),"n/a")} -> 736238.19 | P101: {=IF(ISNUMBER(P12),P12*INDEX(Forecast!$E$7:$AG$7,MATCH(P$96,Forecast!$E$5:$AG$5,0)),"n/a")} -> 754164.6 | ... AK101: {=IF(ISNUMBER(AK12),AK12*INDEX(Forecast!$E$7:$AG$7,MATCH(AK$96,Forecast!$E$5:$AG$5,0)),"n/a")} -> 1271838.1
A102: 1 | B102: Road - Passenger LDV | C102: LPG | I102: {=IF(ISNUMBER(I13),I13*INDEX(Forecast!$E$7:$AG$7,MATCH(I$96,Forecast!$E$5:$AG$5,0)),"n/a")} -> n/a | J102: {=IF(ISNUMBER(J13),J13*INDEX(Forecast!$E$7:$AG$7,MATCH(J$96,Forecast!$E$5:$AG$5,0)),"n/a")} -> n/a | K102: {=IF(ISNUMBER(K13),K13*INDEX(Forecast!$E$7:$AG$7,MATCH(K$96,Forecast!$E$5:$AG$5,0)),"n/a")} -> n/a | L102: {=IF(ISNUMBER(L13),L13*INDEX(Forecast!$E$7:$AG$7,MATCH(L$96,Forecast!$E$5:$AG$5,0)),"n/a")} -> n/a | M102: {=IF(ISNUMBER(M13),M13*INDEX(Forecast!$E$7:$AG$7,MATCH(M$96,Forecast!$E$5:$AG$5,0)),"n/a")} -> n/a | N102: {=IF(ISNUMBER(N13),N13*INDEX(Forecast!$E$7:$AG$7,MATCH(N$96,Forecast!$E$5:$AG$5,0)),"n/a")} -> n/a | O102: {=IF(ISNUMBER(O13),O13*INDEX(Forecast!$E$7:$AG$7,MATCH(O$96,Forecast!$E$5:$AG$5,0)),"n/a")} -> n/a | P102: {=IF(ISNUMBER(P13),P13*INDEX(Forecast!$E$7:$AG$7,MATCH(P$96,Forecast!$E$5:$AG$5,0)),"n/a")} -> n/a | ... AK102: {=IF(ISNUMBER(AK13),AK13*INDEX(Forecast!$E$7:$AG$7,MATCH(AK$96,Forecast!$E$5:$AG$5,0)),"n/a")} -> n/a
A103: 1 | B103: Road - Passenger LDV | C103: Hydrogen | I103: {=IF(ISNUMBER(I14),I14*INDEX(Forecast!$E$7:$AG$7,MATCH(I$96,Forecast!$E$5:$AG$5,0)),"n/a")} -> 869760.81 | J103: {=IF(ISNUMBER(J14),J14*INDEX(Forecast!$E$7:$AG$7,MATCH(J$96,Forecast!$E$5:$AG$5,0)),"n/a")} -> 895908.57 | K103: {=IF(ISNUMBER(K14),K14*INDEX(Forecast!$E$7:$AG$7,MATCH(K$96,Forecast!$E$5:$AG$5,0)),"n/a")} -> 924909.25 | L103: {=IF(ISNUMBER(L14),L14*INDEX(Forecast!$E$7:$AG$7,MATCH(L$96,Forecast!$E$5:$AG$5,0)),"n/a")} -> 949877.1 | M103: {=IF(ISNUMBER(M14),M14*INDEX(Forecast!$E$7:$AG$7,MATCH(M$96,Forecast!$E$5:$AG$5,0)),"n/a")} -> 975370.82 | N103: {=IF(ISNUMBER(N14),N14*INDEX(Forecast!$E$7:$AG$7,MATCH(N$96,Forecast!$E$5:$AG$5,0)),"n/a")} -> 990053.98 | O103: {=IF(ISNUMBER(O14),O14*INDEX(Forecast!$E$7:$AG$7,MATCH(O$96,Forecast!$E$5:$AG$5,0)),"n/a")} -> 1005190.7 | P103: {=IF(ISNUMBER(P14),P14*INDEX(Forecast!$E$7:$AG$7,MATCH(P$96,Forecast!$E$5:$AG$5,0)),"n/a")} -> 1020794.7 | ... AK103: {=IF(ISNUMBER(AK14),AK14*INDEX(Forecast!$E$7:$AG$7,MATCH(AK$96,Forecast!$E$5:$AG$5,0)),"n/a")} -> 1485392
A104: 2 | B104: Road - Passenger HDV | C104: BEV | I104: {=IF(ISNUMBER(I15),I15*INDEX(Forecast!$E$7:$AG$7,MATCH(I$96,Forecast!$E$5:$AG$5,0)),"n/a")} -> 896510.23 | J104: {=IF(ISNUMBER(J15),J15*INDEX(Forecast!$E$7:$AG$7,MATCH(J$96,Forecast!$E$5:$AG$5,0)),"n/a")} -> 919170.42 | K104: {=IF(ISNUMBER(K15),K15*INDEX(Forecast!$E$7:$AG$7,MATCH(K$96,Forecast!$E$5:$AG$5,0)),"n/a")} -> 944491.67 | L104: {=IF(ISNUMBER(L15),L15*INDEX(Forecast!$E$7:$AG$7,MATCH(L$96,Forecast!$E$5:$AG$5,0)),"n/a")} -> 965436.38 | M104: {=IF(ISNUMBER(M15),M15*INDEX(Forecast!$E$7:$AG$7,MATCH(M$96,Forecast!$E$5:$AG$5,0)),"n/a")} -> 986676.22 | N104: {=IF(ISNUMBER(N15),N15*INDEX(Forecast!$E$7:$AG$7,MATCH(N$96,Forecast!$E$5:$AG$5,0)),"n/a")} -> 996792.49 | O104: {=IF(ISNUMBER(O15),O15*INDEX(Forecast!$E$7:$AG$7,MATCH(O$96,Forecast!$E$5:$AG$5,0)),"n/a")} -> 1007229.8 | P104: {=IF(ISNUMBER(P15),P15*INDEX(Forecast!$E$7:$AG$7,MATCH(P$96,Forecast!$E$5:$AG$5,0)),"n/a")} -> 1017997.7 | ... AK104: {=IF(ISNUMBER(AK15),AK15*INDEX(Forecast!$E$7:$AG$7,MATCH(AK$96,Forecast!$E$5:$AG$5,0)),"n/a")} -> 1341000.7
A105: 2 | B105: Road - Passenger HDV | C105: NGV | I105: {=IF(ISNUMBER(I16),I16*INDEX(Forecast!$E$7:$AG$7,MATCH(I$96,Forecast!$E$5:$AG$5,0)),"n/a")} -> 358604.09 | J105: {=IF(ISNUMBER(J16),J16*INDEX(Forecast!$E$7:$AG$7,MATCH(J$96,Forecast!$E$5:$AG$5,0)),"n/a")} -> 374546.32 | K105: {=IF(ISNUMBER(K16),K16*INDEX(Forecast!$E$7:$AG$7,MATCH(K$96,Forecast!$E$5:$AG$5,0)),"n/a")} -> 391987.97 | L105: {=IF(ISNUMBER(L16),L16*INDEX(Forecast!$E$7:$AG$7,MATCH(L$96,Forecast!$E$5:$AG$5,0)),"n/a")} -> 408016.85 | M105: {=IF(ISNUMBER(M16),M16*INDEX(Forecast!$E$7:$AG$7,MATCH(M$96,Forecast!$E$5:$AG$5,0)),"n/a")} -> 424544.06 | N105: {=IF(ISNUMBER(N16),N16*INDEX(Forecast!$E$7:$AG$7,MATCH(N$96,Forecast!$E$5:$AG$5,0)),"n/a")} -> 436575.67 | O105: {=IF(ISNUMBER(O16),O16*INDEX(Forecast!$E$7:$AG$7,MATCH(O$96,Forecast!$E$5:$AG$5,0)),"n/a")} -> 448954.35 | P105: {=IF(ISNUMBER(P16),P16*INDEX(Forecast!$E$7:$AG$7,MATCH(P$96,Forecast!$E$5:$AG$5,0)),"n/a")} -> 461690.23 | ... AK105: {=IF(ISNUMBER(AK16),AK16*INDEX(Forecast!$E$7:$AG$7,MATCH(AK$96,Forecast!$E$5:$AG$5,0)),"n/a")} -> 833202.6
...

Sheet Forecast
A1: Forecast of average new-vehicle prices, 2022-2050
A2: Real price(t) = Real price(t-1) x (1 + real growth of the selected scenario); Nominal = Real x inflation index; US$ = Real R$ / 2022 average PTAX (constant-price US$).
A3: Scenario: | B3: =Assumptions!B7 -> Base | C3: =Assumptions!B10&" used for road base prices" -> Mean used for road base prices
A5: ID | B5: Mode | C5: Vehicle type | D5: Real growth (%/yr) | E5: =Assumptions!$B$4 -> 2022 | F5: =E5+1 -> 2023 | G5: =F5+1 -> 2024 | H5: =G5+1 -> 2025 | I5: =H5+1 -> 2026 | J5: =I5+1 -> 2027 | K5: =J5+1 -> 2028 | L5: =K5+1 -> 2029 | M5: =L5+1 -> 2030 | ... AG5: =AF5+1 -> 2050
C6: Inflation applied (IPCA, % per year) | F6: {=IF(F$5<=Assumptions!$B$13,INDEX(Macro!$O$6:$O$17,MATCH(F$5,Macro!$K$6:$K$17,0)),Assumptions!$B$8)} -> 0.0462 | G6: {=IF(G$5<=Assumptions!$B$13,INDEX(Macro!$O$6:$O$17,MATCH(G$5,Macro!$K$6:$K$17,0)),Assumptions!$B$8)} -> 0.0483 | H6: {=IF(H$5<=Assumptions!$B$13,INDEX(Macro!$O$6:$O$17,MATCH(H$5,Macro!$K$6:$K$17,0)),Assumptions!$B$8)} -> 0.0426 | I6: {=IF(I$5<=Assumptions!$B$13,INDEX(Macro!$O$6:$O$17,MATCH(I$5,Macro!$K$6:$K$17,0)),Assumptions!$B$8)} -> 0.0422 | J6: {=IF(J$5<=Assumptions!$B$13,INDEX(Macro!$O$6:$O$17,MATCH(J$5,Macro!$K$6:$K$17,0)),Assumptions!$B$8)} -> 0.03 | K6: {=IF(K$5<=Assumptions!$B$13,INDEX(Macro!$O$6:$O$17,MATCH(K$5,Macro!$K$6:$K$17,0)),Assumptions!$B$8)} -> 0.03 | L6: {=IF(L$5<=Assumptions!$B$13,INDEX(Macro!$O$6:$O$17,MATCH(L$5,Macro!$K$6:$K$17,0)),Assumptions!$B$8)} -> 0.03 | M6: {=IF(M$5<=Assumptions!$B$13,INDEX(Macro!$O$6:$O$17,MATCH(M$5,Macro!$K$6:$K$17,0)),Assumptions!$B$8)} -> 0.03 | ... AG6: {=IF(AG$5<=Assumptions!$B$13,INDEX(Macro!$O$6:$O$17,MATCH(AG$5,Macro!$K$6:$K$17,0)),Assumptions!$B$8)} -> 0.03
C7: Price index (base year = 1.000) | E7: 1 | F7: =E7*(1+F6) -> 1.0462 | G7: =F7*(1+G6) -> 1.0967315 | H7: =G7*(1+H6) -> 1.1434522 | I7: =H7*(1+I6) -> 1.1917059 | J7: =I7*(1+J6) -> 1.2274571 | K7: =J7*(1+K6) -> 1.2642808 | L7: =K7*(1+L6) -> 1.3022092 | M7: =L7*(1+M6) -> 1.3412755 | ... AG7: =AF7*(1+AG6) -> 2.4224927
A9: A. Constant 2022 R$ (real prices) | D9: R$ per vehicle
A10: 1 | B10: Road | C10: Road - Passenger LDV | D10: =Assumptions!$E$18 -> 0 | E10: =CHOOSE(Assumptions!$B$9,'Road Avg'!$D$6,'Road Avg'!$E$6) -> 427911.79 | F10: =E10*(1+$D10) -> 427911.79 | G10: =F10*(1+$D10) -> 427911.79 | H10: =G10*(1+$D10) -> 427911.79 | I10: =H10*(1+$D10) -> 427911.79 | J10: =I10*(1+$D10) -> 427911.79 | K10: =J10*(1+$D10) -> 427911.79 | L10: =K10*(1+$D10) -> 427911.79 | M10: =L10*(1+$D10) -> 427911.79 | ... AG10: =AF10*(1+$D10) -> 427911.79
A11: 2 | B11: Road | C11: Road - Passenger HDV | D11: =Assumptions!$E$19 -> 0 | E11: =CHOOSE(Assumptions!$B$9,'Road Avg'!$D$7,'Road Avg'!$E$7) -> 298836.74 | F11: =E11*(1+$D11) -> 298836.74 | G11: =F11*(1+$D11) -> 298836.74 | H11: =G11*(1+$D11) -> 298836.74 | I11: =H11*(1+$D11) -> 298836.74 | J11: =I11*(1+$D11) -> 298836.74 | K11: =J11*(1+$D11) -> 298836.74 | L11: =K11*(1+$D11) -> 298836.74 | M11: =L11*(1+$D11) -> 298836.74 | ... AG11: =AF11*(1+$D11) -> 298836.74
A12: 3 | B12: Road | C12: Road - Freight LDV | D12: =Assumptions!$E$20 -> 0 | E12: =CHOOSE(Assumptions!$B$9,'Road Avg'!$D$8,'Road Avg'!$E$8) -> 212826.35 | F12: =E12*(1+$D12) -> 212826.35 | G12: =F12*(1+$D12) -> 212826.35 | H12: =G12*(1+$D12) -> 212826.35 | I12: =H12*(1+$D12) -> 212826.35 | J12: =I12*(1+$D12) -> 212826.35 | K12: =J12*(1+$D12) -> 212826.35 | L12: =K12*(1+$D12) -> 212826.35 | M12: =L12*(1+$D12) -> 212826.35 | ... AG12: =AF12*(1+$D12) -> 212826.35
A13: 4 | B13: Road | C13: Road - Freight HDV | D13: =Assumptions!$E$21 -> 0 | E13: =CHOOSE(Assumptions!$B$9,'Road Avg'!$D$9,'Road Avg'!$E$9) -> 295851.61 | F13: =E13*(1+$D13) -> 295851.61 | G13: =F13*(1+$D13) -> 295851.61 | H13: =G13*(1+$D13) -> 295851.61 | I13: =H13*(1+$D13) -> 295851.61 | J13: =I13*(1+$D13) -> 295851.61 | K13: =J13*(1+$D13) -> 295851.61 | L13: =K13*(1+$D13) -> 295851.61 | M13: =L13*(1+$D13) -> 295851.61 | ... AG13: =AF13*(1+$D13) -> 295851.61
A14: 5 | B14: Motorbike | C14: Motorbike - Passenger | D14: =Assumptions!$E$22 -> 0 | E14: ='NonRoad Avg'!$D$6 -> 11475.445 | F14: =E14*(1+$D14) -> 11475.445 | G14: =F14*(1+$D14) -> 11475.445 | H14: =G14*(1+$D14) -> 11475.445 | I14: =H14*(1+$D14) -> 11475.445 | J14: =I14*(1+$D14) -> 11475.445 | K14: =J14*(1+$D14) -> 11475.445 | L14: =K14*(1+$D14) -> 11475.445 | M14: =L14*(1+$D14) -> 11475.445 | ... AG14: =AF14*(1+$D14) -> 11475.445
A15: 6 | B15: Motorbike | C15: Motorbike - Freight | D15: =Assumptions!$E$23 -> 0 | E15: ='NonRoad Avg'!$D$7 -> 12587.82 | F15: =E15*(1+$D15) -> 12587.82 | G15: =F15*(1+$D15) -> 12587.82 | H15: =G15*(1+$D15) -> 12587.82 | I15: =H15*(1+$D15) -> 12587.82 | J15: =I15*(1+$D15) -> 12587.82 | K15: =J15*(1+$D15) -> 12587.82 | L15: =K15*(1+$D15) -> 12587.82 | M15: =L15*(1+$D15) -> 12587.82 | ... AG15: =AF15*(1+$D15) -> 12587.82
A16: 7 | B16: Aircraft | C16: Aircraft - Passenger | D16: =Assumptions!$E$24 -> 0 | E16: ='NonRoad Avg'!$D$8 -> 2.2354408e+08 | F16: =E16*(1+$D16) -> 2.2354408e+08 | G16: =F16*(1+$D16) -> 2.2354408e+08 | H16: =G16*(1+$D16) -> 2.2354408e+08 | I16: =H16*(1+$D16) -> 2.2354408e+08 | J16: =I16*(1+$D16) -> 2.2354408e+08 | K16: =J16*(1+$D16) -> 2.2354408e+08 | L16: =K16*(1+$D16) -> 2.2354408e+08 | M16: =L16*(1+$D16) -> 2.2354408e+08 | ... AG16: =AF16*(1+$D16) -> 2.2354408e+08
A17: 8 | B17: Aircraft | C17: Aircraft - Freight | D17: =Assumptions!$E$25 -> 0 | E17: ='NonRoad Avg'!$D$9 -> 1.1367651e+08 | F17: =E17*(1+$D17) -> 1.1367651e+08 | G17: =F17*(1+$D17) -> 1.1367651e+08 | H17: =G17*(1+$D17) -> 1.1367651e+08 | I17: =H17*(1+$D17) -> 1.1367651e+08 | J17: =I17*(1+$D17) -> 1.1367651e+08 | K17: =J17*(1+$D17) -> 1.1367651e+08 | L17: =K17*(1+$D17) -> 1.1367651e+08 | M17: =L17*(1+$D17) -> 1.1367651e+08 | ... AG17: =AF17*(1+$D17) -> 1.1367651e+08
A18: 9 | B18: Ship | C18: Ship - Passenger | D18: =Assumptions!$E$26 -> 0 | E18: ='NonRoad Avg'!$D$10 -> 75018509 | F18: =E18*(1+$D18) -> 75018509 | G18: =F18*(1+$D18) -> 75018509 | H18: =G18*(1+$D18) -> 75018509 | I18: =H18*(1+$D18) -> 75018509 | J18: =I18*(1+$D18) -> 75018509 | K18: =J18*(1+$D18) -> 75018509 | L18: =K18*(1+$D18) -> 75018509 | M18: =L18*(1+$D18) -> 75018509 | ... AG18: =AF18*(1+$D18) -> 75018509
A19: 10 | B19: Ship | C19: Ship - Freight | D19: =Assumptions!$E$27 -> 0 | E19: ='NonRoad Avg'!$D$11 -> 4.0037794e+08 | F19: =E19*(1+$D19) -> 4.0037794e+08 | G19: =F19*(1+$D19) -> 4.0037794e+08 | H19: =G19*(1+$D19) -> 4.0037794e+08 | I19: =H19*(1+$D19) -> 4.0037794e+08 | J19: =I19*(1+$D19) -> 4.0037794e+08 | K19: =J19*(1+$D19) -> 4.0037794e+08 | L19: =K19*(1+$D19) -> 4.0037794e+08 | M19: =L19*(1+$D19) -> 4.0037794e+08 | ... AG19: =AF19*(1+$D19) -> 4.0037794e+08
A20: 11 | B20: Rail | C20: Rail - Passenger | D20: =Assumptions!$E$28 -> 0 | E20: ='NonRoad Avg'!$D$12 -> 64329558 | F20: =E20*(1+$D20) -> 64329558 | G20: =F20*(1+$D20) -> 64329558 | H20: =G20*(1+$D20) -> 64329558 | I20: =H20*(1+$D20) -> 64329558 | J20: =I20*(1+$D20) -> 64329558 | K20: =J20*(1+$D20) -> 64329558 | L20: =K20*(1+$D20) -> 64329558 | M20: =L20*(1+$D20) -> 64329558 | ... AG20: =AF20*(1+$D20) -> 64329558
A21: 12 | B21: Rail | C21: Rail - Freight | D21: =Assumptions!$E$29 -> 0 | E21: ='NonRoad Avg'!$D$13 -> 19501752 | F21: =E21*(1+$D21) -> 19501752 | G21: =F21*(1+$D21) -> 19501752 | H21: =G21*(1+$D21) -> 19501752 | I21: =H21*(1+$D21) -> 19501752 | J21: =I21*(1+$D21) -> 19501752 | K21: =J21*(1+$D21) -> 19501752 | L21: =K21*(1+$D21) -> 19501752 | M21: =L21*(1+$D21) -> 19501752 | ... AG21: =AF21*(1+$D21) -> 19501752
A23: B. Nominal R$ (real x inflation index) | D23: R$ per vehicle
A24: 1 | B24: Road | C24: Road - Passenger LDV | E24: =E10*E$7 -> 427911.79 | F24: =F10*F$7 -> 447681.31 | G24: =G10*G$7 -> 469304.32 | H24: =H10*H$7 -> 489296.68 | I24: =I10*I$7 -> 509945 | J24: =J10*J$7 -> 525243.35 | K24: =K10*K$7 -> 541000.66 | L24: =L10*L$7 -> 557230.68 | ... AG24: =AG10*AG$7 -> 1036613.2
A25: 2 | B25: Road | C25: Road - Passenger HDV | E25: =E11*E$7 -> 298836.74 | F25: =F11*F$7 -> 312643 | G25: =G11*G$7 -> 327743.66 | H25: =H11*H$7 -> 341705.54 | I25: =I11*I$7 -> 356125.51 | J25: =J11*J$7 -> 366809.28 | K25: =K11*K$7 -> 377813.56 | L25: =L11*L$7 -> 389147.96 | ... AG25: =AG11*AG$7 -> 723929.84
A26: 3 | B26: Road | C26: Road - Freight LDV | E26: =E12*E$7 -> 212826.35 | F26: =F12*F$7 -> 222658.92 | G26: =G12*G$7 -> 233413.35 | H26: =H12*H$7 -> 243356.76 | I26: =I12*I$7 -> 253626.41 | J26: =J12*J$7 -> 261235.21 | K26: =K12*K$7 -> 269072.26 | L26: =L12*L$7 -> 277144.43 | ... AG26: =AG12*AG$7 -> 515570.28
A27: 4 | B27: Road | C27: Road - Freight HDV | E27: =E13*E$7 -> 295851.61 | F27: =F13*F$7 -> 309519.96 | G27: =G13*G$7 -> 324469.77 | H27: =H13*H$7 -> 338292.18 | I27: =I13*I$7 -> 352568.11 | J27: =J13*J$7 -> 363145.16 | K27: =K13*K$7 -> 374039.51 | L27: =L13*L$7 -> 385260.7 | ... AG27: =AG13*AG$7 -> 716698.38
A28: 5 | B28: Motorbike | C28: Motorbike - Passenger | E28: =E14*E$7 -> 11475.445 | F28: =F14*F$7 -> 12005.61 | G28: =G14*G$7 -> 12585.481 | H28: =H14*H$7 -> 13121.623 | I28: =I14*I$7 -> 13675.355 | J28: =J14*J$7 -> 14085.616 | K28: =K14*K$7 -> 14508.184 | L28: =L14*L$7 -> 14943.43 | ... AG28: =AG14*AG$7 -> 27799.182
A29: 6 | B29: Motorbike | C29: Motorbike - Freight | E29: =E15*E$7 -> 12587.82 | F29: =F15*F$7 -> 13169.377 | G29: =G15*G$7 -> 13805.458 | H29: =H15*H$7 -> 14393.571 | I29: =I15*I$7 -> 15000.979 | J29: =J15*J$7 -> 15451.009 | K29: =K15*K$7 -> 15914.539 | L29: =L15*L$7 -> 16391.975 | ... AG29: =AG15*AG$7 -> 30493.903
A30: 7 | B30: Aircraft | C30: Aircraft - Passenger | E30: =E16*E$7 -> 2.2354408e+08 | F30: =F16*F$7 -> 2.3387182e+08 | G30: =G16*G$7 -> 2.4516783e+08 | H30: =H16*H$7 -> 2.5561198e+08 | I30: =I16*I$7 -> 2.663988e+08 | J30: =J16*J$7 -> 2.7439076e+08 | K30: =K16*K$7 -> 2.8262249e+08 | L30: =L16*L$7 -> 2.9110116e+08 | ... AG30: =AG16*AG$7 -> 5.4153391e+08
A31: 8 | B31: Aircraft | C31: Aircraft - Freight | E31: =E17*E$7 -> 1.1367651e+08 | F31: =F17*F$7 -> 1.1892837e+08 | G31: =G17*G$7 -> 1.2467261e+08 | H31: =H17*H$7 -> 1.2998366e+08 | I31: =I17*I$7 -> 1.3546897e+08 | J31: =J17*J$7 -> 1.3953304e+08 | K31: =K17*K$7 -> 1.4371903e+08 | L31: =L17*L$7 -> 1.480306e+08 | ... AG31: =AG17*AG$7 -> 2.7538053e+08
A32: 9 | B32: Ship | C32: Ship - Passenger | E32: =E18*E$7 -> 75018509 | F32: =F18*F$7 -> 78484364 | G32: =G18*G$7 -> 82275159 | H32: =H18*H$7 -> 85780081 | I32: =I18*I$7 -> 89400000 | J32: =J18*J$7 -> 92082000 | K32: =K18*K$7 -> 94844460 | L32: =L18*L$7 -> 97689794 | ... AG32: =AG18*AG$7 -> 1.8173179e+08
A33: 10 | B33: Ship | C33: Ship - Freight | E33: =E19*E$7 -> 4.0037794e+08 | F33: =F19*F$7 -> 4.188754e+08 | G33: =G19*G$7 -> 4.3910708e+08 | H33: =H19*H$7 -> 4.5781304e+08 | I33: =I19*I$7 -> 4.7713275e+08 | J33: =J19*J$7 -> 4.9144674e+08 | K33: =K19*K$7 -> 5.0619014e+08 | L33: =L19*L$7 -> 5.2137584e+08 | ... AG33: =AG19*AG$7 -> 9.6991265e+08
A34: 11 | B34: Rail | C34: Rail - Passenger | E34: =E20*E$7 -> 64329558 | F34: =F20*F$7 -> 67301584 | G34: =G20*G$7 -> 70552250 | H34: =H20*H$7 -> 73557776 | I34: =I20*I$7 -> 76661914 | J34: =J20*J$7 -> 78961771 | K34: =K20*K$7 -> 81330625 | L34: =L20*L$7 -> 83770543 | ... AG34: =AG20*AG$7 -> 1.5583789e+08
A35: 12 | B35: Rail | C35: Rail - Freight | E35: =E21*E$7 -> 19501752 | F35: =F21*F$7 -> 20402733 | G35: =G21*G$7 -> 21388185 | H35: =H21*H$7 -> 22299321 | I35: =I21*I$7 -> 23240353 | J35: =J21*J$7 -> 23937563 | K35: =K21*K$7 -> 24655690 | L35: =L21*L$7 -> 25395361 | ... AG35: =AG21*AG$7 -> 47242852
A37: C. Constant 2022 US$ (real R$ / 2022 avg PTAX) | D37: US$ per vehicle
A38: 1 | B38: Road | C38: Road - Passenger LDV | E38: =E10/Assumptions!$B$12 -> 82852.105 | F38: =F10/Assumptions!$B$12 -> 82852.105 | G38: =G10/Assumptions!$B$12 -> 82852.105 | H38: =H10/Assumptions!$B$12 -> 82852.105 | I38: =I10/Assumptions!$B$12 -> 82852.105 | J38: =J10/Assumptions!$B$12 -> 82852.105 | K38: =K10/Assumptions!$B$12 -> 82852.105 | L38: =L10/Assumptions!$B$12 -> 82852.105 | ... AG38: =AG10/Assumptions!$B$12 -> 82852.105
A39: 2 | B39: Road | C39: Road - Passenger HDV | E39: =E11/Assumptions!$B$12 -> 57860.648 | F39: =F11/Assumptions!$B$12 -> 57860.648 | G39: =G11/Assumptions!$B$12 -> 57860.648 | H39: =H11/Assumptions!$B$12 -> 57860.648 | I39: =I11/Assumptions!$B$12 -> 57860.648 | J39: =J11/Assumptions!$B$12 -> 57860.648 | K39: =K11/Assumptions!$B$12 -> 57860.648 | L39: =L11/Assumptions!$B$12 -> 57860.648 | ... AG39: =AG11/Assumptions!$B$12 -> 57860.648
A40: 3 | B40: Road | C40: Road - Freight LDV | E40: =E12/Assumptions!$B$12 -> 41207.35 | F40: =F12/Assumptions!$B$12 -> 41207.35 | G40: =G12/Assumptions!$B$12 -> 41207.35 | H40: =H12/Assumptions!$B$12 -> 41207.35 | I40: =I12/Assumptions!$B$12 -> 41207.35 | J40: =J12/Assumptions!$B$12 -> 41207.35 | K40: =K12/Assumptions!$B$12 -> 41207.35 | L40: =L12/Assumptions!$B$12 -> 41207.35 | ... AG40: =AG12/Assumptions!$B$12 -> 41207.35
A41: 4 | B41: Road | C41: Road - Freight HDV | E41: =E13/Assumptions!$B$12 -> 57282.668 | F41: =F13/Assumptions!$B$12 -> 57282.668 | G41: =G13/Assumptions!$B$12 -> 57282.668 | H41: =H13/Assumptions!$B$12 -> 57282.668 | I41: =I13/Assumptions!$B$12 -> 57282.668 | J41: =J13/Assumptions!$B$12 -> 57282.668 | K41: =K13/Assumptions!$B$12 -> 57282.668 | L41: =L13/Assumptions!$B$12 -> 57282.668 | ... AG41: =AG13/Assumptions!$B$12 -> 57282.668
A42: 5 | B42: Motorbike | C42: Motorbike - Passenger | E42: =E14/Assumptions!$B$12 -> 2221.8709 | F42: =F14/Assumptions!$B$12 -> 2221.8709 | G42: =G14/Assumptions!$B$12 -> 2221.8709 | H42: =H14/Assumptions!$B$12 -> 2221.8709 | I42: =I14/Assumptions!$B$12 -> 2221.8709 | J42: =J14/Assumptions!$B$12 -> 2221.8709 | K42: =K14/Assumptions!$B$12 -> 2221.8709 | L42: =L14/Assumptions!$B$12 -> 2221.8709 | ... AG42: =AG14/Assumptions!$B$12 -> 2221.8709
A43: 6 | B43: Motorbike | C43: Motorbike - Freight | E43: =E15/Assumptions!$B$12 -> 2437.2485 | F43: =F15/Assumptions!$B$12 -> 2437.2485 | G43: =G15/Assumptions!$B$12 -> 2437.2485 | H43: =H15/Assumptions!$B$12 -> 2437.2485 | I43: =I15/Assumptions!$B$12 -> 2437.2485 | J43: =J15/Assumptions!$B$12 -> 2437.2485 | K43: =K15/Assumptions!$B$12 -> 2437.2485 | L43: =L15/Assumptions!$B$12 -> 2437.2485 | ... AG43: =AG15/Assumptions!$B$12 -> 2437.2485
A44: 7 | B44: Aircraft | C44: Aircraft - Passenger | E44: =E16/Assumptions!$B$12 -> 43282513 | F44: =F16/Assumptions!$B$12 -> 43282513 | G44: =G16/Assumptions!$B$12 -> 43282513 | H44: =H16/Assumptions!$B$12 -> 43282513 | I44: =I16/Assumptions!$B$12 -> 43282513 | J44: =J16/Assumptions!$B$12 -> 43282513 | K44: =K16/Assumptions!$B$12 -> 43282513 | L44: =L16/Assumptions!$B$12 -> 43282513 | ... AG44: =AG16/Assumptions!$B$12 -> 43282513
A45: 8 | B45: Aircraft | C45: Aircraft - Freight | E45: =E17/Assumptions!$B$12 -> 22010000 | F45: =F17/Assumptions!$B$12 -> 22010000 | G45: =G17/Assumptions!$B$12 -> 22010000 | H45: =H17/Assumptions!$B$12 -> 22010000 | I45: =I17/Assumptions!$B$12 -> 22010000 | J45: =J17/Assumptions!$B$12 -> 22010000 | K45: =K17/Assumptions!$B$12 -> 22010000 | L45: =L17/Assumptions!$B$12 -> 22010000 | ... AG45: =AG17/Assumptions!$B$12 -> 22010000
A46: 9 | B46: Ship | C46: Ship - Passenger | E46: =E18/Assumptions!$B$12 -> 14525053 | F46: =F18/Assumptions!$B$12 -> 14525053 | G46: =G18/Assumptions!$B$12 -> 14525053 | H46: =H18/Assumptions!$B$12 -> 14525053 | I46: =I18/Assumptions!$B$12 -> 14525053 | J46: =J18/Assumptions!$B$12 -> 14525053 | K46: =K18/Assumptions!$B$12 -> 14525053 | L46: =L18/Assumptions!$B$12 -> 14525053 | ... AG46: =AG18/Assumptions!$B$12 -> 14525053
A47: 10 | B47: Ship | C47: Ship - Freight | E47: =E19/Assumptions!$B$12 -> 77521012 | F47: =F19/Assumptions!$B$12 -> 77521012 | G47: =G19/Assumptions!$B$12 -> 77521012 | H47: =H19/Assumptions!$B$12 -> 77521012 | I47: =I19/Assumptions!$B$12 -> 77521012 | J47: =J19/Assumptions!$B$12 -> 77521012 | K47: =K19/Assumptions!$B$12 -> 77521012 | L47: =L19/Assumptions!$B$12 -> 77521012 | ... AG47: =AG19/Assumptions!$B$12 -> 77521012
A48: 11 | B48: Rail | C48: Rail - Passenger | E48: =E20/Assumptions!$B$12 -> 12455463 | F48: =F20/Assumptions!$B$12 -> 12455463 | G48: =G20/Assumptions!$B$12 -> 12455463 | H48: =H20/Assumptions!$B$12 -> 12455463 | I48: =I20/Assumptions!$B$12 -> 12455463 | J48: =J20/Assumptions!$B$12 -> 12455463 | K48: =K20/Assumptions!$B$12 -> 12455463 | L48: =L20/Assumptions!$B$12 -> 12455463 | ... AG48: =AG20/Assumptions!$B$12 -> 12455463
A49: 12 | B49: Rail | C49: Rail - Freight | E49: =E21/Assumptions!$B$12 -> 3775921.1 | F49: =F21/Assumptions!$B$12 -> 3775921.1 | G49: =G21/Assumptions!$B$12 -> 3775921.1 | H49: =H21/Assumptions!$B$12 -> 3775921.1 | I49: =I21/Assumptions!$B$12 -> 3775921.1 | J49: =J21/Assumptions!$B$12 -> 3775921.1 | K49: =K21/Assumptions!$B$12 -> 3775921.1 | L49: =L21/Assumptions!$B$12 -> 3775921.1 | ... AG49: =AG21/Assumptions!$B$12 -> 3775921.1

Sheet Fuel Evidence
A1: Evidence for prices of fuels not present in the FIPE file (Brazil)
A2: Blue = figure from the source. Column J is the value used by Fuel_Price (in constant 2022 terms). Sourced items feed Fuel Price; everything else on that sheet is flagged as an analyst assumption.
A5: ID | B5: Item | C5: Fuel | D5: Used for | E5: Metric | F5: Currency | G5: Value (native) | H5: Price year | I5: Factor to 2022 prices | J5: Value used (2022 terms) | K5: Note | L5: Source | M5: URL
A6: EV-1 | B6: BEV car on sale in Brazil: Renault Kwid E-Tech | C6: BEV | D6: Passenger LDV BEV | E6: Absolute price (list) | F6: BRL | G6: 99990 | H6: 2024 | I6: {=INDEX(Macro!$Q$6:$Q$17,MATCH($H6,Macro!$K$6:$K$17,0))} -> 0.91180023 | J6: =$G6*$I6 -> 91170.905 | K6: One of the 10 cheapest BEVs, Feb-2024. The list excludes premium BEVs, so the average understates the average BEV price. | L6: Bloomberg Linea, 29-Feb-2024 | M6: https://www.bloomberglinea.com.br/2024/02/29/carros-eletricos-conheca-quais-sao-os-10-mais-baratos-no-brasil/
A7: EV-2 | B7: BEV car on sale in Brazil: BYD Dolphin | C7: BEV | D7: Passenger LDV BEV | E7: Absolute price (list) | F7: BRL | G7: 115800 | H7: 2024 | I7: {=INDEX(Macro!$Q$6:$Q$17,MATCH($H7,Macro!$K$6:$K$17,0))} -> 0.91180023 | J7: =$G7*$I7 -> 105586.47 | L7: Bloomberg Linea, 29-Feb-2024 | M7: https://www.bloomberglinea.com.br/2024/02/29/carros-eletricos-conheca-quais-sao-os-10-mais-baratos-no-brasil/
A8: EV-3 | B8: BEV car on sale in Brazil: Caoa Chery iCar | C8: BEV | D8: Passenger LDV BEV | E8: Absolute price (list) | F8: BRL | G8: 119990 | H8: 2024 | I8: {=INDEX(Macro!$Q$6:$Q$17,MATCH($H8,Macro!$K$6:$K$17,0))} -> 0.91180023 | J8: =$G8*$I8 -> 109406.91 | L8: Bloomberg Linea, 29-Feb-2024 | M8: https://www.bloomberglinea.com.br/2024/02/29/carros-eletricos-conheca-quais-sao-os-10-mais-baratos-no-brasil/
A9: EV-4 | B9: BEV car on sale in Brazil: JAC e-JS1 | C9: BEV | D9: Passenger LDV BEV | E9: Absolute price (list) | F9: BRL | G9: 126900 | H9: 2024 | I9: {=INDEX(Macro!$Q$6:$Q$17,MATCH($H9,Macro!$K$6:$K$17,0))} -> 0.91180023 | J9: =$G9*$I9 -> 115707.45 | L9: Bloomberg Linea, 29-Feb-2024 | M9: https://www.bloomberglinea.com.br/2024/02/29/carros-eletricos-conheca-quais-sao-os-10-mais-baratos-no-brasil/
A10: EV-5 | B10: BEV car on sale in Brazil: GWM Ora 03 | C10: BEV | D10: Passenger LDV BEV | E10: Absolute price (list) | F10: BRL | G10: 150000 | H10: 2024 | I10: {=INDEX(Macro!$Q$6:$Q$17,MATCH($H10,Macro!$K$6:$K$17,0))} -> 0.91180023 | J10: =$G10*$I10 -> 136770.03 | L10: Bloomberg Linea, 29-Feb-2024 | M10: https://www.bloomberglinea.com.br/2024/02/29/carros-eletricos-conheca-quais-sao-os-10-mais-baratos-no-brasil/
A11: EV-6 | B11: BEV car on sale in Brazil: Peugeot e-2008 | C11: BEV | D11: Passenger LDV BEV | E11: Absolute price (list) | F11: BRL | G11: 169990 | H11: 2024 | I11: {=INDEX(Macro!$Q$6:$Q$17,MATCH($H11,Macro!$K$6:$K$17,0))} -> 0.91180023 | J11: =$G11*$I11 -> 154996.92 | L11: Bloomberg Linea, 29-Feb-2024 | M11: https://www.bloomberglinea.com.br/2024/02/29/carros-eletricos-conheca-quais-sao-os-10-mais-baratos-no-brasil/
A12: EV-7 | B12: BEV car on sale in Brazil: Hyundai Kona EV | C12: BEV | D12: Passenger LDV BEV | E12: Absolute price (list) | F12: BRL | G12: 189990 | H12: 2024 | I12: {=INDEX(Macro!$Q$6:$Q$17,MATCH($H12,Macro!$K$6:$K$17,0))} -> 0.91180023 | J12: =$G12*$I12 -> 173232.93 | L12: Bloomberg Linea, 29-Feb-2024 | M12: https://www.bloomberglinea.com.br/2024/02/29/carros-eletricos-conheca-quais-sao-os-10-mais-baratos-no-brasil/
A13: EV-8 | B13: BEV car on sale in Brazil: SERES 3 | C13: BEV | D13: Passenger LDV BEV | E13: Absolute price (list) | F13: BRL | G13: 199990 | H13: 2024 | I13: {=INDEX(Macro!$Q$6:$Q$17,MATCH($H13,Macro!$K$6:$K$17,0))} -> 0.91180023 | J13: =$G13*$I13 -> 182350.93 | L13: Bloomberg Linea, 29-Feb-2024 | M13: https://www.bloomberglinea.com.br/2024/02/29/carros-eletricos-conheca-quais-sao-os-10-mais-baratos-no-brasil/
A14: EV-9 | B14: BEV car on sale in Brazil: Fiat 500e | C14: BEV | D14: Passenger LDV BEV | E14: Absolute price (list) | F14: BRL | G14: 214990 | H14: 2024 | I14: {=INDEX(Macro!$Q$6:$Q$17,MATCH($H14,Macro!$K$6:$K$17,0))} -> 0.91180023 | J14: =$G14*$I14 -> 196027.93 | L14: Bloomberg Linea, 29-Feb-2024 | M14: https://www.bloomberglinea.com.br/2024/02/29/carros-eletricos-conheca-quais-sao-os-10-mais-baratos-no-brasil/
A15: EV-10 | B15: BEV car on sale in Brazil: JAC E-JS4 | C15: BEV | D15: Passenger LDV BEV | E15: Absolute price (list) | F15: BRL | G15: 229900 | H15: 2024 | I15: {=INDEX(Macro!$Q$6:$Q$17,MATCH($H15,Macro!$K$6:$K$17,0))} -> 0.91180023 | J15: =$G15*$I15 -> 209622.87 | L15: Bloomberg Linea, 29-Feb-2024 | M15: https://www.bloomberglinea.com.br/2024/02/29/carros-eletricos-conheca-quais-sao-os-10-mais-baratos-no-brasil/
A16: EV-AVG | B16: Average BEV car price (10 models), constant 2022 R$ | C16: BEV | D16: Passenger LDV BEV | E16: Derived | J16: =AVERAGE(J6:J15) -> 147487.33
A17: NG-1 | B17: Fifth-generation NGV kit, installed and legalised (light vehicles) | C17: NGV | D17: NGV additive for Passenger LDV and Freight LDV | E17: Additive cost per vehicle | F17: BRL | G17: 5000 | H17: 2022 | I17: {=INDEX(Macro!$Q$6:$Q$17,MATCH($H17,Macro!$K$6:$K$17,0))} -> 1 | J17: =$G17*$I17 -> 5000 | K17: Brazil has no factory NGV cars: gas is added by retrofit. Other sources quote R$ 3,000-7,000. | L17: Autopapo (F. Calmon), 1-Apr-2022 | M17: https://autopapo.com.br/noticia/quando-vale-a-pena-instalar-o-kit-gnv-e-quais-sao-os-custos/
A18: BUS-1 | B18: Electric bus purchase price vs diesel bus (capex ratio) | C18: BEV | D18: BEV multiplier for Passenger HDV and (proxy) Freight HDV | E18: Multiplier vs diesel | F18: - | G18: 3 | H18: 2026 | J18: =$G18 -> 3 | K18: Article states the purchase cost of an electric bus is about three times that of a diesel bus (SPTrans-based data). Applied to Freight HDV as a proxy. | L18: Diario do Transporte, 6-Jan-2026 | M18: https://diariodotransporte.com.br/2026/01/06/exclusivo-avanco-em-eletrificacao-poderia-resultar-em-tarifas-e-subsidios-menores-em-sao-paulo-em-medio-prazo-operacao-de-onibus-eletrico-natalino-saiu-65-mais-barata/
A19: TRK-1 | B19: VW e-Delivery electric truck (10.7 t GVW), launch price (memo) | C19: BEV | D19: Cross-check only (not used) | E19: Absolute price | F19: BRL | G19: 800000 | H19: 2021 | I19: {=INDEX(Macro!$Q$6:$Q$17,MATCH($H19,Macro!$K$6:$K$17,0))} -> 1.0578 | J19: =$G19*$I19 -> 846240 | K19: Headline price at launch; year inferred from the Jul-2021 launch. Much heavier than the Freight HDV vehicles in FIPE, so not used directly. | L19: Autoo | M19: https://www.autoo.com.br/primeiro-volkswagen-eletrico-do-brasil-e-caminhao-de-r-800-mil/
A20: MB-EV1 | B20: Voltz EV1 Sport electric scooter (2022 model), FIPE value May-2022 | C20: BEV | D20: Motorbike - Passenger BEV | E20: Absolute price (FIPE) | F20: BRL | G20: 16014 | H20: 2022 | I20: {=INDEX(Macro!$Q$6:$Q$17,MATCH($H20,Macro!$K$6:$K$17,0))} -> 1 | J20: =$G20*$I20 -> 16014 | K20: Best-selling electric motorbike in Brazil in 2022 (Fenabrave). First FIPE value shown for the 2022 model. | L20: Tabela FIPE Brasil - Voltz EV1 2022 | M20: https://www.tabelafipebrasil.com/motos/VOLTZ/EV1-SPORT-3000W-ELETRICA/2022
A21: H2-1 | B21: Toyota Mirai fuel-cell sedan (US market price, as shown in Brazil in 2022) | C21: Hydrogen | D21: Numerator of the hydrogen car premium | E21: Absolute price | F21: USD | G21: 49500 | H21: 2022 | J21: =$G21 -> 49500 | K21: Never sold in Brazil (presented in 2022 only). International price used because no Brazilian price exists. | L21: Eixos - Carros a hidrogenio fazem sentido para o Brasil? | M21: https://eixos.com.br/hidrogenio/carros-a-hidrogenio-fazem-sentido-para-o-brasil/
A22: H2-2 | B22: Toyota Corolla hybrid (US market price, same article) | C22: Hydrogen | D22: Denominator of the hydrogen car premium | E22: Absolute price | F22: USD | G22: 24050 | H22: 2022 | J22: =$G22 -> 24050 | K22: Comparator used by the article: the Mirai costs about twice as much. | L22: Eixos - Carros a hidrogenio fazem sentido para o Brasil? | M22: https://eixos.com.br/hidrogenio/carros-a-hidrogenio-fazem-sentido-para-o-brasil/
A23: H2-X | B23: Hydrogen car price premium (Mirai / Corolla hybrid) | C23: Hydrogen | D23: Hydrogen multiplier for Passenger LDV and (proxy) Freight LDV | E23: Multiplier | J23: =G21/G22 -> 2.0582121
A24: PAIR-1 | B24: Renault Kwid E-Tech (BEV) list price | C24: BEV | D24: Like-for-like BEV premium (Freight LDV proxy) | E24: Absolute price (list) | F24: BRL | G24: 99990 | H24: 2024 | I24: {=INDEX(Macro!$Q$6:$Q$17,MATCH($H24,Macro!$K$6:$K$17,0))} -> 0.91180023 | J24: =$G24*$I24 -> 91170.905 | L24: Bloomberg Linea, 29-Feb-2024 | M24: https://www.bloomberglinea.com.br/2024/02/29/carros-eletricos-conheca-quais-sao-os-10-mais-baratos-no-brasil/
A25: PAIR-1a | B25: FIPE 2022 average of the ICE Kwid (from your file) | C25: Gasoline | E25: Average price (FIPE) | F25: BRL | G25: =IFERROR(AVERAGEIFS('Vehicle Price'!$K$2:$K$11633,'Vehicle Price'!$E$2:$E$11633,"Renault",'Vehicle Price'!$F$2:$F$11633,"*KWID*"),"n/a") -> 63711.819 | H25: 2022 | J25: =G25 -> 63711.819 | K25: Kwid 1.0 Flex versions in the FIPE file.
A26: PAIR-1b | B26: BEV / ICE price ratio, Kwid (both in 2022 R$) | E26: Ratio | J26: =J24/J25 -> 1.4309889
